Workbook

Sheet People
A1: Id | B1: Name | C1: DisplayName | D1: Dob | E1: GenderId | F1: IsFamilyHead | G1: FamilyHead
A2: 1 | B2: Arun Venkatesan | C2: Arun | D2: 31092 | E2: 1 | F2: TRUE
A3: 2 | B3: Kurinji Malar Paranthaman | C3: Kurinji | D3: 33526 | E3: 2 | G3: Arun Venkatesan
A4: 3 | B4: Aarna Arun | C4: Aarna | D4: 42978 | E4: 2 | G4: Arun Venkatesan
A5: 4 | B5: Aadhav Arun | C5: Aadhav | D5: 44127 | E5: 1 | G5: Arun Venkatesan

Sheet Equity
A1: ISIN | B1: Company | C1: NSE Symbol | D1: BSE Code | E1: Incorporation Date | F1: ISIN Creation Date
A2: INE238A01034 | B2: Axis Bank Ltd | C2: AXISBANK | D2: 532215 | E2: 03-Dec-1993
A3: INE457A01014 | B3: Bank of Maharashtra | C3: MAHABANK | D3: 532525 | E3: 16-Sep-1935
A4: INE323A01026 | B4: Bosch Ltd | C4: BOSCHLTD | D4: 500530 | E4: 12-Nov-1951
A5: INE925R01014 | B5: CMS Info Systems Ltd | C5: CMSINFO | D5: 543441 | E5: 26-Mar-2008
A6: INE335K01011 | B6: Coffee Day Enterprises Ltd | C6: COFFEEDAY | D6: 539436 | E6: 20-Jun-2008
A7: INE0KL801015 | B7: DCX System Ltd | C7: DCXINDIA | D7: 543650 | E7: 16-Dec-2011 | F7: 44876
A8: INE129A01019 | B8: GAIL (INDIA) Ltd | C8: GAIL | D8: 532155 | E8: 16-Aug-1984
A9: INE040A01034 | B9: HDFC Bank Ltd | C9: HDFCBANK | D9: 500180 | E9: 30-Aug-1994 | F9: 34845
A10: INE090A01021 | B10: ICICI Bank Ltd | C10: ICICIBANK | D10: 532174 | E10: 05-Jan-1994
A11: INE092T01019 | B11: IDFC First Bank Ltd | C11: IDFCFIRSTB | D11: 539437 | E11: 21-Oct-2014
A12: INE562A01011 | B12: Indian Bank | C12: INDIANB | D12: 532814 | E12: 05-Mar-1907 | F12: 43752
A13: INE053A01029 | B13: Indian Hotels Company Ltd | C13: INDHOTEL | D13: 500850 | E13: 01-Apr-1902 | F13: 44497
A14: INE009A01021 | B14: Infosys Ltd | C14: INFY | D14: 500209 | E14: 02-Jul-1981 | F14: 45686
A15: INE335Y01012 | B15: IRCTC Ltd | C15: IRCTC | D15: 542830 | E15: 27-Sep-1999
A16: INE335Y01020 | B16: IRCTC Ltd | C16: IRCTC | D16: 542830 | E16: 27-Sep-1999
A17: INE379A01028 | B17: ITC Hotels Ltd | C17: ITCHOTELS | D17: 544325 | E17: 28-Jul-2023
A18: INE154A01025 | B18: ITC Ltd | C18: ITC | D18: 500875 | E18: 24-Aug-1910
A19: INE351F01018 | B19: Jaiprakash Power Ventures Ltd | C19: JPPOWER | D19: 532627 | E19: 21-Dec-1994
A20: INE498L01015 | B20: L&T Finance Ltd | C20: L&TFH | D20: 533519 | E20: 01-May-2008
A21: INE018A01030 | B21: Larsen & Tubro Ltd | C21: LT | D21: 500510 | E21: 07-Feb-1946
A22: INE848E01016 | B22: NHPC Ltd | C22: NHPC | D22: 533098 | E22: 07-Nov-1975
A23: INE0LXG01040 | B23: OLA Electric Mobility Ltd | C23: OLA | D23: 544225 | E23: 03-Feb-2017 | F23: 45513
A24: INE1NPP01017 | B24: Siemens Energy India Ltd | C24: ENRIN | D24: 544390 | E24: 07-Feb-2024 | F24: 45827
A25: INE003A01024 | B25: Siemens Ltd | C25: SIEMENS | D25: 505372 | E25: 02-Mar-1957
A26: INE114A01011 | B26: Steel Authority of India Ltd (SAIL) | C26: SAIL | D26: 500113 | E26: 24-Jan-1973
A27: INE040H01021 | B27: Suzlon Engergy Ltd | C27: SUZLON | D27: 532667 | E27: 10-Apr-1995 | F27: 45303
A28: INE155A01022 | B28: Tata Motors Ltd | C28: TATAMOTORS | D28: 500570 | E28: 01-Sep-1945
A29: INE1TAE01010 | B29: Tata Motors Passenger Vehicles Ltd (TMPV) | C29: TMPV | D29: 500570 | E29: 01-Sep-1945 | F29: 45839
A30: INE081A01012 | B30: Tata Steel Ltd | C30: TATASTEEL | D30: 500470 | E30: 26-Aug-1907
A31: INE081A01020 | B31: Tata Steel Ltd | C31: TATASTEEL | D31: 500470 | E31: 26-Aug-1907 | F31: 44770

Sheet Equity Transaction
A1: Person | B1: Account | C1: Trade Date | D1: ISIN | E1: Security | F1: Segment | G1: Action | H1: Quantity | I1: Price/Share | J1: Net Amount | K1: BrokeragePerUnit | L1: NetBrokerage | M1: STT | N1: Stamp Duty | O1: GST | P1: Total Amount
A2: Arun Venkatesan | B2: ICICI | C2: 43949 | D2: INE090A01021 | E2: ICICI BANK LTD. | F2: CASH | G2: Buy | H2: 20 | I2: 353.75 | J2: =H2*I2 -> 7075 | K2: 1.25 | L2: =Table1[[#This Row],[Quantity]]*Table1[[#This Row],[BrokeragePerUnit]] -> 25 | M2: 7 | N2: 0.45 | O2: 4.52 | P2: =Table1[[#This Row],[Net Amount]]+Table1[[#This Row],[NetBrokerage]]+Table1[[#This Row],[STT]]+Table1[[#This Row],[Stamp Duty]]+Table1[[#This Row],[GST]] -> 7111.97
A3: Arun Venkatesan | B3: ICICI | C3: 44018 | D3: INE040A01034 | E3: HDFC BANK LTD | F3: CASH | G3: Buy | H3: 10 | I3: 1100 | J3: =H3*I3 -> 11000 | K3: 6.05 | L3: =Table1[[#This Row],[Quantity]]*Table1[[#This Row],[BrokeragePerUnit]] -> 60.5 | M3: 11 | N3: 2 | O3: 10.95 | P3: =Table1[[#This Row],[Net Amount]]+Table1[[#This Row],[NetBrokerage]]+Table1[[#This Row],[STT]]+Table1[[#This Row],[Stamp Duty]]+Table1[[#This Row],[GST]] -> 11084.45
A4: Arun Venkatesan | B4: ICICI | C4: 44550 | D4: INE562A01011 | E4: INDIAN BANK | F4: CASH | G4: Buy | H4: 62 | I4: 136.45 | J4: =H4*I4 -> 8459.9 | K4: 0.75 | L4: =Table1[[#This Row],[Quantity]]*Table1[[#This Row],[BrokeragePerUnit]] -> 46.5 | M4: 0 | N4: 0 | O4: 0 | P4: =Table1[[#This Row],[Net Amount]]+Table1[[#This Row],[NetBrokerage]]+Table1[[#This Row],[STT]]+Table1[[#This Row],[Stamp Duty]]+Table1[[#This Row],[GST]] -> 8506.4
A5: Arun Venkatesan | B5: ICICI | C5: 44550 | D5: INE562A01011 | E5: INDIAN BANK | F5: CASH | G5: Buy | H5: 38 | I5: 136.45 | J5: =H5*I5 -> 5185.1 | K5: 0.75 | L5: =Table1[[#This Row],[Quantity]]*Table1[[#This Row],[BrokeragePerUnit]] -> 28.5 | M5: 13.99 | N5: 2 | O5: 13.55 | P5: =Table1[[#This Row],[Net Amount]]+Table1[[#This Row],[NetBrokerage]]+Table1[[#This Row],[STT]]+Table1[[#This Row],[Stamp Duty]]+Table1[[#This Row],[GST]] -> 5243.14
A6: Arun Venkatesan | B6: ICICI | C6: 44553 | D6: INE040A01034 | E6: HDFC BANK LTD | F6: CASH | G6: Buy | H6: 10 | I6: 1450 | J6: =H6*I6 -> 14500 | K6: 7.97 | L6: =Table1[[#This Row],[Quantity]]*Table1[[#This Row],[BrokeragePerUnit]] -> 79.7 | M6: 14.4 | N6: 2.18 | O6: 14.4 | P6: =Table1[[#This Row],[Net Amount]]+Table1[[#This Row],[NetBrokerage]]+Table1[[#This Row],[STT]]+Table1[[#This Row],[Stamp Duty]]+Table1[[#This Row],[GST]] -> 14610.68
A7: Arun Venkatesan | B7: ICICI | C7: 44553 | D7: INE090A01021 | E7: ICICI BANK LTD. | F7: CASH | G7: Buy | H7: 20 | I7: 730 | J7: =H7*I7 -> 14600 | K7: 4.015 | L7: =Table1[[#This Row],[Quantity]]*Table1[[#This Row],[BrokeragePerUnit]] -> 80.3 | M7: 14.6 | N7: 1.82 | O7: 14.5 | P7: =Table1[[#This Row],[Net Amount]]+Table1[[#This Row],[NetBrokerage]]+Table1[[#This Row],[STT]]+Table1[[#This Row],[Stamp Duty]]+Table1[[#This Row],[GST]] -> 14711.22
A8: Arun Venkatesan | B8: ICICI | C8: 44559 | D8: INE925R01014 | E8: CMS INFO SYSTEMS LIMITED | F8: CASH | G8: IPO | H8: 69 | I8: 216 | J8: =H8*I8 -> 14904 | L8: =H8*K8 -> 0 | P8: =J8+L8 -> 14904
A9: Arun Venkatesan | B9: ICICI | C9: 44880 | D9: INE040A01034 | E9: HDFC BANK LTD | F9: CASH | G9: Buy | H9: 20 | I9: 1608.7 | J9: =H9*I9 -> 32174 | K9: 3.5 | L9: =Table1[[#This Row],[Quantity]]*Table1[[#This Row],[BrokeragePerUnit]] -> 70 | M9: 32.17 | N9: 5.28 | O9: 12.93 | P9: =Table1[[#This Row],[Net Amount]]+Table1[[#This Row],[NetBrokerage]]+Table1[[#This Row],[STT]]+Table1[[#This Row],[Stamp Duty]]+Table1[[#This Row],[GST]] -> 32294.38
A10: Arun Venkatesan | B10: ICICI | C10: 44880 | D10: INE090A01021 | E10: ICICI BANK LTD. | F10: CASH | G10: Buy | H10: 20 | I10: 906.5 | J10: =H10*I10 -> 18130 | K10: 1.99 | L10: =Table1[[#This Row],[Quantity]]*Table1[[#This Row],[BrokeragePerUnit]] -> 39.8 | M10: 17.82 | N10: 2.72 | O10: 7.28 | P10: =Table1[[#This Row],[Net Amount]]+Table1[[#This Row],[NetBrokerage]]+Table1[[#This Row],[STT]]+Table1[[#This Row],[Stamp Duty]]+Table1[[#This Row],[GST]] -> 18197.62
A11: Arun Venkatesan | B11: ICICI | C11: 44880 | D11: INE848E01016 | E11: NHPC LTD | F11: CASH | G11: Buy | H11: 1 | I11: 43.8 | J11: =H11*I11 -> 43.8 | K11: 0.02 | L11: =Table1[[#This Row],[Quantity]]*Table1[[#This Row],[BrokeragePerUnit]] -> 0.02 | P11: =Table1[[#This Row],[Net Amount]]+Table1[[#This Row],[NetBrokerage]]+Table1[[#This Row],[STT]]+Table1[[#This Row],[Stamp Duty]]+Table1[[#This Row],[GST]] -> 43.82
A12: Arun Venkatesan | B12: ICICI | C12: 44880 | D12: INE848E01016 | E12: NHPC LTD | F12: CASH | G12: Sell | H12: 1 | I12: 43.75 | J12: =H12*I12 -> 43.75 | K12: 0.02 | L12: =Table1[[#This Row],[Quantity]]*Table1[[#This Row],[BrokeragePerUnit]] -> 0.02 | P12: =Table1[[#This Row],[Net Amount]]+Table1[[#This Row],[NetBrokerage]]+Table1[[#This Row],[STT]]+Table1[[#This Row],[Stamp Duty]]+Table1[[#This Row],[GST]] -> 43.77
A13: Arun Venkatesan | B13: ICICI | C13: 44882 | D13: INE090A01021 | E13: ICICI BANK LTD. | F13: CASH | G13: Buy | H13: 20 | I13: 918 | J13: =H13*I13 -> 18360 | K13: 2.01 | L13: =Table1[[#This Row],[Quantity]]*Table1[[#This Row],[BrokeragePerUnit]] -> 40.2 | M13: 18 | N13: 3 | O13: 7.36 | P13: =Table1[[#This Row],[Net Amount]]+Table1[[#This Row],[NetBrokerage]]+Table1[[#This Row],[STT]]+Table1[[#This Row],[Stamp Duty]]+Table1[[#This Row],[GST]] -> 18428.56
A14: Arun Venkatesan | B14: ICICI | C14: 44994 | D14: INE040A01034 | E14: HDFC BANK LTD | F14: CASH | G14: Buy | H14: 30 | I14: 1635 | J14: =H14*I14 -> 49050 | K14: 3.59 | L14: =Table1[[#This Row],[Quantity]]*Table1[[#This Row],[BrokeragePerUnit]] -> 107.7 | M14: 49 | N14: 7 | O14: 19.72 | P14: =Table1[[#This Row],[Net Amount]]+Table1[[#This Row],[NetBrokerage]]+Table1[[#This Row],[STT]]+Table1[[#This Row],[Stamp Duty]]+Table1[[#This Row],[GST]] -> 49233.42
A15: Arun Venkatesan | B15: ICICI | C15: 45021 | D15: INE090A01021 | E15: ICICI BANK LTD. | F15: CASH | G15: Buy | H15: 20 | I15: 880 | J15: =H15*I15 -> 17600 | K15: 1.93 | L15: =Table1[[#This Row],[Quantity]]*Table1[[#This Row],[BrokeragePerUnit]] -> 38.6 | M15: 17.6 | N15: 2.64 | O15: 7.06 | P15: =Table1[[#This Row],[Net Amount]]+Table1[[#This Row],[NetBrokerage]]+Table1[[#This Row],[STT]]+Table1[[#This Row],[Stamp Duty]]+Table1[[#This Row],[GST]] -> 17665.9
A16: Arun Venkatesan | B16: ICICI | C16: 45021 | D16: INE562A01011 | E16: INDIAN BANK | F16: CASH | G16: Buy | H16: 100 | I16: 289.55 | J16: =H16*I16 -> 28955 | K16: 0.63 | L16: =Table1[[#This Row],[Quantity]]*Table1[[#This Row],[BrokeragePerUnit]] -> 63 | M16: 29.39 | N16: 4.36 | O16: 11.61 | P16: =Table1[[#This Row],[Net Amount]]+Table1[[#This Row],[NetBrokerage]]+Table1[[#This Row],[STT]]+Table1[[#This Row],[Stamp Duty]]+Table1[[#This Row],[GST]] -> 29063.36
A17: Arun Venkatesan | B17: ICICI | C17: 45026 | D17: INE040A01034 | E17: HDFC BANK LTD | F17: CASH | G17: Buy | H17: 30 | I17: 1663 | J17: =H17*I17 -> 49890 | K17: 3.65 | L17: =Table1[[#This Row],[Quantity]]*Table1[[#This Row],[BrokeragePerUnit]] -> 109.5 | M17: 50 | N17: 7 | O17: 20.01 | P17: =Table1[[#This Row],[Net Amount]]+Table1[[#This Row],[NetBrokerage]]+Table1[[#This Row],[STT]]+Table1[[#This Row],[Stamp Duty]]+Table1[[#This Row],[GST]] -> 50076.51
A18: Arun Venkatesan | B18: ICICI | C18: 45758 | D18: INE549K07824 | E18: NCD | G18: Sell | H18: 20 | I18: 984 | J18: =H18*I18 -> 19680 | L18: =Table1[[#This Row],[Quantity]]*Table1[[#This Row],[BrokeragePerUnit]] -> 0 | P18: =Table1[[#This Row],[Net Amount]]+Table1[[#This Row],[NetBrokerage]]+Table1[[#This Row],[STT]]+Table1[[#This Row],[Stamp Duty]]+Table1[[#This Row],[GST]] -> 19680
A19: Arun Venkatesan | B19: ICICI | C19: 45758 | D19: INE549K07824 | E19: NCD | G19: Sell | H19: 180 | I19: 984 | J19: =H19*I19 -> 177120 | L19: =Table1[[#This Row],[Quantity]]*Table1[[#This Row],[BrokeragePerUnit]] -> 0 | P19: =Table1[[#This Row],[Net Amount]]+Table1[[#This Row],[NetBrokerage]]+Table1[[#This Row],[STT]]+Table1[[#This Row],[Stamp Duty]]+Table1[[#This Row],[GST]] -> 177120
A20: Arun Venkatesan | B20: ICICI | C20: 45895 | D20: INE040A01034 | E20: HDFC BANK LTD | F20: DIVIDEND | G20: Bonus | H20: 100 | J20: =H20*I20 -> 0 | L20: =H20*K20 -> 0 | P20: =J20+L20 -> 0
A21: Arun Venkatesan | B21: IIFL | C21: 41624 | D21: INE081A01012 | E21: Tata Steel | F21: CASH | G21: BUY | H21: 4 | I21: 410.64 | J21: =H21*I21 -> 1642.56 | P21: 1642.56
A22: Arun Venkatesan | B22: IIFL | C22: 41940 | D22: INE018A01030 | E22: L & T LTD | F22: CASH | G22: BUY | H22: 2 | I22: 1581.45 | J22: =H22*I22 -> 3162.9 | K22: 12.5 | L22: =H22*K22 -> 25 | P22: =J22+L22 -> 3187.9
A23: Arun Venkatesan | B23: IIFL | C23: 41940 | D23: INE498L01015 | E23: L&T FINANCE LTD | F23: CASH | G23: BUY | H23: 50 | I23: 68.7 | J23: =H23*I23 -> 3435 | K23: 0.5 | L23: =H23*K23 -> 25 | P23: =J23+L23 -> 3460
A24: Arun Venkatesan | B24: IIFL | C24: 41940 | D24: INE081A01012 | E24: Tata Steel | F24: CASH | G24: BUY | H24: 10 | I24: 452.7 | J24: =H24*I24 -> 4527 | K24: 2.5 | L24: =H24*K24 -> 25 | P24: =J24+L24 -> 4552
A25: Arun Venkatesan | B25: IIFL | C25: 41942 | D25: INE498L01015 | E25: L&T FINANCE LTD | F25: CASH | G25: BUY | H25: 50 | I25: 68 | J25: =H25*I25 -> 3400 | K25: 0.5 | L25: =H25*K25 -> 25 | P25: =J25+L25 -> 3425
A26: Arun Venkatesan | B26: IIFL | C26: 41960 | D26: INE018A01030 | E26: L & T LTD | F26: CASH | G26: BUY | H26: 2 | I26: 1613.3 | J26: =H26*I26 -> 3226.6 | K26: 12.5 | L26: =H26*K26 -> 25 | P26: =J26+L26 -> 3251.6
A27: Arun Venkatesan | B27: IIFL | C27: 42059 | D27: INE081A01012 | E27: Tata Steel | F27: CASH | G27: BUY | H27: 20 | I27: 360 | J27: =H27*I27 -> 7200 | K27: 1.8 | L27: =H27*K27 -> 36 | P27: =J27+L27 -> 7236
A28: Arun Venkatesan | B28: IIFL | C28: 42065 | D28: INE081A01012 | E28: Tata Steel | F28: CASH | G28: BUY | H28: 20 | I28: 350 | J28: =H28*I28 -> 7000 | K28: 1.75 | L28: =H28*K28 -> 35 | P28: =J28+L28 -> 7035
A29: Arun Venkatesan | B29: IIFL | C29: 42156 | D29: INE018A01030 | E29: L & T LTD | F29: CASH | G29: BUY | H29: 3 | I29: 1700 | J29: =H29*I29 -> 5100 | K29: 8.5 | L29: =H29*K29 -> 25.5 | P29: =J29+L29 -> 5125.5
A30: Arun Venkatesan | B30: IIFL | C30: 42156 | D30: INE018A01030 | E30: L & T LTD | F30: CASH | G30: BUY | H30: 2 | I30: 1700 | J30: =H30*I30 -> 3400 | K30: 8.5 | L30: =H30*K30 -> 17 | P30: =J30+L30 -> 3417
A31: Arun Venkatesan | B31: IIFL | C31: 42167 | D31: INE081A01012 | E31: Tata Steel | F31: CASH | G31: BUY | H31: 30 | I31: 298 | J31: =H31*I31 -> 8940 | K31: 1.49 | L31: =H31*K31 -> 44.7 | P31: =J31+L31 -> 8984.7
A32: Arun Venkatesan | B32: IIFL | C32: 42170 | D32: INE009A01021 | E32: INFY | F32: CASH | G32: BUY | H32: 3 | I32: 992 | J32: =H32*I32 -> 2976 | K32: 4.96 | L32: =H32*K32 -> 14.88 | P32: =J32+L32 -> 2990.88
A33: Arun Venkatesan | B33: IIFL | C33: 42170 | D33: INE009A01021 | E33: INFY | F33: CASH | G33: BUY | H33: 10 | I33: 992 | J33: =H33*I33 -> 9920 | K33: 4.96 | L33: =H33*K33 -> 49.6 | P33: =J33+L33 -> 9969.6
... A42: Arun Venkatesan | B42: IIFL | C42: 42234 | D42: INE081A01012 | E42: Tata Steel | F42: CASH | G42: BUY | H42: 1 | I42: 249 | J42: =H42*I42 -> 249 | K42: 1.56 | L42: =H42*K42 -> 1.56 | P42: =J42+L42 -> 250.56
A43: Arun Venkatesan | B43: IIFL | C43: 42933 | D43: INE018A01030 | E43: L & T LTD | F43: DIVIDEND | G43: Bonus | H43: 4 | J43: =H43*I43 -> 0 | L43: =H43*K43 -> 0 | P43: =J43+L43 -> 0
A44: Arun Venkatesan | B44: IIFL | C44: 43350 | D44: INE009A01021 | E44: INFY | F44: DIVIDEND | G44: Bonus | H44: 53 | J44: =H44*I44 -> 0 | L44: =H44*K44 -> 0 | P44: =J44+L44 -> 0
A45: Arun Venkatesan | B45: IIFL | C45: 43916 | D45: INE003A01024 | E45: SIEMENS | F45: CASH | G45: BUY | H45: 50 | I45: 1085 | J45: =H45*I45 -> 54250 | K45: 5.43 | L45: =H45*K45 -> 271.5 | P45: =J45+L45 -> 54521.5
A46: Arun Venkatesan | B46: IIFL | C46: 43917 | D46: INE323A01026 | E46: BOSCHLTD | F46: CASH | G46: Buy | H46: 6 | I46: 10000 | J46: =H46*I46 -> 60000 | K46: 50 | L46: =H46*K46 -> 300 | P46: =J46+L46 -> 60300
A47: Arun Venkatesan | B47: IIFL | C47: 43917 | D47: INE498L01015 | E47: L&T FINANCE LTD | F47: CASH | G47: Buy | H47: 50 | I47: 55 | J47: =H47*I47 -> 2750 | K47: 0.5 | L47: =H47*K47 -> 25 | P47: =J47+L47 -> 2775
A48: Arun Venkatesan | B48: IIFL | C48: 43917 | D48: INE018A01030 | E48: L & T LTD | F48: CASH | G48: Buy | H48: 30 | I48: 880 | J48: =H48*I48 -> 26400 | K48: 4.4 | L48: =H48*K48 -> 132 | P48: =J48+L48 -> 26532
A49: Arun Venkatesan | B49: IIFL | C49: 44253 | D49: INE498L01015 | E49: L&T FINANCE LTD | F49: CASH | G49: Rights | H49: 34 | I49: 65 | J49: =H49*I49 -> 2210 | L49: =H49*K49 -> 0 | P49: =J49+L49 -> 2210
A50: Arun Venkatesan | B50: IIFL | C50: 44355 | D50: INE155A01022 | E50: TATAMOTORS | F50: CASH | G50: Buy | H50: 50 | I50: 340 | J50: =H50*I50 -> 17000 | K50: 1.7 | L50: =H50*K50 -> 85 | P50: =J50+L50 -> 17085
A51: Arun Venkatesan | B51: IIFL | C51: 44356 | D51: INE335K01011 | E51: COFFEEDAY | F51: CASH | G51: Buy | H51: 200 | I51: 40.5 | J51: =H51*I51 -> 8100 | K51: 0.2 | L51: =H51*K51 -> 40 | P51: =J51+L51 -> 8140
A52: Arun Venkatesan | B52: IIFL | C52: 44356 | D52: INE053A01029 | E52: INDHOTEL | F52: CASH | G52: Buy | H52: 50 | I52: 137.55 | J52: =H52*I52 -> 6877.5 | K52: 0.68 | L52: =H52*K52 -> 34 | P52: =J52+L52 -> 6911.5
A53: Arun Venkatesan | B53: IIFL | C53: 44356 | D53: INE457A01014 | E53: MAHABANK | F53: CASH | G53: Buy | H53: 500 | I53: 26.85 | J53: =H53*I53 -> 13425 | K53: 0.13 | L53: =H53*K53 -> 65 | P53: =J53+L53 -> 13490
A54: Arun Venkatesan | B54: IIFL | C54: 44411 | D54: INE335Y01012 | E54: IRCTC | F54: CASH | G54: Buy | H54: 1 | I54: 2463.2 | J54: =H54*I54 -> 2463.2 | K54: 12.31 | L54: =H54*K54 -> 12.31 | P54: =J54+L54 -> 2475.51
A55: Arun Venkatesan | B55: IIFL | C55: 44411 | D55: INE335Y01012 | E55: IRCTC | F55: CASH | G55: Buy | H55: 19 | I55: 2463.35 | J55: =H55*I55 -> 46803.65 | K55: 12.31 | L55: =H55*K55 -> 233.89 | P55: =J55+L55 -> 47037.54
A56: Arun Venkatesan | B56: IIFL | C56: 44499 | D56: INE335Y01012 | E56: IRCTC | F56: SPLIT | G56: Split | H56: -20 | I56: 0 | J56: =H56*I56 -> 0 | L56: =H56*K56 -> 0 | P56: =J56+L56 -> 0
A57: Arun Venkatesan | B57: IIFL | C57: 44499 | D57: INE335Y01020 | E57: IRCTC | F57: SPLIT | G57: Split | H57: 100 | I57: 0 | J57: =H57*I57 -> 0 | L57: =H57*K57 -> 0 | P57: =J57+L57 -> 0
A58: Arun Venkatesan | B58: IIFL | C58: 44545 | D58: INE053A01029 | E58: INDHOTEL | F58: CASH | G58: Rights | H58: 5 | I58: 150 | J58: =H58*I58 -> 750 | L58: =H58*K58 -> 0 | P58: =J58+L58 -> 750
A59: Arun Venkatesan | B59: IIFL | C59: 45078 | D59: INE009A01021 | E59: INFY | F59: CASH | G59: Buy | H59: 20 | I59: 1325 | J59: =H59*I59 -> 26500 | K59: 6.63 | L59: =H59*K59 -> 132.6 | P59: =J59+L59 -> 26632.6
A60: Arun Venkatesan | B60: IIFL | C60: 44772 | D60: INE081A01012 | E60: Tata Steel | F60: SPLIT | G60: Split | H60: -100 | J60: =H60*I60 -> 0 | L60: =H60*K60 -> 0 | P60: =J60+L60 -> 0
A61: Arun Venkatesan | B61: IIFL | C61: 44772 | D61: INE081A01020 | E61: Tata Steel | F61: SPLIT | G61: Split | H61: 1000 | I61: 0 | J61: 0 | L61: =H61*K61 -> 0 | P61: =J61+L61 -> 0
A62: Arun Venkatesan | B62: IIFL | C62: 45642 | D62: INE335K01011 | E62: COFFEEDAY | F62: CASH | G62: BUY | H62: 500 | I62: 25.15 | J62: =H62*I62 -> 12575 | K62: 0.19 | L62: =H62*K62 -> 95 | P62: =J62+L62 -> 12670
A63: Arun Venkatesan | B63: IIFL | C63: 45644 | D63: INE457A01014 | E63: MAHABANK | F63: CASH | G63: BUY | H63: 100 | I63: 54 | J63: =H63*I63 -> 5400 | K63: 0.27 | L63: =H63*K63 -> 27 | P63: =J63+L63 -> 5427
A64: Arun Venkatesan | B64: IIFL | C64: 45644 | D64: INE018A01030 | E64: L & T LTD | F64: CASH | G64: Buy | H64: 7 | I64: 3776.35 | J64: =H64*I64 -> 26434.45 | K64: 18.88 | L64: =H64*K64 -> 132.16 | P64: =J64+L64 -> 26566.61
A65: Arun Venkatesan | B65: IIFL | C65: 45644 | D65: INE009A01021 | E65: INFY | F65: CASH | G65: Buy | H65: 4 | I65: 1971 | J65: =H65*I65 -> 7884 | K65: 9.85 | L65: =H65*K65 -> 39.4 | P65: =J65+L65 -> 7923.4
A66: Arun Venkatesan | B66: IIFL | C66: 45646 | D66: INE053A01029 | E66: INDHOTEL | F66: CASH | G66: BUY | H66: 5 | I66: 855 | J66: =H66*I66 -> 4275 | K66: 5 | L66: =H66*K66 -> 25 | P66: =J66+L66 -> 4300
A67: Arun Venkatesan | B67: IIFL | C67: 45646 | D67: INE498L01015 | E67: L&T FINANCE LTD | F67: CASH | G67: BUY | H67: 6 | I67: 137 | J67: =H67*I67 -> 822 | K67: 3.42 | L67: =H67*K67 -> 20.52 | P67: =J67+L67 -> 842.52
A68: Arun Venkatesan | B68: IIFL | C68: 45764 | D68: INE1NPP01017 | E68: SIEMENS ENERGY | F68: SPLIT | G68: Split | H68: 50 | I68: 0 | J68: =H68*I68 -> 0 | L68: =H68*K68 -> 0 | P68: =J68+L68 -> 0
A69: Arun Venkatesan | B69: IIFL | C69: 45946 | D69: INE1TAE01010 | E69: Tata Motors Commercial Vehicles | F69: SPLIT | G69: Split | H69: 50 | I69: 0 | J69: =H69*I69 -> 0 | K69: 0 | L69: =H69*K69 -> 0 | P69: =J69+L69 -> 0
A70: Kurinji Malar Paranthaman | B70: ICICI | C70: 44707 | D70: INE090A01021 | E70: ICICI BANK LTD. | F70: CASH | G70: Buy | H70: 2 | I70: 718.95 | J70: =H70*I70 -> 1437.9 | K70: 5.39 | L70: =H70*K70 -> 10.78 | M70: 0 | N70: 0 | O70: 1.94 | P70: =Table1[[#This Row],[Net Amount]]+Table1[[#This Row],[NetBrokerage]]+Table1[[#This Row],[STT]]+Table1[[#This Row],[Stamp Duty]]+Table1[[#This Row],[GST]] -> 1450.62
A71: Kurinji Malar Paranthaman | B71: ICICI | C71: 44707 | D71: INE090A01021 | E71: ICICI BANK LTD. | F71: CASH | G71: Sell | H71: 2 | I71: 718.25 | J71: =H71*I71 -> 1436.5 | K71: 0 | L71: =H71*K71 -> 0 | M71: 0 | N71: 0 | O71: 1.95 | P71: =Table1[[#This Row],[Net Amount]]+Table1[[#This Row],[NetBrokerage]]+Table1[[#This Row],[STT]]+Table1[[#This Row],[Stamp Duty]]+Table1[[#This Row],[GST]] -> 1438.45
A72: Kurinji Malar Paranthaman | B72: ICICI | C72: 44823 | D72: INE092T01019 | E72: IDFC FIRST BANK LIMITED | F72: CASH | G72: Buy | H72: 100 | I72: 51.45 | J72: =H72*I72 -> 5145 | K72: 0.25 | L72: =H72*K72 -> 25 | M72: 4.99 | N72: 1 | O72: 4.52 | P72: =Table1[[#This Row],[Net Amount]]+Table1[[#This Row],[NetBrokerage]]+Table1[[#This Row],[STT]]+Table1[[#This Row],[Stamp Duty]]+Table1[[#This Row],[GST]] -> 5180.51
A73: Kurinji Malar Paranthaman | B73: ICICI | C73: 44984 | D73: INE238A01034 | E73: AXIS BANK LIMITED | F73: CASH | G73: Buy | H73: 50 | I73: 850 | J73: =H73*I73 -> 42500 | K73: 1.87 | L73: =H73*K73 -> 93.5 | M73: 43 | N73: 6.38 | O73: 17.08 | P73: =Table1[[#This Row],[Net Amount]]+Table1[[#This Row],[NetBrokerage]]+Table1[[#This Row],[STT]]+Table1[[#This Row],[Stamp Duty]]+Table1[[#This Row],[GST]] -> 42659.96
A74: Kurinji Malar Paranthaman | B74: ICICI | C74: 44984 | D74: INE092T01019 | E74: IDFC FIRST BANK LIMITED | F74: CASH | G74: Buy | H74: 1000 | I74: 54 | J74: =H74*I74 -> 54000 | K74: 0.11 | L74: =H74*K74 -> 110 | M74: 54 | N74: 7.62 | O74: 21.61 | P74: =Table1[[#This Row],[Net Amount]]+Table1[[#This Row],[NetBrokerage]]+Table1[[#This Row],[STT]]+Table1[[#This Row],[Stamp Duty]]+Table1[[#This Row],[GST]] -> 54193.23
A75: Kurinji Malar Paranthaman | B75: ICICI | C75: 44994 | D75: INE238A01034 | E75: AXIS BANK LIMITED | F75: CASH | G75: Buy | H75: 5 | I75: 870 | J75: =H75*I75 -> 4350 | K75: 2.5 | L75: =H75*K75 -> 12.5 | M75: 0 | N75: 0 | O75: 0 | P75: =Table1[[#This Row],[Net Amount]]+Table1[[#This Row],[NetBrokerage]]+Table1[[#This Row],[STT]]+Table1[[#This Row],[Stamp Duty]]+Table1[[#This Row],[GST]] -> 4362.5
A76: Kurinji Malar Paranthaman | B76: ICICI | C76: 44994 | D76: INE238A01034 | E76: AXIS BANK LIMITED | F76: CASH | G76: Buy | H76: 5 | I76: 870 | J76: =H76*I76 -> 4350 | K76: 2.5 | L76: =H76*K76 -> 12.5 | M76: 9 | N76: 1 | O76: 4.55 | P76: =Table1[[#This Row],[Net Amount]]+Table1[[#This Row],[NetBrokerage]]+Table1[[#This Row],[STT]]+Table1[[#This Row],[Stamp Duty]]+Table1[[#This Row],[GST]] -> 4377.05
A77: Kurinji Malar Paranthaman | B77: ICICI | C77: 45321 | D77: INE092T01019 | E77: IDFC FIRST BANK LIMITED | F77: CASH | G77: Buy | H77: 400 | I77: 83 | J77: =H77*I77 -> 33200 | K77: 0.182 | L77: =H77*K77 -> 72.8 | M77: 33 | N77: 5 | O77: 13.33 | P77: =Table1[[#This Row],[Net Amount]]+Table1[[#This Row],[NetBrokerage]]+Table1[[#This Row],[STT]]+Table1[[#This Row],[Stamp Duty]]+Table1[[#This Row],[GST]] -> 33324.13
A78: Kurinji Malar Paranthaman | B78: ICICI | C78: 45470 | D78: INE351F01018 | E78: JAIPRAKASH POWER VEN. LTD | F78: CASH | G78: Buy | H78: 10 | I78: 19.66 | J78: =H78*I78 -> 196.6 | K78: 0.147 | L78: =H78*K78 -> 1.47 | M78: 0 | N78: 0 | O78: 0.26 | P78: =J78+L78 -> 198.07
A79: Kurinji Malar Paranthaman | B79: ICICI | C79: 45517 | D79: INE040H01021 | E79: SUZLON ENERGY LIMITED | F79: CASH | G79: Buy | H79: 50 | I79: 83.1 | J79: =H79*I79 -> 4155 | K79: 0.5 | L79: =H79*K79 -> 25 | M79: 0 | N79: 0 | O79: 4.52 | P79: =Table1[[#This Row],[Net Amount]]+Table1[[#This Row],[NetBrokerage]]+Table1[[#This Row],[STT]]+Table1[[#This Row],[Stamp Duty]]+Table1[[#This Row],[GST]] -> 4184.52
A80: Kurinji Malar Paranthaman | B80: ICICI | C80: 45517 | D80: INE040H01021 | E80: SUZLON ENERGY LIMITED | F80: CASH | G80: Sell | H80: 31 | I80: 82.65 | J80: =H80*I80 -> 2562.15 | K80: 0 | L80: =H80*K80 -> 0 | M80: 0 | N80: 0 | P80: =Table1[[#This Row],[Net Amount]]+Table1[[#This Row],[NetBrokerage]]+Table1[[#This Row],[STT]]+Table1[[#This Row],[Stamp Duty]]+Table1[[#This Row],[GST]] -> 2562.15
A81: Kurinji Malar Paranthaman | B81: ICICI | C81: 45517 | D81: INE040H01021 | E81: SUZLON ENERGY LIMITED | F81: CASH | G81: Sell | H81: 19 | I81: 82.64 | J81: =H81*I81 -> 1570.16 | K81: 0 | L81: =H81*K81 -> 0 | M81: 0.99 | N81: 0 | O81: 0.02 | P81: =Table1[[#This Row],[Net Amount]]+Table1[[#This Row],[NetBrokerage]]+Table1[[#This Row],[STT]]+Table1[[#This Row],[Stamp Duty]]+Table1[[#This Row],[GST]] -> 1571.17
A82: Kurinji Malar Paranthaman | B82: ICICI | C82: 45524 | D82: INE129A01019 | E82: GAIL (INDIA) LTD | F82: CASH | G82: Buy | H82: 5 | I82: 236.65 | J82: =H82*I82 -> 1183.25 | K82: 1.77 | L82: =H82*K82 -> 8.85 | M82: 1 | N82: 0 | O82: 1.6 | P82: =Table1[[#This Row],[Net Amount]]+Table1[[#This Row],[NetBrokerage]]+Table1[[#This Row],[STT]]+Table1[[#This Row],[Stamp Duty]]+Table1[[#This Row],[GST]] -> 1194.7
A83: Kurinji Malar Paranthaman | B83: ICICI | C83: 45525 | D83: INE0KL801015 | E83: DCX SYSTEMS LIMITED | F83: CASH | G83: Buy | H83: 10 | I83: 348.9 | J83: =H83*I83 -> 3489 | K83: 2.5 | L83: =H83*K83 -> 25 | M83: 2.99 | N83: 1 | O83: 4.52 | P83: =Table1[[#This Row],[Net Amount]]+Table1[[#This Row],[NetBrokerage]]+Table1[[#This Row],[STT]]+Table1[[#This Row],[Stamp Duty]]+Table1[[#This Row],[GST]] -> 3522.51
A84: Kurinji Malar Paranthaman | B84: ICICI | C84: 45525 | D84: INE129A01019 | E84: GAIL (INDIA) LTD | F84: CASH | G84: Buy | H84: 25 | I84: 237.9 | J84: =H84*I84 -> 5947.5 | K84: 1 | L84: =H84*K84 -> 25 | M84: 5.61 | N84: 0.79 | O84: 4.53 | P84: =Table1[[#This Row],[Net Amount]]+Table1[[#This Row],[NetBrokerage]]+Table1[[#This Row],[STT]]+Table1[[#This Row],[Stamp Duty]]+Table1[[#This Row],[GST]] -> 5983.43
A85: Kurinji Malar Paranthaman | B85: ICICI | C85: 45525 | D85: INE0LXG01040 | E85: OLA ELECTRIC MOBILITY LTD | F85: CASH | G85: Buy | H85: 10 | I85: 138.6 | J85: =H85*I85 -> 1386 | K85: 1.039 | L85: =H85*K85 -> 10.39 | M85: 1.38 | N85: 0.21 | O85: 1.87 | P85: =J85+L85 -> 1396.39
A86: Kurinji Malar Paranthaman | B86: ICICI | C86: 45534 | D86: INE0LXG01040 | E86: OLA ELECTRIC MOBILITY LTD | F86: CASH | G86: Buy | H86: 10 | I86: 121.91 | J86: =H86*I86 -> 1219.1 | K86: 0.91 | L86: =H86*K86 -> 9.1 | M86: 0.99 | N86: 0 | O86: 1.65 | P86: =J86+L86 -> 1228.2
A87: Kurinji Malar Paranthaman | B87: ICICI | C87: 45638 | D87: INE040H01021 | E87: SUZLON ENERGY LIMITED | F87: CASH | G87: Buy | H87: 100 | I87: 65 | J87: =H87*I87 -> 6500 | K87: 0.25 | L87: =H87*K87 -> 25 | M87: 6.5 | N87: 0.98 | O87: 4.53 | P87: =Table1[[#This Row],[Net Amount]]+Table1[[#This Row],[NetBrokerage]]+Table1[[#This Row],[STT]]+Table1[[#This Row],[Stamp Duty]]+Table1[[#This Row],[GST]] -> 6537.01
A88: Kurinji Malar Paranthaman | B88: ICICI | C88: 45638 | D88: INE155A01022 | E88: TATA MOTORS LIMITED | F88: CASH | G88: Buy | H88: 50 | I88: 790 | J88: =H88*I88 -> 39500 | K88: 1.73 | L88: =H88*K88 -> 86.5 | M88: 39.5 | N88: 6.02 | O88: 15.86 | P88: =Table1[[#This Row],[Net Amount]]+Table1[[#This Row],[NetBrokerage]]+Table1[[#This Row],[STT]]+Table1[[#This Row],[Stamp Duty]]+Table1[[#This Row],[GST]] -> 39647.88
A89: Kurinji Malar Paranthaman | B89: ICICI | C89: 45644 | D89: INE0KL801015 | E89: DCX SYSTEMS LIMITED | F89: CASH | G89: Buy | H89: 10 | I89: 330 | J89: =H89*I89 -> 3300 | K89: 2.47 | L89: =H89*K89 -> 24.7 | M89: 3.45 | N89: 0.5 | O89: 4.47 | P89: =Table1[[#This Row],[Net Amount]]+Table1[[#This Row],[NetBrokerage]]+Table1[[#This Row],[STT]]+Table1[[#This Row],[Stamp Duty]]+Table1[[#This Row],[GST]] -> 3333.12
A90: Kurinji Malar Paranthaman | B90: ICICI | C90: 45644 | D90: INE129A01019 | E90: GAIL (INDIA) LTD | F90: CASH | G90: Buy | H90: 10 | I90: 195 | J90: =H90*I90 -> 1950 | K90: 1.46 | L90: =H90*K90 -> 14.6 | M90: 1.95 | N90: 0.29 | O90: 2.64 | P90: =Table1[[#This Row],[Net Amount]]+Table1[[#This Row],[NetBrokerage]]+Table1[[#This Row],[STT]]+Table1[[#This Row],[Stamp Duty]]+Table1[[#This Row],[GST]] -> 1969.48
A91: Kurinji Malar Paranthaman | B91: ICICI | C91: 45644 | D91: INE0LXG01040 | E91: OLA ELECTRIC MOBILITY LTD | F91: CASH | G91: Buy | H91: 10 | I91: 95 | J91: =H91*I91 -> 950 | K91: 0.71 | L91: =H91*K91 -> 7.1 | M91: 0.94 | N91: 0.14 | O91: 1.28 | P91: =J91+L91 -> 957.1
A92: Kurinji Malar Paranthaman | B92: ICICI | C92: 45644 | D92: INE155A01022 | E92: TATA MOTORS LIMITED | F92: CASH | G92: Buy | H92: 10 | I92: 765 | J92: =H92*I92 -> 7650 | K92: 2.5 | L92: =H92*K92 -> 25 | M92: 7.65 | N92: 1.07 | O92: 4.54 | P92: =Table1[[#This Row],[Net Amount]]+Table1[[#This Row],[NetBrokerage]]+Table1[[#This Row],[STT]]+Table1[[#This Row],[Stamp Duty]]+Table1[[#This Row],[GST]] -> 7688.26
A93: Kurinji Malar Paranthaman | B93: ICICI | C93: 45645 | D93: INE155A01022 | E93: TATA MOTORS LIMITED | F93: CASH | G93: Buy | H93: 5 | I93: 744.75 | J93: =H93*I93 -> 3723.75 | K93: 5 | L93: =H93*K93 -> 25 | M93: 0 | N93: 0 | O93: 0 | P93: =Table1[[#This Row],[Net Amount]]+Table1[[#This Row],[NetBrokerage]]+Table1[[#This Row],[STT]]+Table1[[#This Row],[Stamp Duty]]+Table1[[#This Row],[GST]] -> 3748.75
A94: Kurinji Malar Paranthaman | B94: ICICI | C94: 45645 | D94: INE155A01022 | E94: TATA MOTORS LIMITED | F94: CASH | G94: Buy | H94: 5 | I94: 744.75 | J94: =H94*I94 -> 3723.75 | K94: 5 | L94: =H94*K94 -> 25 | M94: 6.99 | N94: 1 | O94: 9.04 | P94: =Table1[[#This Row],[Net Amount]]+Table1[[#This Row],[NetBrokerage]]+Table1[[#This Row],[STT]]+Table1[[#This Row],[Stamp Duty]]+Table1[[#This Row],[GST]] -> 3765.78
A95: Kurinji Malar Paranthaman | B95: ICICI | C95: 45646 | D95: INE0LXG01040 | E95: OLA ELECTRIC MOBILITY LTD | F95: CASH | G95: Buy | H95: 10 | I95: 94 | J95: =H95*I95 -> 940 | K95: 0.7 | L95: =H95*K95 -> 7 | M95: 0.75 | N95: 0.14 | O95: 1.27 | P95: =Table1[[#This Row],[Net Amount]]+Table1[[#This Row],[NetBrokerage]]+Table1[[#This Row],[STT]]+Table1[[#This Row],[Stamp Duty]]+Table1[[#This Row],[GST]] -> 949.16
A96: Kurinji Malar Paranthaman | B96: ICICI | C96: 45646 | D96: INE155A01022 | E96: TATA MOTORS LIMITED | F96: CASH | G96: Buy | H96: 10 | I96: 725 | J96: =H96*I96 -> 7250 | K96: 2.5 | L96: =H96*K96 -> 25 | M96: 7.25 | N96: 0.86 | O96: 4.54 | P96: =Table1[[#This Row],[Net Amount]]+Table1[[#This Row],[NetBrokerage]]+Table1[[#This Row],[STT]]+Table1[[#This Row],[Stamp Duty]]+Table1[[#This Row],[GST]] -> 7287.65
A97: Kurinji Malar Paranthaman | B97: ICICI | C97: 45946 | D97: INE1TAE01010 | E97: Tata Motors Commercial Vehicles | F97: SPLIT | G97: Split | H97: 80 | I97: 0 | J97: 0 | K97: 0 | L97: 0 | M97: 0 | N97: 0 | O97: 0 | P97: =Table1[[#This Row],[Net Amount]]+Table1[[#This Row],[NetBrokerage]]+Table1[[#This Row],[STT]]+Table1[[#This Row],[Stamp Duty]]+Table1[[#This Row],[GST]] -> 0
A98: Kurinji Malar Paranthaman | B98: GEOJIT | C98: 43917 | D98: INE323A01026 | E98: BOSCH LIMITED | F98: CASH | G98: Buy | H98: 2 | I98: 10050 | J98: =H98*I98 -> 20100 | K98: 30.15 | L98: =H98*K98 -> 60.3 | M98: 20 | N98: 1.21 | O98: 10.98 | P98: =Table1[[#This Row],[Net Amount]]+Table1[[#This Row],[NetBrokerage]]+Table1[[#This Row],[STT]]+Table1[[#This Row],[Stamp Duty]]+Table1[[#This Row],[GST]] -> 20192.49
A99: Kurinji Malar Paranthaman | B99: GEOJIT | C99: 43992 | D99: INE040A01034 | E99: HDFC BANK LIMITED | F99: CASH | G99: Buy | H99: 10 | I99: 990 | J99: =H99*I99 -> 9900 | K99: 2.97 | L99: =H99*K99 -> 29.7 | M99: 10 | N99: 0.59 | O99: 5.41 | P99: =Table1[[#This Row],[Net Amount]]+Table1[[#This Row],[NetBrokerage]]+Table1[[#This Row],[STT]]+Table1[[#This Row],[Stamp Duty]]+Table1[[#This Row],[GST]] -> 9945.7
A100: Kurinji Malar Paranthaman | B100: GEOJIT | C100: 44019 | D100: INE154A01025 | E100: ITC LIMITED | F100: CASH | G100: Buy | H100: 50 | I100: 200 | J100: =H100*I100 -> 10000 | K100: 0.6 | L100: =H100*K100 -> 30 | M100: 10 | N100: 1.5 | O100: 5.46 | P100: =Table1[[#This Row],[Net Amount]]+Table1[[#This Row],[NetBrokerage]]+Table1[[#This Row],[STT]]+Table1[[#This Row],[Stamp Duty]]+Table1[[#This Row],[GST]] -> 10046.96
A101: Kurinji Malar Paranthaman | B101: GEOJIT | C101: 45895 | D101: INE040A01034 | E101: HDFC BANK LIMITED | F101: DIVIDEND | G101: Bonus | H101: 10 | I101: 0 | J101: =H101*I101 -> 0 | K101: 0 | L101: =H101*K101 -> 0 | P101: =J101+L101 -> 0
A102: Kurinji Malar Paranthaman | B102: GEOJIT | C102: 45671 | D102: INE379A01028 | E102: ITC Hotels Limited | F102: SPLIT | G102: Split | H102: 5 | I102: 0 | J102: =H102*I102 -> 0 | K102: 0 | L102: =H102*K102 -> 0 | P102: =J102+L102 -> 0

Sheet Equity Dividend
A1: People | B1: Record Date | C1: Date | D1: Account | E1: ISIN | F1: Stock | G1: Nature | H1: Quantity | I1: Per Share | J1: Ratio | K1: Dividend Amount | L1: Total Units | M1: TaxOnDividend | N1: FinalAmount
A2: Arun Venkatesan | C2: 41870 | D2: IIFL | E2: INE081A01012 | F2: Tata Steel | H2: 100 | I2: 0.4 | K2: 40
A3: Arun Venkatesan | C3: 42230 | D3: IIFL | E3: INE081A01012 | F3: Tata Steel | H3: 100 | I3: 6.72 | K3: 672
A4: Arun Venkatesan | C4: 42258 | D4: IIFL | E4: INE018A01030 | F4: Larsen & Tubro | H4: 9 | I4: 16.25 | K4: 146.25
A5: Arun Venkatesan | C5: 42261 | D5: IIFL | E5: INE498L01015 | F5: L&T Finance | H5: 100 | I5: 0.8 | K5: 80
A6: Arun Venkatesan | C6: 42292 | D6: IIFL | E6: INE114A01011 | F6: Steel Authority of India | H6: 50 | K6: 12.5
A7: Arun Venkatesan | C7: 42298 | D7: IIFL | E7: INE009A01021 | F7: Infosys | H7: 53 | I7: 10 | K7: 530
A8: Arun Venkatesan | C8: 42541 | D8: IIFL | E8: INE009A01021 | F8: Infosys | H8: 53 | I8: 14.25 | K8: 755.25
A9: Arun Venkatesan | C9: 42598 | D9: IIFL | E9: INE081A01012 | F9: Tata Steel | H9: 100 | I9: 8 | K9: 800
A10: Arun Venkatesan | C10: 42612 | D10: IIFL | E10: INE018A01030 | F10: Larsen & Tubro | H10: 9 | I10: 18.25 | K10: 164.25
A11: Arun Venkatesan | C11: 42669 | D11: IIFL | E11: INE009A01021 | F11: Infosys | H11: 53 | I11: 11 | K11: 583
A12: Arun Venkatesan | C12: 42913 | D12: IIFL | E12: INE009A01021 | F12: Infosys | H12: 53 | I12: 14.75 | K12: 781.75
A13: Arun Venkatesan | C13: 42933 | D13: IIFL | E13: INE018A01030 | F13: Larsen & Tubro | H13: 0.5 | K13: 581.5
A14: Arun Venkatesan | C14: 42933 | D14: IIFL | E14: INE018A01030 | F14: Larsen & Tubro | G14: Bonus | H14: 4 | L14: 4
A15: Arun Venkatesan | C15: 42957 | D15: IIFL | E15: INE081A01012 | F15: Tata Steel | H15: 100 | I15: 10 | K15: 1000
A16: Arun Venkatesan | C16: 42971 | D16: IIFL | E16: INE018A01030 | F16: Larsen & Tubro | H16: 13 | I16: 14 | K16: 182
A17: Arun Venkatesan | C17: 42992 | D17: IIFL | E17: INE498L01015 | F17: L&T Finance | H17: 100 | I17: 0.8 | K17: 80
A18: Arun Venkatesan | C18: 43043 | D18: IIFL | E18: INE009A01021 | F18: Infosys | H18: 53 | I18: 13 | K18: 689
A19: Arun Venkatesan | C19: 43277 | D19: IIFL | E19: INE009A01021 | F19: Infosys | H19: 53 | I19: 30.5 | K19: 1616.5
A20: Arun Venkatesan | C20: 43304 | D20: IIFL | E20: INE081A01012 | F20: Tata Steel | H20: 100 | I20: 10 | K20: 1000
A21: Arun Venkatesan | C21: 43339 | D21: IIFL | E21: INE018A01030 | F21: Larsen & Tubro | H21: 13 | I21: 16 | K21: 208
A22: Arun Venkatesan | C22: 43343 | D22: IIFL | E22: INE498L01015 | F22: L&T Finance | H22: 100 | I22: 1 | K22: 100
A23: Arun Venkatesan | C23: 43360 | D23: IIFL | E23: INE009A01021 | F23: Infosys | G23: Bonus | H23: 53 | J23: 1:1 | L23: 53
A24: Arun Venkatesan | C24: 43403 | D24: IIFL | E24: INE009A01021 | F24: Infosys | H24: 106 | I24: 7 | K24: 742
A25: Arun Venkatesan | C25: 43493 | D25: IIFL | E25: INE009A01021 | F25: Infosys | H25: 106 | I25: 4 | K25: 424
A26: Arun Venkatesan | C26: 43641 | D26: IIFL | E26: INE009A01021 | F26: Infosys | H26: 106 | I26: 10.5 | K26: 1113
A27: Arun Venkatesan | C27: 43669 | D27: IIFL | E27: INE081A01012 | F27: Tata Steel | H27: 100 | I27: 13 | K27: 1300
A28: Arun Venkatesan | C28: 43678 | D28: IIFL | E28: INE498L01015 | F28: L&T Finance | H28: 100 | I28: 1 | K28: 100
A29: Arun Venkatesan | C29: 43682 | D29: IIFL | E29: INE018A01030 | F29: Larsen & Tubro | H29: 13 | I29: 18 | K29: 234
A30: Arun Venkatesan | C30: 43728 | D30: IIFL | E30: INE114A01011 | F30: Steel Authority of India | H30: 100 | I30: 0.5 | K30: 50
A31: Arun Venkatesan | C31: 43768 | D31: IIFL | E31: INE009A01021 | F31: Infosys | H31: 106 | I31: 8 | K31: 848
A32: Arun Venkatesan | C32: 43920 | D32: IIFL | E32: INE018A01030 | F32: Larsen & Tubro | H32: 13 | I32: 10 | K32: 130
A33: Arun Venkatesan | C33: 44015 | D33: IIFL | E33: INE009A01021 | F33: Infosys | H33: 106 | I33: 9.5 | K33: 1007
A34: Arun Venkatesan | C34: 44060 | D34: IIFL | E34: INE018A01030 | F34: Larsen & Tubro | H34: 43 | I34: 8 | K34: 344
A35: Arun Venkatesan | C35: 44067 | D35: IIFL | E35: INE081A01012 | F35: Tata Steel | H35: 100 | I35: 10 | K35: 1000
A36: Arun Venkatesan | C36: 44078 | D36: IIFL | E36: INE323A01026 | F36: Bosch Limited | H36: 6 | I36: 105 | K36: 630
A37: Kurinji Malar Paranthaman | C37: 44078 | D37: GEOGIT | E37: INE323A01026 | F37: Bosch Limited | H37: 2 | I37: 105 | K37: 210 | M37: 0 | N37: 0
A38: Arun Venkatesan | C38: 44145 | D38: IIFL | E38: INE018A01030 | F38: Larsen & Tubro | H38: 43 | I38: 18 | K38: 774
A39: Arun Venkatesan | C39: 44148 | D39: IIFL | E39: INE009A01021 | F39: Infosys | H39: 106 | I39: 12 | K39: 1272
A40: Arun Venkatesan | C40: 44243 | D40: IIFL | E40: INE003A01024 | F40: Siemens | H40: 50 | I40: 7 | K40: 350
A41: Arun Venkatesan | C41: 44348 | D41: IIFL | E41: INE009A01021 | F41: Infosys | H41: 106 | I41: 15 | K41: 1590
A42: Arun Venkatesan | C42: 44348 | D42: IIFL | E42: INE009A01021 | F42: Infosys | H42: 106 | I42: 15 | K42: 1590
A43: Kurinji Malar Paranthaman | C43: 44358 | D43: GEOGIT | E43: INE154A01025 | F43: ITC Limited | G43: Yearly Dividend | H43: 50 | I43: 5.75 | K43: 288
A44: Arun Venkatesan | C44: 44379 | D44: IIFL | E44: INE081A01012 | F44: Tata Steel | H44: 100 | I44: 25 | K44: 2500
A45: Arun Venkatesan | C45: 44406 | D45: IIFL | E45: INE053A01029 | F45: Indian Hotels Company Ltd | H45: 50 | I45: 0.4 | K45: 20
A46: Kurinji Malar Paranthaman | C46: 44416 | D46: GEOGIT | E46: INE040A01034 | F46: HDFC Bank Ltd | H46: 10 | K46: 65 | M46: 0 | N46: 0
A47: Arun Venkatesan | B47: 44376 | C47: 44418 | D47: ICICI | E47: INE040A01034 | F47: HDFC Bank Ltd | G47: Yearly Dividend | H47: 10 | I47: 6.5 | K47: 65
A48: Kurinji Malar Paranthaman | C48: 44418 | D48: GEOGIT | E48: INE040A01034 | F48: HDFC Bank Ltd | G48: Yearly Dividend | H48: 10 | I48: 6.5 | K48: 65
A49: Arun Venkatesan | C49: 44420 | D49: IIFL | E49: INE323A01026 | F49: Bosch Limited | H49: 6 | I49: 115 | K49: 690
A50: Arun Venkatesan | C50: 44420 | D50: IIFL | E50: INE018A01030 | F50: Larsen & Tubro | H50: 43 | I50: 18 | K50: 774
A51: Kurinji Malar Paranthaman | C51: 44420 | D51: GEOGIT | E51: INE323A01026 | F51: Bosch Limited | G51: Yearly Dividend | H51: 2 | I51: 115 | K51: 230
A52: Kurinji Malar Paranthaman | C52: 44421 | D52: GEOGIT | E52: INE154A01025 | F52: ITC Limited | H52: 50 | K52: 288 | M52: 0 | N52: 0
A53: Arun Venkatesan | B53: 44376 | C53: 44440 | D53: ICICI | E53: INE090A01021 | F53: ICICI Bank Limited | G53: Yearly Dividend | H53: 20 | I53: 2 | K53: 40
A54: Arun Venkatesan | C54: 44487 | D54: IIFL | E54: INE114A01011 | F54: Steel Authority of India | H54: 100 | I54: 1.8 | K54: 180
A55: Arun Venkatesan | C55: 44490 | D55: IIFL | E55: INE335Y01012 | F55: IRCTC | H55: 20 | I55: 5 | K55: 100
A56: Arun Venkatesan | C56: 44510 | D56: IIFL | E56: INE009A01021 | F56: Infosys | H56: 106 | I56: 15 | K56: 1590
A57: Arun Venkatesan | C57: 44524 | D57: IIFL | E57: INE114A01011 | F57: Steel Authority of India | H57: 100 | I57: 4 | K57: 400
A58: Arun Venkatesan | C58: 44600 | D58: IIFL | E58: INE003A01024 | F58: Siemens | H58: 50 | I58: 8 | K58: 400
A59: Kurinji Malar Paranthaman | C59: 44607 | D59: GEOGIT | E59: INE154A01025 | F59: ITC Limited | G59: Interim Dividend | H59: 50 | I59: 5.25 | K59: 263
A60: Arun Venkatesan | C60: 44624 | D60: IIFL | E60: INE335Y01020 | F60: IRCTC | H60: 100 | I60: 2 | K60: 200
A61: Kurinji Malar Paranthaman | C61: 44624 | D61: GEOGIT | E61: INE154A01025 | F61: ITC Limited | H61: 50 | K61: 263 | M61: 0 | N61: 0
A62: Arun Venkatesan | C62: 44664 | D62: IIFL | E62: INE114A01011 | F62: Steel Authority of India | H62: 100 | I62: 2.5 | K62: 250
A63: Arun Venkatesan | C63: 44740 | D63: IIFL | E63: INE009A01021 | F63: Infosys | H63: 106 | I63: 16 | K63: 1696
A64: Arun Venkatesan | C64: 44744 | D64: IIFL | E64: INE081A01012 | F64: Tata Steel | H64: 100 | I64: 45.9 | K64: 4590
A65: Arun Venkatesan | C65: 44744 | D65: IIFL | E65: INE081A01012 | F65: Tata Steel | H65: 100 | I65: 51 | K65: 5100 | M65: 510 | N65: 4590
A66: Arun Venkatesan | C66: 44749 | D66: IIFL | E66: INE053A01029 | F66: Indian Hotels Company Ltd | H66: 55 | I66: 0.4 | K66: 22
A67: Arun Venkatesan | C67: 44756 | D67: IIFL | E67: INE498L01015 | F67: L&T Finance | H67: 184 | I67: 0.92 | K67: 92
A68: Arun Venkatesan | B68: 44727 | C68: 44757 | D68: ICICI | E68: INE562A01011 | F68: Indian Bank | G68: Yearly Dividend | H68: 100 | I68: 6.5 | K68: 650
A69: Arun Venkatesan | C69: 44757 | D69: IIFL | E69: INE457A01014 | F69: Bank of Maharastra | H69: 500 | I69: 0.5 | K69: 250
A70: Arun Venkatesan | B70: 44693 | C70: 44760 | D70: ICICI | E70: INE040A01034 | F70: HDFC Bank Ltd | G70: Yearly Dividend | H70: 20 | I70: 15.5 | K70: 310
A71: Kurinji Malar Paranthaman | C71: 44760 | D71: GEOGIT | E71: INE040A01034 | F71: HDFC Bank Ltd | H71: 10 | K71: 155 | M71: 0 | N71: 0
A72: Kurinji Malar Paranthaman | C72: 44764 | D72: GEOGIT | E72: INE154A01025 | F72: ITC Limited | H72: 50 | K72: 313 | M72: 0 | N72: 0
A73: Arun Venkatesan | C73: 44781 | D73: IIFL | E73: INE018A01030 | F73: Larsen & Tubro | H73: 43 | I73: 22 | K73: 946
A74: Arun Venkatesan | C74: 44783 | D74: IIFL | E74: INE323A01026 | F74: Bosch Limited | G74: Yearly Dividend | H74: 6 | I74: 210 | K74: 1260
A75: Kurinji Malar Paranthaman | C75: 44783 | D75: GEOGIT | E75: INE323A01026 | F75: Bosch Limited | H75: 2 | K75: 420 | M75: 0 | N75: 0
A76: Kurinji Malar Paranthaman | C76: 44785 | D76: GEOGIT | E76: INE323A01026 | F76: Bosch Limited | H76: 2 | K76: 230 | M76: 0 | N76: 0
A77: Arun Venkatesan | B77: 44782 | C77: 44805 | D77: ICICI | E77: INE090A01021 | F77: ICICI Bank Limited | G77: Yearly Dividend | H77: 40 | I77: 5 | K77: 200
A78: Arun Venkatesan | C78: 44823 | D78: IIFL | E78: INE335Y01020 | F78: IRCTC | H78: 100 | I78: 1.5 | K78: 150
A79: Arun Venkatesan | B79: 44817 | C79: 44825 | D79: ICICI | E79: INE925R01014 | F79: CMS Info Systems Limited | G79: Yearly Dividend | H79: 69 | I79: 1 | K79: 69
A80: Arun Venkatesan | C80: 44847 | D80: IIFL | E80: INE114A01011 | F80: Steel Authority of India | H80: 100 | I80: 2.25 | K80: 225
A81: Arun Venkatesan | C81: 44875 | D81: IIFL | E81: INE009A01021 | F81: Infosys | H81: 106 | I81: 16.5 | K81: 1749
A82: Arun Venkatesan | C82: 44991 | D82: IIFL | E82: INE335Y01020 | F82: IRCTC | H82: 100 | I82: 3.5 | K82: 350
A83: Arun Venkatesan | C83: 44991 | D83: IIFL | E83: INE323A01026 | F83: Bosch Limited | H83: 6 | I83: 280 | K83: 1680
A84: Kurinji Malar Paranthaman | C84: 44991 | D84: GEOGIT | E84: INE323A01026 | F84: Bosch Limited | H84: 2 | I84: 280 | K84: 560
A85: Arun Venkatesan | C85: 45026 | D85: IIFL | E85: INE114A01011 | F85: Steel Authority of India | H85: 100 | I85: 1 | K85: 100
A86: Arun Venkatesan | C86: 45109 | D86: IIFL | E86: INE457A01014 | F86: Bank of Maharastra | H86: 500 | I86: 1.26 | K86: 630
A87: Arun Venkatesan | C87: 45110 | D87: IIFL | E87: INE009A01021 | F87: Infosys | H87: 126 | I87: 17.5 | K87: 2205
A88: Kurinji Malar Paranthaman | B88: 45113 | C88: 45114 | D88: ICICI | E88: INE238A01034 | F88: AXIS BANK LIMITED | G88: Yearly Dividend | H88: 60 | I88: 1 | K88: 60 | M88: 0 | N88: 0
A89: Arun Venkatesan | C89: 45117 | D89: IIFL | E89: INE081A01020 | F89: Tata Steel | H89: 1000 | I89: 3.6 | K89: 3600
A90: Arun Venkatesan | B90: 45089 | C90: 45121 | D90: ICICI | E90: INE562A01011 | F90: Indian Bank | G90: Yearly Dividend | H90: 200 | I90: 8.6 | K90: 1720
A91: Arun Venkatesan | C91: 45139 | D91: IIFL | E91: INE498L01015 | F91: L&T Finance | H91: 184 | K91: 368
A92: Arun Venkatesan | C92: 45148 | D92: IIFL | E92: INE323A01026 | F92: Bosch Limited | H92: 6 | I92: 200 | K92: 1200
A93: Arun Venkatesan | C93: 45148 | D93: GEOGIT | E93: INE323A01026 | F93: Bosch Limited | H93: 2 | I93: 200 | K93: 400
A94: Arun Venkatesan | C94: 45149 | D94: IIFL | E94: INE155A01022 | F94: Tata Motors | H94: 50 | I94: 2 | K94: 100
A95: Arun Venkatesan | B95: 45061 | C95: 45152 | D95: ICICI | E95: INE040A01034 | F95: HDFC Bank Ltd | G95: Yearly Dividend | H95: 100 | I95: 19 | K95: 1900
A96: Arun Venkatesan | C96: 45152 | D96: IIFL | E96: INE018A01030 | F96: Larsen & Tubro | H96: 43 | I96: 6 | K96: 258
A97: Arun Venkatesan | C97: 45152 | D97: IIFL | E97: INE018A01030 | F97: Larsen & Tubro | H97: 43 | I97: 24 | K97: 1032
A98: Arun Venkatesan | B98: 45168 | C98: 45168 | D98: ICICI | E98: INE925R01014 | F98: CMS INFO SYSTEMS LIMITED | G98: Yearly Dividend | H98: 69 | I98: 4.75 | K98: 327.75
A99: Arun Venkatesan | B99: 45146 | C99: 45170 | D99: ICICI | E99: INE090A01021 | F99: ICICI BANK LIMITED | G99: Yearly Dividend | H99: 100 | I99: 8 | K99: 800
A100: Arun Venkatesan | C100: 45187 | D100: IIFL | E100: INE335Y01020 | F100: IRCTC | H100: 100 | I100: 2 | K100: 200
...

Sheet Mutual Fund

Sheet Mutual Fund Transaction
A1: Person | B1: Account | C1: Date | D1: Transaction ID | E1: Transaction Type | F1: Fund Name | G1: Scheme Name | H1: Folio No | I1: Last recorded NAV | J1: Last recorded NAV On | K1: Div-Reinvestment | L1: Amount | M1: Secure Mind Premium Amount | N1: Unit | O1: Status | P1: Tax Saving | Q1: Channel
A2: Arun Venkatesan | B2: ICICI | C2: 43771 | D2: 82572277 | E2: Purchase | F2: ADITYA BIRLA SUN LIFE ASSET MANAGEMENT COMPANY LTD | G2: ADITYA BIRLA SUN LIFE ELSS TAX SAVER FUND - IDCW | H2: 1039297412 | I2: 152.47 | J2: 43773 | K2: N | L2: 4500 | M2: 0 | N2: 29.514 | O2: Executed | P2: Tax Receipt | Q2: Web
A3: Arun Venkatesan | B3: ICICI | C3: 43916 | D3: 87979374 | E3: Purchase | F3: HDFC ASSET MANAGEMENT COMPANY LIMITED | G3: HDFC Balanced Advantage Fund - Regular Plan - IDCW | H3: 16747427/33 | I3: 18.707 | J3: 43917 | K3: Y | L3: 5000 | M3: 0 | N3: 267.28 | O3: Executed | Q3: Web
A4: Arun Venkatesan | B4: ICICI | C4: 43917 | D4: 87993474 | E4: Purchase | F4: ICICI PRUDENTIAL MUTUAL FUND | G4: ICICI Prudential Midcap Fund - Growth | H4: 15070068/41 | I4: 64.34 | J4: 43917 | K4: N | L4: 5000 | M4: 0 | N4: 77.712 | O4: Executed | Q4: Web
A5: Arun Venkatesan | B5: ICICI | C5: 43949 | D5: 89034197 | E5: Div-Reinvestment | F5: HDFC ASSET MANAGEMENT COMPANY LIMITED | G5: HDFC Balanced Advantage Fund - Regular Plan - IDCW | H5: 16747427/33 | I5: 19.803 | J5: 43949 | K5: Y | L5: 55.47 | M5: 0 | N5: 2.801 | O5: Executed | Q5: SYS
A6: Arun Venkatesan | B6: ICICI | C6: 43949 | D6: 89024044 | E6: Purchase | F6: ICICI PRUDENTIAL MUTUAL FUND | G6: ICICI Prudential Midcap Fund - Growth | H6: 15070068/41 | I6: 69.75 | J6: 43949 | K6: N | L6: 20000 | M6: 0 | N6: 286.738 | O6: Executed | Q6: Web
A7: Arun Venkatesan | B7: ICICI | C7: 43949 | D7: 89024065 | E7: Purchase | F7: HDFC ASSET MANAGEMENT COMPANY LIMITED | G7: HDFC Balanced Advantage Fund - Regular Plan - IDCW | H7: 16747427/33 | I7: 19.82 | J7: 43949 | K7: Y | L7: 20000 | M7: 0 | N7: 1009.082 | O7: Executed | Q7: Web
A8: Arun Venkatesan | B8: ICICI | C8: 43952 | D8: 89163576 | E8: Purchase | F8: HSBC ASSET MANAGEMENT INDIA PVT Ltd | G8: HSBC Midcap Fund Growth | H8: 5572421/08 | I8: 107.92 | J8: 43955 | K8: N | L8: 30000 | M8: 0 | N8: 277.984 | O8: Executed | Q8: Web
A9: Arun Venkatesan | B9: ICICI | C9: 43978 | D9: 89984464 | E9: Div-Reinvestment | F9: HDFC ASSET MANAGEMENT COMPANY LIMITED | G9: HDFC Balanced Advantage Fund - Regular Plan - IDCW | H9: 16747427/33 | I9: 18.888 | J9: 43978 | K9: Y | L9: 294.21 | M9: 0 | N9: 15.577 | O9: Executed | Q9: SYS
A10: Arun Venkatesan | B10: ICICI | C10: 44005 | D10: 90833658 | E10: Purchase | F10: AXIS ASSET MANAGEMENT COMPANY LIMITED | G10: Axis Midcap Fund - Growth | H10: 91087813195 | I10: 38.01 | J10: 44005 | K10: N | L10: 40000 | M10: 0 | N10: 1052.355 | O10: Executed | Q10: Web
A11: Arun Venkatesan | B11: ICICI | C11: 44006 | D11: 90837474 | E11: Purchase-SIP | F11: ICICI PRUDENTIAL MUTUAL FUND | G11: ICICI Prudential Multi-Asset Fund - IDCW | H11: 15070068/41 | I11: 16.7906 | J11: 44006 | K11: N | L11: 5000 | M11: 0 | N11: 297.786 | O11: Executed | Q11: SYS
A12: Arun Venkatesan | B12: ICICI | C12: 44008 | D12: 90992226 | E12: Div-Reinvestment | F12: HDFC ASSET MANAGEMENT COMPANY LIMITED | G12: HDFC Balanced Advantage Fund - Regular Plan - IDCW | H12: 16747427/33 | I12: 21.051 | J12: 44008 | K12: Y | L12: 297.79 | M12: 0 | N12: 14.146 | O12: Executed | Q12: SYS
A13: Arun Venkatesan | B13: ICICI | C13: 44010 | D13: 90987394 | E13: Purchase-SIP | F13: HDFC ASSET MANAGEMENT COMPANY LIMITED | G13: HDFC Balanced Advantage Fund - Regular Plan - IDCW | H13: 16747427/33 | I13: 20.843 | J13: 44011 | K13: Y | L13: 5000 | M13: 0 | N13: 239.889 | O13: Executed | Q13: SYS
A14: Arun Venkatesan | B14: ICICI | C14: 44012 | D14: 91035580 | E14: Purchase | F14: ICICI PRUDENTIAL MUTUAL FUND | G14: ICICI Prudential Midcap Fund - Growth | H14: 15070068/41 | I14: 78.47 | J14: 44012 | K14: N | L14: 0 | M14: 0 | N14: 318.593 | O14: Executed | Q14: Web
A15: Arun Venkatesan | B15: ICICI | C15: 44015 | D15: 91289318 | E15: Div-Reinvestment | F15: ICICI PRUDENTIAL MUTUAL FUND | G15: ICICI Prudential Multi-Asset Fund - IDCW | H15: 15070068/41 | I15: 16.8552 | J15: 44015 | K15: N | L15: 47.65 | M15: 0 | N15: 2.827 | O15: Executed | Q15: SYS
A16: Arun Venkatesan | B16: ICICI | C16: 44036 | D16: 91940347 | E16: Purchase-SIP | F16: ICICI PRUDENTIAL MUTUAL FUND | G16: ICICI Prudential Multi-Asset Fund - IDCW | H16: 15070068/41 | I16: 17.2364 | J16: 44036 | K16: N | L16: 5000 | M16: 0 | N16: 290.069 | O16: Executed | Q16: SYS
A17: Arun Venkatesan | B17: ICICI | C17: 44040 | D17: 92063258 | E17: Purchase-SIP | F17: HDFC ASSET MANAGEMENT COMPANY LIMITED | G17: HDFC Balanced Advantage Fund - Regular Plan - IDCW | H17: 16747427/33 | I17: 21.398 | J17: 44040 | K17: Y | L17: 5000 | M17: 0 | N17: 233.655 | O17: Executed | Q17: SYS
A18: Arun Venkatesan | B18: ICICI | C18: 44040 | D18: 92100713 | E18: Div-Reinvestment | F18: HDFC ASSET MANAGEMENT COMPANY LIMITED | G18: HDFC Balanced Advantage Fund - Regular Plan - IDCW | H18: 16747427/33 | I18: 21.317 | J18: 44040 | K18: Y | L18: 356.2 | M18: 0 | N18: 16.71 | O18: Executed | Q18: SYS
A19: Arun Venkatesan | B19: ICICI | C19: 44048 | D19: 92385427 | E19: Div-Reinvestment | F19: ICICI PRUDENTIAL MUTUAL FUND | G19: ICICI Prudential Multi-Asset Fund - IDCW | H19: 15070068/41 | I19: 17.2249 | J19: 44048 | K19: N | L19: 94.51 | M19: 0 | N19: 5.487 | O19: Executed | Q19: SYS
A20: Arun Venkatesan | B20: ICICI | C20: 44061 | D20: 92834291 | E20: Purchase | F20: AXIS ASSET MANAGEMENT COMPANY LIMITED | G20: AXIS LARGE CAP FUND - Growth | H20: 91087813195 | I20: 30.98 | J20: 44062 | K20: N | L20: 25000 | M20: 0 | N20: 806.932 | O20: Executed | Q20: Web
A21: Arun Venkatesan | B21: ICICI | C21: 44067 | D21: 93011188 | E21: Purchase-SIP | F21: ICICI PRUDENTIAL MUTUAL FUND | G21: ICICI Prudential Multi-Asset Fund - IDCW | H21: 15070068/41 | I21: 18.049 | J21: 44067 | K21: N | L21: 5000 | M21: 0 | N21: 277.01 | O21: Executed | Q21: SYS
A22: Arun Venkatesan | B22: ICICI | C22: 44069 | D22: 93141330 | E22: Div-Reinvestment | F22: HDFC ASSET MANAGEMENT COMPANY LIMITED | G22: HDFC Balanced Advantage Fund - Regular Plan - IDCW | H22: 16747427/33 | I22: 22.479 | J22: 44069 | K22: Y | L22: 413.78 | M22: 0 | N22: 18.407 | O22: Executed | Q22: SYS
A23: Arun Venkatesan | B23: ICICI | C23: 44071 | D23: 93178156 | E23: Purchase-SIP | F23: HDFC ASSET MANAGEMENT COMPANY LIMITED | G23: HDFC Balanced Advantage Fund - Regular Plan - IDCW | H23: 16747427/33 | I23: 22.759 | J23: 44071 | K23: Y | L23: 5000 | M23: 0 | N23: 219.682 | O23: Executed | Q23: SYS
A24: Arun Venkatesan | B24: ICICI | C24: 44098 | D24: 94111638 | E24: Purchase-SIP | F24: ICICI PRUDENTIAL MUTUAL FUND | G24: ICICI Prudential Multi-Asset Fund - IDCW | H24: 15070068/41 | I24: 16.0465 | J24: 44098 | K24: N | L24: 5000 | M24: 0 | N24: 311.579 | O24: Executed | Q24: SYS
A25: Arun Venkatesan | B25: ICICI | C25: 44100 | D25: 94260425 | E25: Div-Reinvestment | F25: HDFC ASSET MANAGEMENT COMPANY LIMITED | G25: HDFC Balanced Advantage Fund - Regular Plan - IDCW | H25: 16747427/33 | I25: 20.408 | J25: 44100 | K25: Y | L25: 468.54 | M25: 0 | N25: 22.959 | O25: Executed | Q25: SYS
A26: Arun Venkatesan | B26: ICICI | C26: 44102 | D26: 94244967 | E26: Purchase-SIP | F26: HDFC ASSET MANAGEMENT COMPANY LIMITED | G26: HDFC Balanced Advantage Fund - Regular Plan - IDCW | H26: 16747427/33 | I26: 20.808 | J26: 44102 | K26: Y | L26: 5000 | M26: 0 | N26: 240.28 | O26: Executed | Q26: SYS
A27: Arun Venkatesan | B27: ICICI | C27: 44119 | D27: 94940735 | E27: Purchase | F27: HSBC ASSET MANAGEMENT INDIA PVT Ltd | G27: HSBC Midcap Fund IDCW | H27: 5572421/08 | I27: 37.56 | J27: 44119 | K27: N | L27: 200000 | M27: 0 | N27: 5324.547 | O27: Executed | Q27: Web
A28: Arun Venkatesan | B28: ICICI | C28: 44124 | D28: 95075300 | E28: Purchase | F28: ADITYA BIRLA SUN LIFE ASSET MANAGEMENT COMPANY LTD | G28: Aditya Birla Sun Life Savings Fund - Growth | H28: 1039297412 | I28: 415.5092 | J28: 44124 | K28: N | L28: 100000 | M28: 0 | N28: 240.657 | O28: Executed | Q28: Web
A29: Arun Venkatesan | B29: ICICI | C29: 44124 | D29: 95075348 | E29: Redemption | F29: ADITYA BIRLA SUN LIFE ASSET MANAGEMENT COMPANY LTD | G29: ADITYA BIRLA SUN LIFE ELSS TAX SAVER FUND - IDCW | H29: 1039297412 | I29: 0 | J29: 46007 | K29: N | L29: 0 | M29: 0 | N29: 0 | O29: Rejected | Q29: Web
A30: Arun Venkatesan | B30: ICICI | C30: 44128 | D30: 95174584 | E30: Purchase-SIP | F30: ICICI PRUDENTIAL MUTUAL FUND | G30: ICICI Prudential Multi-Asset Fund - IDCW | H30: 15070068/41 | I30: 16.5502 | J30: 44130 | K30: N | L30: 5000 | M30: 0 | N30: 302.096 | O30: Executed | Q30: SYS
A31: Arun Venkatesan | B31: ICICI | C31: 44131 | D31: 95307503 | E31: Div-Reinvestment | F31: HDFC ASSET MANAGEMENT COMPANY LIMITED | G31: HDFC Balanced Advantage Fund - Regular Plan - IDCW | H31: 16747427/33 | I31: 21.028 | J31: 44131 | K31: Y | L31: 529.08 | M31: 0 | N31: 25.161 | O31: Executed | Q31: SYS
A32: Arun Venkatesan | B32: ICICI | C32: 44132 | D32: 95303782 | E32: Purchase-SIP | F32: HDFC ASSET MANAGEMENT COMPANY LIMITED | G32: HDFC Balanced Advantage Fund - Regular Plan - IDCW | H32: 16747427/33 | I32: 20.927 | J32: 44132 | K32: Y | L32: 5000 | M32: 0 | N32: 238.914 | O32: Executed | Q32: SYS
A33: Arun Venkatesan | B33: ICICI | C33: 44137 | D33: 95474589 | E33: Purchase | F33: MIRAE ASSET GLOBAL INVESTMENT MGMT INDIA P LTD | G33: MIRAE ASSET ESG SECTOR LEADERS ETF - REGULAR GROWTH | H33: 79932348715 | I33: 22.345 | J33: 44152 | K33: N | L33: 200000 | M33: 0 | N33: 8950 | O33: Executed | Q33: Web
A34: Arun Venkatesan | B34: ICICI | C34: 44148 | D34: 95920767 | E34: Purchase | F34: ICICI PRUDENTIAL MUTUAL FUND | G34: ICICI Prudential Esg Exclusionary Strategy Fund Growth | H34: 15070068/41 | I34: 0 | J34: 46007 | K34: N | L34: 100000 | M34: 0 | N34: 0 | O34: Cancelled | Q34: Web
A35: Arun Venkatesan | B35: ICICI | C35: 44148 | D35: 95920772 | E35: Purchase | F35: ICICI PRUDENTIAL MUTUAL FUND | G35: ICICI Prudential Esg Exclusionary Strategy Fund Growth | H35: 15070068/41 | I35: 10.58 | J35: 44148 | K35: N | L35: 100000 | M35: 0 | N35: 9451.323 | O35: Executed | Q35: Web
A36: Arun Venkatesan | B36: ICICI | C36: 44152 | D36: 96833552 | E36: TO | F36: MIRAE ASSET GLOBAL INVESTMENT MGMT INDIA P LTD | G36: MIRAE ASSET ESG SECTOR LEADERS ETF - REGULAR GROWTH | H36: 79932348715 | I36: 22.345 | J36: 44152 | K36: N | L36: 199990 | M36: 0 | N36: 8950 | O36: Executed | Q36: SYS
A37: Arun Venkatesan | B37: ICICI | C37: 44159 | D37: 96265204 | E37: Purchase-SIP | F37: ICICI PRUDENTIAL MUTUAL FUND | G37: ICICI Prudential Multi-Asset Fund - IDCW | H37: 15070068/41 | I37: 17.8105 | J37: 44159 | K37: N | L37: 5000 | M37: 0 | N37: 280.719 | O37: Executed | Q37: SYS
A38: Arun Venkatesan | B38: ICICI | C38: 44161 | D38: 96392184 | E38: Div-Reinvestment | F38: HDFC ASSET MANAGEMENT COMPANY LIMITED | G38: HDFC Balanced Advantage Fund - Regular Plan - IDCW | H38: 16747427/33 | I38: 23.113 | J38: 44161 | K38: Y | L38: 589.81 | M38: 0 | N38: 25.519 | O38: Executed | Q38: SYS
A39: Arun Venkatesan | B39: ICICI | C39: 44163 | D39: 96432721 | E39: Purchase-SIP | F39: HDFC ASSET MANAGEMENT COMPANY LIMITED | G39: HDFC Balanced Advantage Fund - Regular Plan - IDCW | H39: 16747427/33 | I39: 23.504 | J39: 44166 | K39: Y | L39: 5000 | M39: 0 | N39: 212.719 | O39: Executed | Q39: SYS
A40: Arun Venkatesan | B40: ICICI | C40: 44189 | D40: 97448198 | E40: Purchase-SIP | F40: ICICI PRUDENTIAL MUTUAL FUND | G40: ICICI Prudential Multi-Asset Fund - IDCW | H40: 15070068/41 | I40: 19.0908 | J40: 44189 | K40: N | L40: 5000 | M40: 0 | N40: 261.893 | O40: Executed | Q40: SYS
A41: Arun Venkatesan | B41: ICICI | C41: 44193 | D41: 97576018 | E41: Purchase-SIP | F41: HDFC ASSET MANAGEMENT COMPANY LIMITED | G41: HDFC Balanced Advantage Fund - Regular Plan - IDCW | H41: 16747427/33 | I41: 25.08 | J41: 44193 | K41: Y | L41: 5000 | M41: 0 | N41: 199.352 | O41: Executed | Q41: SYS
A42: Arun Venkatesan | B42: ICICI | C42: 44194 | D42: 97636527 | E42: Div-Reinvestment | F42: HDFC ASSET MANAGEMENT COMPANY LIMITED | G42: HDFC Balanced Advantage Fund - Regular Plan - IDCW | H42: 16747427/33 | I42: 24.85 | J42: 44194 | K42: Y | L42: 690.49 | M42: 0 | N42: 27.785 | O42: Executed | Q42: SYS
A43: Arun Venkatesan | B43: ICICI | C43: 44220 | D43: 98687732 | E43: Purchase-SIP | F43: ICICI PRUDENTIAL MUTUAL FUND | G43: ICICI Prudential Multi-Asset Fund - IDCW | H43: 15070068/41 | I43: 19.3252 | J43: 44221 | K43: N | L43: 5000 | M43: 0 | N43: 258.717 | O43: Executed | Q43: SYS
A44: Arun Venkatesan | B44: ICICI | C44: 44222 | D44: 98773381 | E44: Div-Reinvestment | F44: HDFC ASSET MANAGEMENT COMPANY LIMITED | G44: HDFC Balanced Advantage Fund - Regular Plan - IDCW | H44: 16747427/33 | I44: 25.074 | J44: 44222 | K44: Y | L44: 371.88 | M44: 0 | N44: 14.831 | O44: Executed | Q44: SYS
A45: Arun Venkatesan | B45: ICICI | C45: 44224 | D45: 98838279 | E45: Purchase-SIP | F45: HDFC ASSET MANAGEMENT COMPANY LIMITED | G45: HDFC Balanced Advantage Fund - Regular Plan - IDCW | H45: 16747427/33 | I45: 24.787 | J45: 44224 | K45: Y | L45: 5000 | M45: 0 | N45: 201.709 | O45: Executed | Q45: SYS
A46: Arun Venkatesan | B46: ICICI | C46: 44251 | D46: 100012306 | E46: Purchase-SIP | F46: ICICI PRUDENTIAL MUTUAL FUND | G46: ICICI Prudential Multi-Asset Fund - IDCW | H46: 15070068/41 | I46: 20.9394 | J46: 44251 | K46: N | L46: 5000 | M46: 0 | N46: 238.772 | O46: Executed | Q46: SYS
A47: Arun Venkatesan | B47: ICICI | C47: 44253 | D47: 100149217 | E47: Div-Reinvestment | F47: HDFC ASSET MANAGEMENT COMPANY LIMITED | G47: HDFC Balanced Advantage Fund - Regular Plan - IDCW | H47: 16747427/33 | I47: 27.677 | J47: 44253 | K47: Y | L47: 690.69 | M47: 0 | N47: 24.954 | O47: Executed | Q47: SYS
A48: Arun Venkatesan | B48: ICICI | C48: 44255 | D48: 100182427 | E48: Purchase-SIP | F48: HDFC ASSET MANAGEMENT COMPANY LIMITED | G48: HDFC Balanced Advantage Fund - Regular Plan - IDCW | H48: 16747427/33 | I48: 27.347 | J48: 44256 | K48: Y | L48: 5000 | M48: 0 | N48: 182.826 | O48: Executed | Q48: SYS
... A127: Arun Venkatesan | B127: ICICI | C127: 45013 | D127: 143829248 | E127: Div-Reinvestment | F127: HDFC ASSET MANAGEMENT COMPANY LIMITED | G127: HDFC Balanced Advantage Fund - Regular Plan - IDCW | H127: 16747427/33 | I127: 28.828 | J127: 45013 | K127: Y | L127: 2055.93 | M127: 0 | N127: 71.314 | O127: Executed | Q127: SYS/DBC
A128: Arun Venkatesan | B128: ICICI | C128: 45021 | D128: 144237737 | E128: Purchase | F128: AXIS ASSET MANAGEMENT COMPANY LIMITED | G128: Axis Midcap Fund - Growth | H128: 91087813195 | I128: 64.77 | J128: 45021 | K128: N | L128: 60000 | M128: 0 | N128: 926.308 | O128: Executed | Q128: Web
A129: Arun Venkatesan | B129: ICICI | C129: 45040 | D129: 145161526 | E129: Purchase-SIP | F129: ICICI PRUDENTIAL MUTUAL FUND | G129: ICICI Prudential Multi-Asset Fund - IDCW | H129: 15070068/41 | I129: 25.2627 | J129: 45040 | K129: N | L129: 5000 | M129: 0 | N129: 197.91 | O129: Executed | Q129: SYS
A130: Arun Venkatesan | B130: ICICI | C130: 45042 | D130: 145334442 | E130: Div-Reinvestment | F130: HDFC ASSET MANAGEMENT COMPANY LIMITED | G130: HDFC Balanced Advantage Fund - Regular Plan - IDCW | H130: 16747427/33 | I130: 29.691 | J130: 45042 | K130: Y | L130: 2076.75 | M130: 0 | N130: 69.942 | O130: Executed | Q130: SYS/DBC
A131: Arun Venkatesan | B131: ICICI | C131: 45044 | D131: 145377422 | E131: Purchase-SIP | F131: HDFC ASSET MANAGEMENT COMPANY LIMITED | G131: HDFC Balanced Advantage Fund - Regular Plan - IDCW | H131: 16747427/33 | I131: 30.056 | J131: 45044 | K131: Y | L131: 5000 | M131: 0 | N131: 166.348 | O131: Executed | Q131: SYS
A132: Arun Venkatesan | B132: ICICI | C132: 45070 | D132: 146772633 | E132: Purchase-SIP | F132: ICICI PRUDENTIAL MUTUAL FUND | G132: ICICI Prudential Multi-Asset Fund - IDCW | H132: 15070068/41 | I132: 25.6663 | J132: 45070 | K132: N | L132: 5000 | M132: 0 | N132: 194.798 | O132: Executed | Q132: SYS
A133: Arun Venkatesan | B133: ICICI | C133: 45072 | D133: 146950338 | E133: Div-Reinvestment | F133: HDFC ASSET MANAGEMENT COMPANY LIMITED | G133: HDFC Balanced Advantage Fund - Regular Plan - IDCW | H133: 16747427/33 | I133: 30.069 | J133: 45072 | K133: Y | L133: 1710.09 | M133: 0 | N133: 56.869 | O133: Executed | Q133: SYS/DBC
A134: Arun Venkatesan | B134: ICICI | C134: 45074 | D134: 146986069 | E134: Purchase-SIP | F134: HDFC ASSET MANAGEMENT COMPANY LIMITED | G134: HDFC Balanced Advantage Fund - Regular Plan - IDCW | H134: 16747427/33 | I134: 30.314 | J134: 45075 | K134: Y | L134: 5000 | M134: 0 | N134: 164.932 | O134: Executed | Q134: SYS
A135: Arun Venkatesan | B135: ICICI | C135: 45075 | D135: 147008695 | E135: Purchase | F135: HDFC ASSET MANAGEMENT COMPANY LIMITED | G135: HDFC Defence Fund Regular Plan Growth | H135: 22394108/70 | I135: 10 | J135: 45079 | K135: N | L135: 5000 | M135: 0 | N135: 499.975 | O135: Executed | Q135: CNT
A136: Arun Venkatesan | B136: ICICI | C136: 45075 | D136: 147008699 | E136: Purchase | F136: HDFC ASSET MANAGEMENT COMPANY LIMITED | G136: HDFC Defence Fund Regular Plan Growth | H136: 22394108/70 | I136: 10 | J136: 45079 | K136: N | L136: 5000 | M136: 0 | N136: 499.975 | O136: Executed | Q136: CNT
A137: Arun Venkatesan | B137: ICICI | C137: 45075 | D137: 147008704 | E137: Purchase | F137: HDFC ASSET MANAGEMENT COMPANY LIMITED | G137: HDFC Defence Fund Regular Plan Growth | H137: 22394108/70 | I137: 10 | J137: 45079 | K137: N | L137: 5000 | M137: 0 | N137: 499.975 | O137: Executed | Q137: CNT
A138: Arun Venkatesan | B138: ICICI | C138: 45075 | D138: 147008708 | E138: Purchase | F138: HDFC ASSET MANAGEMENT COMPANY LIMITED | G138: HDFC Defence Fund Regular Plan Growth | H138: 22394108/70 | I138: 10 | J138: 45079 | K138: N | L138: 5000 | M138: 0 | N138: 499.975 | O138: Executed | Q138: CNT
A139: Arun Venkatesan | B139: ICICI | C139: 45085 | D139: 147624642 | E139: Redemption | F139: ADITYA BIRLA SUN LIFE ASSET MANAGEMENT COMPANY LTD | G139: ADITYA BIRLA SUN LIFE ELSS TAX SAVER FUND - IDCW | H139: 1039297412 | I139: 156.83 | J139: 45085 | K139: N | L139: 4628.68 | M139: 0 | N139: 29.514 | O139: Executed | Q139: Web
A140: Arun Venkatesan | B140: ICICI | C140: 45085 | D140: 147624681 | E140: Redemption | F140: ADITYA BIRLA SUN LIFE ASSET MANAGEMENT COMPANY LTD | G140: Aditya Birla Sun Life Savings Fund - Growth | H140: 1039297412 | I140: 470.865 | J140: 45086 | K140: N | L140: 113316.96 | M140: 0 | N140: 240.657 | O140: Executed | Q140: Web
A141: Arun Venkatesan | B141: ICICI | C141: 45085 | D141: 147625043 | E141: Redemption | F141: AXIS ASSET MANAGEMENT COMPANY LIMITED | G141: AXIS LARGE CAP FUND - Growth | H141: 91087813195 | I141: 44.33 | J141: 45086 | K141: N | L141: 35771.3 | M141: 0 | N141: 806.932 | O141: Executed | Q141: Web
A142: Arun Venkatesan | B142: ICICI | C142: 45085 | D142: 147625058 | E142: Redemption | F142: AXIS ASSET MANAGEMENT COMPANY LIMITED | G142: Axis Midcap Fund - Growth | H142: 91087813195 | I142: 71.75 | J142: 45086 | K142: N | L142: 141962.42 | M142: 0 | N142: 1978.663 | O142: Executed | Q142: Web
A143: Arun Venkatesan | B143: ICICI | C143: 45085 | D143: 147625081 | E143: Redemption | F143: ICICI PRUDENTIAL MUTUAL FUND | G143: ICICI Prudential Esg Exclusionary Strategy Fund Growth | H143: 15070068/41 | I143: 14.02 | J143: 45086 | K143: N | L143: 132507.55 | M143: 0 | N143: 9451.323 | O143: Executed | Q143: Web
A144: Arun Venkatesan | B144: ICICI | C144: 45101 | D144: 148478613 | E144: Purchase-SIP | F144: ICICI PRUDENTIAL MUTUAL FUND | G144: ICICI Prudential Multi-Asset Fund - IDCW | H144: 15070068/41 | I144: 25.993 | J144: 45103 | K144: N | L144: 5000 | M144: 0 | N144: 192.35 | O144: Executed | Q144: SYS
A145: Arun Venkatesan | B145: ICICI | C145: 45104 | D145: 148696762 | E145: Div-Reinvestment | F145: HDFC ASSET MANAGEMENT COMPANY LIMITED | G145: HDFC Balanced Advantage Fund - Regular Plan - IDCW | H145: 16747427/33 | I145: 30.631 | J145: 45104 | K145: Y | L145: 1964.11 | M145: 0 | N145: 64.118 | O145: Executed | Q145: SYS/DBC
A146: Arun Venkatesan | B146: ICICI | C146: 45105 | D146: 148680093 | E146: Purchase-SIP | F146: HDFC ASSET MANAGEMENT COMPANY LIMITED | G146: HDFC Balanced Advantage Fund - Regular Plan - IDCW | H146: 16747427/33 | I146: 30.961 | J146: 45105 | K146: Y | L146: 5000 | M146: 0 | N146: 161.485 | O146: Executed | Q146: SYS
A147: Arun Venkatesan | B147: ICICI | C147: 45131 | D147: 150193074 | E147: Purchase-SIP | F147: ICICI PRUDENTIAL MUTUAL FUND | G147: ICICI Prudential Multi-Asset Fund - IDCW | H147: 15070068/41 | I147: 26.9361 | J147: 45131 | K147: N | L147: 5000 | M147: 0 | N147: 185.615 | O147: Executed | Q147: SYS
A148: Arun Venkatesan | B148: ICICI | C148: 45133 | D148: 150643447 | E148: Div-Reinvestment | F148: HDFC ASSET MANAGEMENT COMPANY LIMITED | G148: HDFC Balanced Advantage Fund - Regular Plan - IDCW | H148: 16747427/33 | I148: 31.876 | J148: 45133 | K148: Y | L148: 2011 | M148: 0 | N148: 63.085 | O148: Executed | Q148: SYS/DBC
A149: Arun Venkatesan | B149: ICICI | C149: 45135 | D149: 150421064 | E149: Purchase-SIP | F149: HDFC ASSET MANAGEMENT COMPANY LIMITED | G149: HDFC Balanced Advantage Fund - Regular Plan - IDCW | H149: 16747427/33 | I149: 32.078 | J149: 45135 | K149: Y | L149: 5000 | M149: 0 | N149: 155.862 | O149: Executed | Q149: SYS
A150: Arun Venkatesan | B150: ICICI | C150: 45162 | D150: 152066591 | E150: Purchase-SIP | F150: ICICI PRUDENTIAL MUTUAL FUND | G150: ICICI Prudential Multi-Asset Fund - IDCW | H150: 15070068/41 | I150: 27.2648 | J150: 45162 | K150: N | L150: 5000 | M150: 0 | N150: 183.377 | O150: Executed | Q150: SYS
A151: Arun Venkatesan | B151: ICICI | C151: 45164 | D151: 152289607 | E151: Div-Reinvestment | F151: HDFC ASSET MANAGEMENT COMPANY LIMITED | G151: HDFC Balanced Advantage Fund - Regular Plan - IDCW | H151: 16747427/33 | I151: 32.223 | J151: 45164 | K151: Y | L151: 2056.35 | M151: 0 | N151: 63.813 | O151: Executed | Q151: SYS/DBC
A152: Arun Venkatesan | B152: ICICI | C152: 45166 | D152: 152270852 | E152: Purchase-SIP | F152: HDFC ASSET MANAGEMENT COMPANY LIMITED | G152: HDFC Balanced Advantage Fund - Regular Plan - IDCW | H152: 16747427/33 | I152: 32.349 | J152: 45166 | K152: Y | L152: 5000 | M152: 0 | N152: 154.557 | O152: Executed | Q152: SYS
A153: Arun Venkatesan | B153: ICICI | C153: 45193 | D153: 153841221 | E153: Purchase-SIP | F153: ICICI PRUDENTIAL MUTUAL FUND | G153: ICICI Prudential Multi-Asset Fund - IDCW | H153: 15070068/41 | I153: 27.6214 | J153: 45194 | K153: N | L153: 5000 | M153: 0 | N153: 181.01 | O153: Executed | Q153: SYS
A154: Arun Venkatesan | B154: ICICI | C154: 45195 | D154: 154033116 | E154: Div-Reinvestment | F154: HDFC ASSET MANAGEMENT COMPANY LIMITED | G154: HDFC Balanced Advantage Fund - Regular Plan - IDCW | H154: 16747427/33 | I154: 33.018 | J154: 45195 | K154: Y | L154: 2101.58 | M154: 0 | N154: 63.646 | O154: Executed | Q154: SYS/DBC
... A259: Kurinji Malar Paranthaman | B259: ICICI | C259: 44990.294 | D259: 142608788 | E259: Purchase | F259: HDFC ASSET MANAGEMENT COMPANY LIMITED | G259: HDFC Business Cycle Fund Regular IDCW | H259: 19582098/10 | I259: 9.695 | J259: 44991 | K259: N | L259: 50000 | M259: 0 | N259: 5157.04 | O259: Executed | Q259: Web
A260: Kurinji Malar Paranthaman | B260: ICICI | C260: 45639 | D260: 186302558 | E260: Purchase-SIP | F260: NAVI MUTUAL FUND | G260: Navi Nifty 50 Index Fund Regular Plan Growth | H260: 9778075610 | I260: 15.9364 | J260: 45639 | K260: N | L260: 5000 | M260: 0 | N260: 313.731 | O260: Executed | Q260: SYS
A261: Kurinji Malar Paranthaman | B261: ICICI | C261: 45321.5 | D261: 163432671 | E261: Purchase | F261: FRANKLIN TEMPLETON MUTUAL FUND | G261: Franklin India Small Cap Fund-Growth | H261: 34055597 | I261: 148.6451 | J261: 45321 | K261: N | L261: 30000 | M261: 0 | N261: 201.813 | O261: Executed | Q261: Web
A262: Kurinji Malar Paranthaman | B262: ICICI | C262: 46004 | D262: 212014302 | E262: Purchase-SIP | F262: NAVI MUTUAL FUND | G262: Navi Nifty 50 Index Fund Regular Plan Growth | H262: 9778075610 | I262: 16.8984 | J262: 46006 | K262: N | L262: 5000 | M262: 0 | N262: 295.871 | O262: Executed | Q262: SYS
A263: Kurinji Malar Paranthaman | B263: ICICI | C263: 45974 | D263: 209848377 | E263: Purchase-SIP | F263: NAVI MUTUAL FUND | G263: Navi Nifty 50 Index Fund Regular Plan Growth | H263: 9778075610 | I263: 16.8063 | J263: 45974 | K263: N | L263: 5000 | M263: 0 | N263: 297.493 | O263: Executed | Q263: SYS
A264: Kurinji Malar Paranthaman | B264: ICICI | C264: 45943 | D264: 207709421 | E264: Purchase-SIP | F264: NAVI MUTUAL FUND | G264: Navi Nifty 50 Index Fund Regular Plan Growth | H264: 9778075610 | I264: 0 | J264: 46019 | K264: N | L264: 5000 | M264: 0 | N264: 0 | O264: Rejected | Q264: SYS
A265: Kurinji Malar Paranthaman | B265: ICICI | C265: 45913 | D265: 205571077 | E265: Purchase-SIP | F265: NAVI MUTUAL FUND | G265: Navi Nifty 50 Index Fund Regular Plan Growth | H265: 9778075610 | I265: 16.266 | J265: 45915 | K265: N | L265: 5000 | M265: 0 | N265: 307.374 | O265: Executed | Q265: SYS
A266: Kurinji Malar Paranthaman | B266: ICICI | C266: 45882 | D266: 203455741 | E266: Purchase-SIP | F266: NAVI MUTUAL FUND | G266: Navi Nifty 50 Index Fund Regular Plan Growth | H266: 9778075610 | I266: 15.9673 | J266: 45882 | K266: N | L266: 5000 | M266: 0 | N266: 313.124 | O266: Executed | Q266: SYS
A267: Kurinji Malar Paranthaman | B267: ICICI | C267: 45851 | D267: 201277056 | E267: Purchase-SIP | F267: NAVI MUTUAL FUND | G267: Navi Nifty 50 Index Fund Regular Plan Growth | H267: 9778075610 | I267: 16.2315 | J267: 45852 | K267: N | L267: 5000 | M267: 0 | N267: 308.028 | O267: Executed | Q267: SYS
A268: Kurinji Malar Paranthaman | B268: ICICI | C268: 45821 | D268: 199137829 | E268: Purchase-SIP | F268: NAVI MUTUAL FUND | G268: Navi Nifty 50 Index Fund Regular Plan Growth | H268: 9778075610 | I268: 15.9659 | J268: 45821 | K268: N | L268: 5000 | M268: 0 | N268: 313.152 | O268: Executed | Q268: SYS
A269: Kurinji Malar Paranthaman | B269: ICICI | C269: 45790 | D269: 197008268 | E269: Purchase-SIP | F269: NAVI MUTUAL FUND | G269: Navi Nifty 50 Index Fund Regular Plan Growth | H269: 9778075610 | I269: 15.8326 | J269: 45790 | K269: N | L269: 5000 | M269: 0 | N269: 315.788 | O269: Executed | Q269: SYS
A270: Kurinji Malar Paranthaman | B270: ICICI | C270: 45760 | D270: 194768937 | E270: Purchase-SIP | F270: NAVI MUTUAL FUND | G270: Navi Nifty 50 Index Fund Regular Plan Growth | H270: 9778075610 | I270: 15.0282 | J270: 45762 | K270: N | L270: 5000 | M270: 0 | N270: 332.691 | O270: Executed | Q270: SYS
A271: Kurinji Malar Paranthaman | B271: ICICI | C271: 45729 | D271: 192727230 | E271: Purchase-SIP | F271: NAVI MUTUAL FUND | G271: Navi Nifty 50 Index Fund Regular Plan Growth | H271: 9778075610 | I271: 14.4347 | J271: 45729 | K271: N | L271: 5000 | M271: 0 | N271: 346.37 | O271: Executed | Q271: SYS
... A273: Kurinji Malar Paranthaman | B273: ICICI | C273: 45670 | D273: 188499345 | E273: Purchase-SIP | F273: NAVI MUTUAL FUND | G273: Navi Nifty 50 Index Fund Regular Plan Growth | H273: 9778075610 | I273: 14.8503 | J273: 45670 | K273: N | L273: 5000 | M273: 0 | N273: 336.677 | O273: Executed | Q273: SYS

Sheet Mutual Fund Dividend
A1: Person | B1: Account | C1: AMC Name | D1: Scheme Name | E1: Record Date | F1: Dividend Per Unit(Rs./Unit) | G1: NAV as on Record Date | H1: Gross Amount(rs.) | I1: Units | J1: Dividend Type | K1: Missing Date
A2: Arun Venkatesan | B2: ICICI | C2: ADITYA BIRLA SUN LIFE ASSET MANAGEMENT COMPANY LTD | D2: ADITYA BIRLA SUN LIFE ELSS TAX SAVER FUND - IDCW | E2: 43798 | F2: 0 | G2: 153.16 | H2: 277.26 | I2: 0 | J2: DP
A3: Arun Venkatesan | B3: ICICI | C3: HDFC ASSET MANAGEMENT COMPANY LIMITED | D3: HDFC Balanced Advantage Fund - Regular Plan - IDCW | E3: 43949 | F3: 0 | G3: 19.803 | H3: 55.47 | I3: 2.801 | J3: DR | K3: {=_xlfn.XLOOKUP( 1, ('Mutual Fund Transaction'!G:G='Mutual Fund Dividend'!D144) * ('Mutual Fund Transaction'!L:L='Mutual Fund Dividend'!H144) * ('Mutual Fund Transaction'!N:N='Mutual Fund Dividend'!I144), 'Mutual Fund Transaction'!C:C, "" )}
A4: Arun Venkatesan | B4: ICICI | C4: HDFC ASSET MANAGEMENT COMPANY LIMITED | D4: HDFC Balanced Advantage Fund - Regular Plan - IDCW | E4: 43978 | F4: 0 | G4: 18.888 | H4: 294.21 | I4: 15.577 | J4: DR | K4: {=_xlfn.XLOOKUP( 1, ('Mutual Fund Transaction'!G:G='Mutual Fund Dividend'!D143) * ('Mutual Fund Transaction'!L:L='Mutual Fund Dividend'!H143) * ('Mutual Fund Transaction'!N:N='Mutual Fund Dividend'!I143), 'Mutual Fund Transaction'!C:C, "" )} -> 45987
A5: Arun Venkatesan | B5: ICICI | C5: HDFC ASSET MANAGEMENT COMPANY LIMITED | D5: HDFC Balanced Advantage Fund - Regular Plan - IDCW | E5: 44008 | F5: 0 | G5: 21.051 | H5: 297.79 | I5: 14.146 | J5: DR | K5: {=_xlfn.XLOOKUP( 1, ('Mutual Fund Transaction'!G:G='Mutual Fund Dividend'!D142) * ('Mutual Fund Transaction'!L:L='Mutual Fund Dividend'!H142) * ('Mutual Fund Transaction'!N:N='Mutual Fund Dividend'!I142), 'Mutual Fund Transaction'!C:C, "" )}
A6: Arun Venkatesan | B6: ICICI | C6: ICICI PRUDENTIAL MUTUAL FUND | D6: ICICI Prudential Multi-Asset Fund - IDCW | E6: 44015 | F6: 0 | G6: 16.8552 | H6: 47.65 | I6: 2.827 | J6: DR | K6: {=_xlfn.XLOOKUP( 1, ('Mutual Fund Transaction'!G:G='Mutual Fund Dividend'!D141) * ('Mutual Fund Transaction'!L:L='Mutual Fund Dividend'!H141) * ('Mutual Fund Transaction'!N:N='Mutual Fund Dividend'!I141), 'Mutual Fund Transaction'!C:C, "" )} -> 45958
A7: Arun Venkatesan | B7: ICICI | C7: HDFC ASSET MANAGEMENT COMPANY LIMITED | D7: HDFC Balanced Advantage Fund - Regular Plan - IDCW | E7: 44040 | F7: 0 | G7: 21.317 | H7: 356.2 | I7: 16.71 | J7: DR | K7: {=_xlfn.XLOOKUP( 1, ('Mutual Fund Transaction'!G:G='Mutual Fund Dividend'!D140) * ('Mutual Fund Transaction'!L:L='Mutual Fund Dividend'!H140) * ('Mutual Fund Transaction'!N:N='Mutual Fund Dividend'!I140), 'Mutual Fund Transaction'!C:C, "" )}
A8: Arun Venkatesan | B8: ICICI | C8: ICICI PRUDENTIAL MUTUAL FUND | D8: ICICI Prudential Multi-Asset Fund - IDCW | E8: 44048 | F8: 0 | G8: 17.2249 | H8: 94.51 | I8: 5.487 | J8: DR | K8: {=_xlfn.XLOOKUP( 1, ('Mutual Fund Transaction'!G:G='Mutual Fund Dividend'!D139) * ('Mutual Fund Transaction'!L:L='Mutual Fund Dividend'!H139) * ('Mutual Fund Transaction'!N:N='Mutual Fund Dividend'!I139), 'Mutual Fund Transaction'!C:C, "" )} -> 45926
A9: Arun Venkatesan | B9: ICICI | C9: HDFC ASSET MANAGEMENT COMPANY LIMITED | D9: HDFC Balanced Advantage Fund - Regular Plan - IDCW | E9: 44069 | F9: 0 | G9: 22.479 | H9: 413.78 | I9: 18.407 | J9: DR | K9: {=_xlfn.XLOOKUP( 1, ('Mutual Fund Transaction'!G:G='Mutual Fund Dividend'!D138) * ('Mutual Fund Transaction'!L:L='Mutual Fund Dividend'!H138) * ('Mutual Fund Transaction'!N:N='Mutual Fund Dividend'!I138), 'Mutual Fund Transaction'!C:C, "" )}
A10: Arun Venkatesan | B10: ICICI | C10: ICICI PRUDENTIAL MUTUAL FUND | D10: ICICI Prudential Multi-Asset Fund - IDCW | E10: 44082 | F10: 0 | G10: 17.2545 | H10: 139.71 | I10: 0 | J10: DP
A11: Arun Venkatesan | B11: ICICI | C11: HDFC ASSET MANAGEMENT COMPANY LIMITED | D11: HDFC Balanced Advantage Fund - Regular Plan - IDCW | E11: 44100 | F11: 0 | G11: 20.408 | H11: 468.54 | I11: 22.959 | J11: DR | K11: {=_xlfn.XLOOKUP( 1, ('Mutual Fund Transaction'!G:G='Mutual Fund Dividend'!D137) * ('Mutual Fund Transaction'!L:L='Mutual Fund Dividend'!H137) * ('Mutual Fund Transaction'!N:N='Mutual Fund Dividend'!I137), 'Mutual Fund Transaction'!C:C, "" )} -> 45895
A12: Arun Venkatesan | B12: ICICI | C12: ICICI PRUDENTIAL MUTUAL FUND | D12: ICICI Prudential Multi-Asset Fund - IDCW | E12: 44109 | F12: 0 | G12: 16.7074 | H12: 189.56 | I12: 0 | J12: DP
A13: Arun Venkatesan | B13: ICICI | C13: HDFC ASSET MANAGEMENT COMPANY LIMITED | D13: HDFC Balanced Advantage Fund - Regular Plan - IDCW | E13: 44131 | F13: 0 | G13: 21.028 | H13: 529.08 | I13: 25.161 | J13: DR | K13: {=_xlfn.XLOOKUP( 1, ('Mutual Fund Transaction'!G:G='Mutual Fund Dividend'!D136) * ('Mutual Fund Transaction'!L:L='Mutual Fund Dividend'!H136) * ('Mutual Fund Transaction'!N:N='Mutual Fund Dividend'!I136), 'Mutual Fund Transaction'!C:C, "" )}
A14: Arun Venkatesan | B14: ICICI | C14: ICICI PRUDENTIAL MUTUAL FUND | D14: ICICI Prudential Multi-Asset Fund - IDCW | E14: 44137 | F14: 0 | G14: 16.6284 | H14: 237.9 | I14: 0 | J14: DP
A15: Arun Venkatesan | B15: ICICI | C15: ADITYA BIRLA SUN LIFE ASSET MANAGEMENT COMPANY LTD | D15: ADITYA BIRLA SUN LIFE ELSS TAX SAVER FUND - IDCW | E15: 44160 | F15: 0 | G15: 149.92 | H15: 242.61 | I15: 0 | J15: DP
A16: Arun Venkatesan | B16: ICICI | C16: HDFC ASSET MANAGEMENT COMPANY LIMITED | D16: HDFC Balanced Advantage Fund - Regular Plan - IDCW | E16: 44161 | F16: 0 | G16: 23.113 | H16: 589.81 | I16: 25.519 | J16: DR | K16: {=_xlfn.XLOOKUP( 1, ('Mutual Fund Transaction'!G:G='Mutual Fund Dividend'!D135) * ('Mutual Fund Transaction'!L:L='Mutual Fund Dividend'!H135) * ('Mutual Fund Transaction'!N:N='Mutual Fund Dividend'!I135), 'Mutual Fund Transaction'!C:C, "" )}
A17: Arun Venkatesan | B17: ICICI | C17: ICICI PRUDENTIAL MUTUAL FUND | D17: ICICI Prudential Multi-Asset Fund - IDCW | E17: 44167 | F17: 0 | G17: 18.259 | H17: 282.81 | I17: 0 | J17: DP
A18: Arun Venkatesan | B18: ICICI | C18: HDFC ASSET MANAGEMENT COMPANY LIMITED | D18: HDFC Balanced Advantage Fund - Regular Plan - IDCW | E18: 44194 | F18: 0 | G18: 24.85 | H18: 690.49 | I18: 27.785 | J18: DR | K18: {=_xlfn.XLOOKUP( 1, ('Mutual Fund Transaction'!G:G='Mutual Fund Dividend'!D134) * ('Mutual Fund Transaction'!L:L='Mutual Fund Dividend'!H134) * ('Mutual Fund Transaction'!N:N='Mutual Fund Dividend'!I134), 'Mutual Fund Transaction'!C:C, "" )} -> 45864
A19: Arun Venkatesan | B19: ICICI | C19: ICICI PRUDENTIAL MUTUAL FUND | D19: ICICI Prudential Multi-Asset Fund - IDCW | E19: 44200 | F19: 0 | G19: 19.5936 | H19: 324.71 | I19: 0 | J19: DP
A20: Arun Venkatesan | B20: ICICI | C20: HDFC ASSET MANAGEMENT COMPANY LIMITED | D20: HDFC Balanced Advantage Fund - Regular Plan - IDCW | E20: 44222 | F20: 0 | G20: 25.074 | H20: 371.88 | I20: 14.831 | J20: DR | K20: {=_xlfn.XLOOKUP( 1, ('Mutual Fund Transaction'!G:G='Mutual Fund Dividend'!D133) * ('Mutual Fund Transaction'!L:L='Mutual Fund Dividend'!H133) * ('Mutual Fund Transaction'!N:N='Mutual Fund Dividend'!I133), 'Mutual Fund Transaction'!C:C, "" )}
A21: Arun Venkatesan | B21: ICICI | C21: ICICI PRUDENTIAL MUTUAL FUND | D21: ICICI Prudential Multi-Asset Fund - IDCW | E21: 44229 | F21: 0 | G21: 19.9224 | H21: 339.11 | I21: 0 | J21: DP
A22: Arun Venkatesan | B22: ICICI | C22: HDFC ASSET MANAGEMENT COMPANY LIMITED | D22: HDFC Balanced Advantage Fund - Regular Plan - IDCW | E22: 44253 | F22: 0 | G22: 27.677 | H22: 690.69 | I22: 24.954 | J22: DR | K22: {=_xlfn.XLOOKUP( 1, ('Mutual Fund Transaction'!G:G='Mutual Fund Dividend'!D132) * ('Mutual Fund Transaction'!L:L='Mutual Fund Dividend'!H132) * ('Mutual Fund Transaction'!N:N='Mutual Fund Dividend'!I132), 'Mutual Fund Transaction'!C:C, "" )} -> 45834
A23: Arun Venkatesan | B23: ICICI | C23: ICICI PRUDENTIAL MUTUAL FUND | D23: ICICI Prudential Multi-Asset Fund - IDCW | E23: 44257 | F23: 0 | G23: 21.132 | H23: 374.31 | I23: 0 | J23: DP
A24: Arun Venkatesan | B24: ICICI | C24: HDFC ASSET MANAGEMENT COMPANY LIMITED | D24: HDFC Balanced Advantage Fund - Regular Plan - IDCW | E24: 44281 | F24: 0 | G24: 25.886 | H24: 734.47 | I24: 28.372 | J24: DR | K24: {=_xlfn.XLOOKUP( 1, ('Mutual Fund Transaction'!G:G='Mutual Fund Dividend'!D131) * ('Mutual Fund Transaction'!L:L='Mutual Fund Dividend'!H131) * ('Mutual Fund Transaction'!N:N='Mutual Fund Dividend'!I131), 'Mutual Fund Transaction'!C:C, "" )}
A25: Arun Venkatesan | B25: ICICI | C25: ICICI PRUDENTIAL MUTUAL FUND | D25: ICICI Prudential Multi-Asset Fund - IDCW | E25: 44292 | F25: 0 | G25: 20.5283 | H25: 443.78 | I25: 0 | J25: DP
A26: Arun Venkatesan | B26: ICICI | C26: HDFC ASSET MANAGEMENT COMPANY LIMITED | D26: HDFC Balanced Advantage Fund - Regular Plan - IDCW | E26: 44313 | F26: 0 | G26: 25.696 | H26: 844.68 | I26: 32.87 | J26: DR | K26: {=_xlfn.XLOOKUP( 1, ('Mutual Fund Transaction'!G:G='Mutual Fund Dividend'!D130) * ('Mutual Fund Transaction'!L:L='Mutual Fund Dividend'!H130) * ('Mutual Fund Transaction'!N:N='Mutual Fund Dividend'!I130), 'Mutual Fund Transaction'!C:C, "" )} -> 45804
A27: Arun Venkatesan | B27: ICICI | C27: ICICI PRUDENTIAL MUTUAL FUND | D27: ICICI Prudential Multi-Asset Fund - IDCW | E27: 44319 | F27: 0 | G27: 20.7274 | H27: 483.22 | I27: 0 | J27: DP
A28: Arun Venkatesan | B28: ICICI | C28: HDFC ASSET MANAGEMENT COMPANY LIMITED | D28: HDFC Balanced Advantage Fund - Regular Plan - IDCW | E28: 44342 | F28: 0 | G28: 27.676 | H28: 896.3 | I28: 32.384 | J28: DR | K28: {=_xlfn.XLOOKUP( 1, ('Mutual Fund Transaction'!G:G='Mutual Fund Dividend'!D129) * ('Mutual Fund Transaction'!L:L='Mutual Fund Dividend'!H129) * ('Mutual Fund Transaction'!N:N='Mutual Fund Dividend'!I129), 'Mutual Fund Transaction'!C:C, "" )}
A29: Arun Venkatesan | B29: ICICI | C29: ICICI PRUDENTIAL MUTUAL FUND | D29: ICICI Prudential Multi-Asset Fund - IDCW | E29: 44348 | F29: 0 | G29: 21.7737 | H29: 520.33 | I29: 0 | J29: DP
A30: Arun Venkatesan | B30: ICICI | C30: HDFC ASSET MANAGEMENT COMPANY LIMITED | D30: HDFC Balanced Advantage Fund - Regular Plan - IDCW | E30: 44373 | F30: 0 | G30: 28.136 | H30: 945.19 | I30: 33.592 | J30: DR | K30: {=_xlfn.XLOOKUP( 1, ('Mutual Fund Transaction'!G:G='Mutual Fund Dividend'!D128) * ('Mutual Fund Transaction'!L:L='Mutual Fund Dividend'!H128) * ('Mutual Fund Transaction'!N:N='Mutual Fund Dividend'!I128), 'Mutual Fund Transaction'!C:C, "" )} -> 45773
A31: Arun Venkatesan | B31: ICICI | C31: ICICI PRUDENTIAL MUTUAL FUND | D31: ICICI Prudential Multi-Asset Fund - IDCW | E31: 44378 | F31: 0 | G31: 21.7673 | H31: 557.08 | I31: 0 | J31: DP
A32: Arun Venkatesan | B32: ICICI | C32: HDFC ASSET MANAGEMENT COMPANY LIMITED | D32: HDFC Balanced Advantage Fund - Regular Plan - IDCW | E32: 44404 | F32: 0 | G32: 28.31 | H32: 993.73 | I32: 35.1 | J32: DR | K32: {=_xlfn.XLOOKUP( 1, ('Mutual Fund Transaction'!G:G='Mutual Fund Dividend'!D127) * ('Mutual Fund Transaction'!L:L='Mutual Fund Dividend'!H127) * ('Mutual Fund Transaction'!N:N='Mutual Fund Dividend'!I127), 'Mutual Fund Transaction'!C:C, "" )}
A33: Arun Venkatesan | B33: ICICI | C33: ICICI PRUDENTIAL MUTUAL FUND | D33: ICICI Prudential Multi-Asset Fund - IDCW | E33: 44411 | F33: 0 | G33: 22.5292 | H33: 593.56 | I33: 0 | J33: DP
A34: Arun Venkatesan | B34: ICICI | C34: L&T ASSET MANAGEMENT COMPANY | D34: LNT Mid Cap Fund-Regular Plan-IDCW | E34: 44434 | F34: 0 | G34: 55.09 | H34: 16771.91 | I34: 0 | J34: DP
A35: Arun Venkatesan | B35: ICICI | C35: HDFC ASSET MANAGEMENT COMPANY LIMITED | D35: HDFC Balanced Advantage Fund - Regular Plan - IDCW | E35: 44434 | F35: 0 | G35: 27.806 | H35: 570.64 | I35: 20.521 | J35: DR | K35: {=_xlfn.XLOOKUP( 1, ('Mutual Fund Transaction'!G:G='Mutual Fund Dividend'!D126) * ('Mutual Fund Transaction'!L:L='Mutual Fund Dividend'!H126) * ('Mutual Fund Transaction'!N:N='Mutual Fund Dividend'!I126), 'Mutual Fund Transaction'!C:C, "" )} -> 45742
A36: Arun Venkatesan | B36: ICICI | C36: ICICI PRUDENTIAL MUTUAL FUND | D36: ICICI Prudential Multi-Asset Fund - IDCW | E36: 44440 | F36: 0 | G36: 22.8851 | H36: 629.42 | I36: 0 | J36: DP
A37: Arun Venkatesan | B37: ICICI | C37: HDFC ASSET MANAGEMENT COMPANY LIMITED | D37: HDFC Balanced Advantage Fund - Regular Plan - IDCW | E37: 44467 | F37: 0 | G37: 29.068 | H37: 979.03 | I37: 33.679 | J37: DR | K37: {=_xlfn.XLOOKUP( 1, ('Mutual Fund Transaction'!G:G='Mutual Fund Dividend'!D125) * ('Mutual Fund Transaction'!L:L='Mutual Fund Dividend'!H125) * ('Mutual Fund Transaction'!N:N='Mutual Fund Dividend'!I125), 'Mutual Fund Transaction'!C:C, "" )}
A38: Arun Venkatesan | B38: ICICI | C38: ICICI PRUDENTIAL MUTUAL FUND | D38: ICICI Prudential Multi-Asset Fund - IDCW | E38: 44474 | F38: 0 | G38: 24.4148 | H38: 663.35 | I38: 0 | J38: DP
A39: Arun Venkatesan | B39: ICICI | C39: HDFC ASSET MANAGEMENT COMPANY LIMITED | D39: HDFC Balanced Advantage Fund - Regular Plan - IDCW | E39: 44495 | F39: 0 | G39: 30.065 | H39: 1155.06 | I39: 38.417 | J39: DR | K39: {=_xlfn.XLOOKUP( 1, ('Mutual Fund Transaction'!G:G='Mutual Fund Dividend'!D124) * ('Mutual Fund Transaction'!L:L='Mutual Fund Dividend'!H124) * ('Mutual Fund Transaction'!N:N='Mutual Fund Dividend'!I124), 'Mutual Fund Transaction'!C:C, "" )} -> 45714
A40: Arun Venkatesan | B40: ICICI | C40: ICICI PRUDENTIAL MUTUAL FUND | D40: ICICI Prudential Multi-Asset Fund - IDCW | E40: 44501 | F40: 0 | G40: 24.5488 | H40: 237.69 | I40: 0 | J40: DP
A41: Arun Venkatesan | B41: ICICI | C41: HDFC ASSET MANAGEMENT COMPANY LIMITED | D41: HDFC Balanced Advantage Fund - Regular Plan - IDCW | E41: 44526 | F41: 0 | G41: 29.202 | H41: 1202.83 | I41: 41.188 | J41: DR | K41: {=_xlfn.XLOOKUP( 1, ('Mutual Fund Transaction'!G:G='Mutual Fund Dividend'!D123) * ('Mutual Fund Transaction'!L:L='Mutual Fund Dividend'!H123) * ('Mutual Fund Transaction'!N:N='Mutual Fund Dividend'!I123), 'Mutual Fund Transaction'!C:C, "" )}
A42: Arun Venkatesan | B42: ICICI | C42: ICICI PRUDENTIAL MUTUAL FUND | D42: ICICI Prudential Multi-Asset Fund - IDCW | E42: 44531 | F42: 0 | G42: 23.703 | H42: 655.48 | I42: 0 | J42: DP
A43: Arun Venkatesan | B43: ICICI | C43: HDFC ASSET MANAGEMENT COMPANY LIMITED | D43: HDFC Balanced Advantage Fund - Regular Plan - IDCW | E43: 44558 | F43: 0 | G43: 28.091 | H43: 1254.29 | I43: 44.649 | J43: DR | K43: {=_xlfn.XLOOKUP( 1, ('Mutual Fund Transaction'!G:G='Mutual Fund Dividend'!D122) * ('Mutual Fund Transaction'!L:L='Mutual Fund Dividend'!H122) * ('Mutual Fund Transaction'!N:N='Mutual Fund Dividend'!I122), 'Mutual Fund Transaction'!C:C, "" )} -> 45685
A44: Arun Venkatesan | B44: ICICI | C44: ICICI PRUDENTIAL MUTUAL FUND | D44: ICICI Prudential Multi-Asset Fund - IDCW | E44: 44564 | F44: 0 | G44: 23.888 | H44: 686.84 | I44: 0 | J44: DP
A45: Arun Venkatesan | B45: ICICI | C45: HDFC ASSET MANAGEMENT COMPANY LIMITED | D45: HDFC Balanced Advantage Fund - Regular Plan - IDCW | E45: 44587 | F45: 0 | G45: 28.965 | H45: 1305.82 | I45: 45.08 | J45: DR | K45: {=_xlfn.XLOOKUP( 1, ('Mutual Fund Transaction'!G:G='Mutual Fund Dividend'!D121) * ('Mutual Fund Transaction'!L:L='Mutual Fund Dividend'!H121) * ('Mutual Fund Transaction'!N:N='Mutual Fund Dividend'!I121), 'Mutual Fund Transaction'!C:C, "" )}
A46: Arun Venkatesan | B46: ICICI | C46: ICICI PRUDENTIAL MUTUAL FUND | D46: ICICI Prudential Multi-Asset Fund - IDCW | E46: 44594 | F46: 0 | G46: 24.835 | H46: 716.12 | I46: 0 | J46: DP
A47: Arun Venkatesan | B47: ICICI | C47: ADITYA BIRLA SUN LIFE ASSET MANAGEMENT COMPANY LTD | D47: ADITYA BIRLA SUN LIFE ELSS TAX SAVER FUND - IDCW | E47: 44617 | F47: 0 | G47: 162.41 | H47: 272.15 | I47: 0 | J47: DP
A48: Arun Venkatesan | B48: ICICI | C48: HDFC ASSET MANAGEMENT COMPANY LIMITED | D48: HDFC Balanced Advantage Fund - Regular Plan - IDCW | E48: 44618 | F48: 0 | G48: 27.949 | H48: 1356.21 | I48: 48.522 | J48: DR | K48: {=_xlfn.XLOOKUP( 1, ('Mutual Fund Transaction'!G:G='Mutual Fund Dividend'!D120) * ('Mutual Fund Transaction'!L:L='Mutual Fund Dividend'!H120) * ('Mutual Fund Transaction'!N:N='Mutual Fund Dividend'!I120), 'Mutual Fund Transaction'!C:C, "" )} -> 45653
A49: Arun Venkatesan | B49: ICICI | C49: ICICI PRUDENTIAL MUTUAL FUND | D49: ICICI Prudential Multi-Asset Fund - IDCW | E49: 44622 | F49: 0 | G49: 23.9331 | H49: 747.15 | I49: 0 | J49: DP
A50: Arun Venkatesan | B50: ICICI | C50: HDFC ASSET MANAGEMENT COMPANY LIMITED | D50: HDFC Balanced Advantage Fund - Regular Plan - IDCW | E50: 44646 | F50: 0 | G50: 28.556 | H50: 1408.94 | I50: 49.337 | J50: DR | K50: {=_xlfn.XLOOKUP( 1, ('Mutual Fund Transaction'!G:G='Mutual Fund Dividend'!D119) * ('Mutual Fund Transaction'!L:L='Mutual Fund Dividend'!H119) * ('Mutual Fund Transaction'!N:N='Mutual Fund Dividend'!I119), 'Mutual Fund Transaction'!C:C, "" )}
A51: Arun Venkatesan | B51: ICICI | C51: ICICI PRUDENTIAL MUTUAL FUND | D51: ICICI Prudential Multi-Asset Fund - IDCW | E51: 44655 | F51: 0 | G51: 25.0792 | H51: 862.89 | I51: 0 | J51: DP
A52: Arun Venkatesan | B52: ICICI | C52: HDFC ASSET MANAGEMENT COMPANY LIMITED | D52: HDFC Balanced Advantage Fund - Regular Plan - IDCW | E52: 44677 | F52: 0 | G52: 29.009 | H52: 1624.09 | I52: 55.983 | J52: DR | K52: {=_xlfn.XLOOKUP( 1, ('Mutual Fund Transaction'!G:G='Mutual Fund Dividend'!D118) * ('Mutual Fund Transaction'!L:L='Mutual Fund Dividend'!H118) * ('Mutual Fund Transaction'!N:N='Mutual Fund Dividend'!I118), 'Mutual Fund Transaction'!C:C, "" )} -> 45622
A53: Arun Venkatesan | B53: ICICI | C53: ICICI PRUDENTIAL MUTUAL FUND | D53: ICICI Prudential Multi-Asset Fund - IDCW | E53: 44685 | F53: 0 | G53: 24.3821 | H53: 895.26 | I53: 0 | J53: DP
A54: Arun Venkatesan | B54: ICICI | C54: HDFC ASSET MANAGEMENT COMPANY LIMITED | D54: HDFC Balanced Advantage Fund - Regular Plan - IDCW | E54: 44707 | F54: 0 | G54: 27.681 | H54: 1683.08 | I54: 60.8 | J54: DR | K54: {=_xlfn.XLOOKUP( 1, ('Mutual Fund Transaction'!G:G='Mutual Fund Dividend'!D117) * ('Mutual Fund Transaction'!L:L='Mutual Fund Dividend'!H117) * ('Mutual Fund Transaction'!N:N='Mutual Fund Dividend'!I117), 'Mutual Fund Transaction'!C:C, "" )}
A55: Arun Venkatesan | B55: ICICI | C55: ICICI PRUDENTIAL MUTUAL FUND | D55: ICICI Prudential Multi-Asset Fund - IDCW | E55: 44713 | F55: 0 | G55: 24.1159 | H55: 929.01 | I55: 0 | J55: DP
A56: Arun Venkatesan | B56: ICICI | C56: HDFC ASSET MANAGEMENT COMPANY LIMITED | D56: HDFC Balanced Advantage Fund - Regular Plan - IDCW | E56: 44740 | F56: 0 | G56: 27.326 | H56: 1240.82 | I56: 45.406 | J56: DR | K56: {=_xlfn.XLOOKUP( 1, ('Mutual Fund Transaction'!G:G='Mutual Fund Dividend'!D116) * ('Mutual Fund Transaction'!L:L='Mutual Fund Dividend'!H116) * ('Mutual Fund Transaction'!N:N='Mutual Fund Dividend'!I116), 'Mutual Fund Transaction'!C:C, "" )} -> 45591
A57: Arun Venkatesan | B57: ICICI | C57: ICICI PRUDENTIAL MUTUAL FUND | D57: ICICI Prudential Multi-Asset Fund - IDCW | E57: 44746 | F57: 0 | G57: 23.2677 | H57: 963.8 | I57: 0 | J57: DP
A58: Arun Venkatesan | B58: ICICI | C58: HDFC ASSET MANAGEMENT COMPANY LIMITED | D58: HDFC Balanced Advantage Fund - Regular Plan - IDCW | E58: 44768 | F58: 0 | G58: 28.448 | H58: 1624.07 | I58: 57.086 | J58: DR | K58: {=_xlfn.XLOOKUP( 1, ('Mutual Fund Transaction'!G:G='Mutual Fund Dividend'!D115) * ('Mutual Fund Transaction'!L:L='Mutual Fund Dividend'!H115) * ('Mutual Fund Transaction'!N:N='Mutual Fund Dividend'!I115), 'Mutual Fund Transaction'!C:C, "" )}
A59: Arun Venkatesan | B59: ICICI | C59: ICICI PRUDENTIAL MUTUAL FUND | D59: ICICI Prudential Multi-Asset Fund - IDCW | E59: 44775 | F59: 0 | G59: 24.4354 | H59: 532.43 | I59: 0 | J59: DP
A60: Arun Venkatesan | B60: ICICI | C60: L&T ASSET MANAGEMENT COMPANY | D60: LNT Mid Cap Fund-Regular Plan-IDCW | E60: 44799 | F60: 0 | G60: 54.24 | H60: 17970.05 | I60: 0 | J60: DP
A61: Arun Venkatesan | B61: ICICI | C61: HDFC ASSET MANAGEMENT COMPANY LIMITED | D61: HDFC Balanced Advantage Fund - Regular Plan - IDCW | E61: 44799 | F61: 0 | G61: 29.463 | H61: 1678.21 | I61: 56.957 | J61: DR | K61: {=_xlfn.XLOOKUP( 1, ('Mutual Fund Transaction'!G:G='Mutual Fund Dividend'!D114) * ('Mutual Fund Transaction'!L:L='Mutual Fund Dividend'!H114) * ('Mutual Fund Transaction'!N:N='Mutual Fund Dividend'!I114), 'Mutual Fund Transaction'!C:C, "" )} -> 45561
A62: Arun Venkatesan | B62: ICICI | C62: ICICI PRUDENTIAL MUTUAL FUND | D62: ICICI Prudential Multi-Asset Fund - IDCW | E62: 44805 | F62: 0 | G62: 24.5564 | H62: 926.86 | I62: 0 | J62: DP
A63: Arun Venkatesan | B63: ICICI | C63: HDFC ASSET MANAGEMENT COMPANY LIMITED | D63: HDFC Balanced Advantage Fund - Regular Plan - IDCW | E63: 44831 | F63: 0 | G63: 28.853 | H63: 1731.27 | I63: 60 | J63: DR | K63: {=_xlfn.XLOOKUP( 1, ('Mutual Fund Transaction'!G:G='Mutual Fund Dividend'!D113) * ('Mutual Fund Transaction'!L:L='Mutual Fund Dividend'!H113) * ('Mutual Fund Transaction'!N:N='Mutual Fund Dividend'!I113), 'Mutual Fund Transaction'!C:C, "" )}
A64: Arun Venkatesan | B64: ICICI | C64: ICICI PRUDENTIAL MUTUAL FUND | D64: ICICI Prudential Multi-Asset Fund - IDCW | E64: 44837 | F64: 0 | G64: 24.4239 | H64: 957.14 | I64: 0 | J64: DP
A65: Arun Venkatesan | B65: ICICI | C65: HDFC ASSET MANAGEMENT COMPANY LIMITED | D65: HDFC Balanced Advantage Fund - Regular Plan - IDCW | E65: 44860 | F65: 0 | G65: 29.751 | H65: 1786.24 | I65: 60.037 | J65: DR | K65: {=_xlfn.XLOOKUP( 1, ('Mutual Fund Transaction'!G:G='Mutual Fund Dividend'!D112) * ('Mutual Fund Transaction'!L:L='Mutual Fund Dividend'!H112) * ('Mutual Fund Transaction'!N:N='Mutual Fund Dividend'!I112), 'Mutual Fund Transaction'!C:C, "" )} -> 45531
A66: Arun Venkatesan | B66: ICICI | C66: ICICI PRUDENTIAL MUTUAL FUND | D66: ICICI Prudential Multi-Asset Fund - IDCW | E66: 44869 | F66: 0 | G66: 25.2731 | H66: 985.21 | I66: 0 | J66: DP
A67: Arun Venkatesan | B67: ICICI | C67: HDFC ASSET MANAGEMENT COMPANY LIMITED | D67: HDFC Balanced Advantage Fund - Regular Plan - IDCW | E67: 44891 | F67: 0 | G67: 30.618 | H67: 1839.32 | I67: 60.07 | J67: DR | K67: {=_xlfn.XLOOKUP( 1, ('Mutual Fund Transaction'!G:G='Mutual Fund Dividend'!D111) * ('Mutual Fund Transaction'!L:L='Mutual Fund Dividend'!H111) * ('Mutual Fund Transaction'!N:N='Mutual Fund Dividend'!I111), 'Mutual Fund Transaction'!C:C, "" )}
A68: Arun Venkatesan | B68: ICICI | C68: ICICI PRUDENTIAL MUTUAL FUND | D68: ICICI Prudential Multi-Asset Fund - IDCW | E68: 44900 | F68: 0 | G68: 25.9505 | H68: 1013.51 | I68: 0 | J68: DP
A69: Arun Venkatesan | B69: ICICI | C69: HDFC ASSET MANAGEMENT COMPANY LIMITED | D69: HDFC Balanced Advantage Fund - Regular Plan - IDCW | E69: 44922 | F69: 0 | G69: 29.993 | H69: 1891.25 | I69: 63.053 | J69: DR | K69: {=_xlfn.XLOOKUP( 1, ('Mutual Fund Transaction'!G:G='Mutual Fund Dividend'!D110) * ('Mutual Fund Transaction'!L:L='Mutual Fund Dividend'!H110) * ('Mutual Fund Transaction'!N:N='Mutual Fund Dividend'!I110), 'Mutual Fund Transaction'!C:C, "" )}
A70: Arun Venkatesan | B70: ICICI | C70: ICICI PRUDENTIAL MUTUAL FUND | D70: ICICI Prudential Multi-Asset Fund - IDCW | E70: 44930 | F70: 0 | G70: 25.65 | H70: 1041.8 | I70: 0 | J70: DP
A71: Arun Venkatesan | B71: ICICI | C71: HDFC ASSET MANAGEMENT COMPANY LIMITED | D71: HDFC Balanced Advantage Fund - Regular Plan - IDCW | E71: 44952 | F71: 0 | G71: 29.949 | H71: 1944.78 | I71: 64.933 | J71: DR | K71: {=_xlfn.XLOOKUP( 1, ('Mutual Fund Transaction'!G:G='Mutual Fund Dividend'!D109) * ('Mutual Fund Transaction'!L:L='Mutual Fund Dividend'!H109) * ('Mutual Fund Transaction'!N:N='Mutual Fund Dividend'!I109), 'Mutual Fund Transaction'!C:C, "" )} -> 45499
A72: Arun Venkatesan | B72: ICICI | C72: ICICI PRUDENTIAL MUTUAL FUND | D72: ICICI Prudential Multi-Asset Fund - IDCW | E72: 44960 | F72: 0 | G72: 25.4489 | H72: 1070.12 | I72: 0 | J72: DP
A73: Arun Venkatesan | B73: ICICI | C73: ADITYA BIRLA SUN LIFE ASSET MANAGEMENT COMPANY LTD | D73: ADITYA BIRLA SUN LIFE ELSS TAX SAVER FUND - IDCW | E73: 44979 | F73: 0 | G73: 154.57 | H73: 185.94 | I73: 0 | J73: DP
A74: Arun Venkatesan | B74: ICICI | C74: HDFC ASSET MANAGEMENT COMPANY LIMITED | D74: HDFC Balanced Advantage Fund - Regular Plan - IDCW | E74: 44985 | F74: 0 | G74: 29.251 | H74: 1999.64 | I74: 68.358 | J74: DR | K74: {=_xlfn.XLOOKUP( 1, ('Mutual Fund Transaction'!G:G='Mutual Fund Dividend'!D108) * ('Mutual Fund Transaction'!L:L='Mutual Fund Dividend'!H108) * ('Mutual Fund Transaction'!N:N='Mutual Fund Dividend'!I108), 'Mutual Fund Transaction'!C:C, "" )}
A75: Arun Venkatesan | B75: ICICI | C75: ICICI PRUDENTIAL MUTUAL FUND | D75: ICICI Prudential Multi-Asset Fund - IDCW | E75: 44988 | F75: 0 | G75: 25.1471 | H75: 1099.05 | I75: 0 | J75: DP
A76: Arun Venkatesan | B76: ICICI | C76: HDFC ASSET MANAGEMENT COMPANY LIMITED | D76: HDFC Balanced Advantage Fund - Regular Plan - IDCW | E76: 45013 | F76: 0 | G76: 28.828 | H76: 2055.93 | I76: 71.314 | J76: DR | K76: {=_xlfn.XLOOKUP( 1, ('Mutual Fund Transaction'!G:G='Mutual Fund Dividend'!D107) * ('Mutual Fund Transaction'!L:L='Mutual Fund Dividend'!H107) * ('Mutual Fund Transaction'!N:N='Mutual Fund Dividend'!I107), 'Mutual Fund Transaction'!C:C, "" )} -> 45469
A77: Arun Venkatesan | B77: ICICI | C77: ICICI PRUDENTIAL MUTUAL FUND | D77: ICICI Prudential Multi-Asset Fund - IDCW | E77: 45021 | F77: 0 | G77: 25.3092 | H77: 1253.39 | I77: 0 | J77: DP
A78: Arun Venkatesan | B78: ICICI | C78: HDFC ASSET MANAGEMENT COMPANY LIMITED | D78: HDFC Balanced Advantage Fund - Regular Plan - IDCW | E78: 45042 | F78: 0 | G78: 29.691 | H78: 2076.75 | I78: 69.942 | J78: DR | K78: {=_xlfn.XLOOKUP( 1, ('Mutual Fund Transaction'!G:G='Mutual Fund Dividend'!D106) * ('Mutual Fund Transaction'!L:L='Mutual Fund Dividend'!H106) * ('Mutual Fund Transaction'!N:N='Mutual Fund Dividend'!I106), 'Mutual Fund Transaction'!C:C, "" )}
A79: Arun Venkatesan | B79: ICICI | C79: ICICI PRUDENTIAL MUTUAL FUND | D79: ICICI Prudential Multi-Asset Fund - IDCW | E79: 45051 | F79: 0 | G79: 25.6297 | H79: 1285.05 | I79: 0 | J79: DP
A80: Arun Venkatesan | B80: ICICI | C80: HDFC ASSET MANAGEMENT COMPANY LIMITED | D80: HDFC Balanced Advantage Fund - Regular Plan - IDCW | E80: 45072 | F80: 0 | G80: 30.069 | H80: 1710.09 | I80: 56.869 | J80: DR | K80: {=_xlfn.XLOOKUP( 1, ('Mutual Fund Transaction'!G:G='Mutual Fund Dividend'!D105) * ('Mutual Fund Transaction'!L:L='Mutual Fund Dividend'!H105) * ('Mutual Fund Transaction'!N:N='Mutual Fund Dividend'!I105), 'Mutual Fund Transaction'!C:C, "" )} -> 45440
A81: Arun Venkatesan | B81: ICICI | C81: ICICI PRUDENTIAL MUTUAL FUND | D81: ICICI Prudential Multi-Asset Fund - IDCW | E81: 45079 | F81: 0 | G81: 25.9308 | H81: 1316.22 | I81: 0 | J81: DP
A82: Arun Venkatesan | B82: ICICI | C82: HDFC ASSET MANAGEMENT COMPANY LIMITED | D82: HDFC Balanced Advantage Fund - Regular Plan - IDCW | E82: 45104 | F82: 0 | G82: 30.631 | H82: 1964.11 | I82: 64.118 | J82: DR | K82: {=_xlfn.XLOOKUP( 1, ('Mutual Fund Transaction'!G:G='Mutual Fund Dividend'!D104) * ('Mutual Fund Transaction'!L:L='Mutual Fund Dividend'!H104) * ('Mutual Fund Transaction'!N:N='Mutual Fund Dividend'!I104), 'Mutual Fund Transaction'!C:C, "" )}
A83: Arun Venkatesan | B83: ICICI | C83: ICICI PRUDENTIAL MUTUAL FUND | D83: ICICI Prudential Multi-Asset Fund - IDCW | E83: 45111 | F83: 0 | G83: 26.4759 | H83: 826 | I83: 0 | J83: DP
A84: Arun Venkatesan | B84: ICICI | C84: HDFC ASSET MANAGEMENT COMPANY LIMITED | D84: HDFC Balanced Advantage Fund - Regular Plan - IDCW | E84: 45133 | F84: 0 | G84: 31.876 | H84: 2011 | I84: 63.085 | J84: DR | K84: {=_xlfn.XLOOKUP( 1, ('Mutual Fund Transaction'!G:G='Mutual Fund Dividend'!D103) * ('Mutual Fund Transaction'!L:L='Mutual Fund Dividend'!H103) * ('Mutual Fund Transaction'!N:N='Mutual Fund Dividend'!I103), 'Mutual Fund Transaction'!C:C, "" )} -> 45408
A85: Arun Venkatesan | B85: ICICI | C85: ICICI PRUDENTIAL MUTUAL FUND | D85: ICICI Prudential Multi-Asset Fund - IDCW | E85: 45142 | F85: 0 | G85: 27.3897 | H85: 1238.69 | I85: 0 | J85: DP | K85: {=_xlfn.XLOOKUP( 1, ('Mutual Fund Transaction'!G:G='Mutual Fund Dividend'!D61) * ('Mutual Fund Transaction'!L:L='Mutual Fund Dividend'!H61), 'Mutual Fund Transaction'!C:C, "" )} -> 44799
A86: Arun Venkatesan | B86: ICICI | C86: HSBC ASSET MANAGEMENT INDIA PVT Ltd | D86: HSBC Midcap Fund IDCW | E86: 45163 | F86: 0 | G86: 59.646 | H86: 23960.74 | I86: 0 | J86: DP | K86: {=_xlfn.XLOOKUP( 1, ('Mutual Fund Transaction'!G:G='Mutual Fund Dividend'!D60) * ('Mutual Fund Transaction'!L:L='Mutual Fund Dividend'!H60), 'Mutual Fund Transaction'!C:C, "" )}
A87: Arun Venkatesan | B87: ICICI | C87: HDFC ASSET MANAGEMENT COMPANY LIMITED | D87: HDFC Balanced Advantage Fund - Regular Plan - IDCW | E87: 45164 | F87: 0 | G87: 32.223 | H87: 2056.35 | I87: 63.813 | J87: DR | K87: {=_xlfn.XLOOKUP( 1, ('Mutual Fund Transaction'!G:G='Mutual Fund Dividend'!D102) * ('Mutual Fund Transaction'!L:L='Mutual Fund Dividend'!H102) * ('Mutual Fund Transaction'!N:N='Mutual Fund Dividend'!I102), 'Mutual Fund Transaction'!C:C, "" )}
A88: Arun Venkatesan | B88: ICICI | C88: ICICI PRUDENTIAL MUTUAL FUND | D88: ICICI Prudential Multi-Asset Fund - IDCW | E88: 45174 | F88: 0 | G88: 27.7423 | H88: 1265.03 | I88: 0 | J88: DP | K88: {=_xlfn.XLOOKUP( 1, ('Mutual Fund Transaction'!G:G='Mutual Fund Dividend'!D58) * ('Mutual Fund Transaction'!L:L='Mutual Fund Dividend'!H58), 'Mutual Fund Transaction'!C:C, "" )} -> 44768
A89: Arun Venkatesan | B89: ICICI | C89: HDFC ASSET MANAGEMENT COMPANY LIMITED | D89: HDFC Balanced Advantage Fund - Regular Plan - IDCW | E89: 45195 | F89: 0 | G89: 33.018 | H89: 2101.58 | I89: 63.646 | J89: DR | K89: {=_xlfn.XLOOKUP( 1, ('Mutual Fund Transaction'!G:G='Mutual Fund Dividend'!D101) * ('Mutual Fund Transaction'!L:L='Mutual Fund Dividend'!H101) * ('Mutual Fund Transaction'!N:N='Mutual Fund Dividend'!I101), 'Mutual Fund Transaction'!C:C, "" )} -> 45378
A90: Arun Venkatesan | B90: ICICI | C90: ICICI PRUDENTIAL MUTUAL FUND | D90: ICICI Prudential Multi-Asset Fund - IDCW | E90: 45204 | F90: 0 | G90: 27.3739 | H90: 1291 | I90: 0 | J90: DP | K90: {=_xlfn.XLOOKUP( 1, ('Mutual Fund Transaction'!G:G='Mutual Fund Dividend'!D56) * ('Mutual Fund Transaction'!L:L='Mutual Fund Dividend'!H56), 'Mutual Fund Transaction'!C:C, "" )} -> 44740
A91: Arun Venkatesan | B91: ICICI | C91: HDFC ASSET MANAGEMENT COMPANY LIMITED | D91: HDFC Balanced Advantage Fund - Regular Plan - IDCW | E91: 45225 | F91: 0 | G91: 32.364 | H91: 2145.77 | I91: 66.298 | J91: DR | K91: {=_xlfn.XLOOKUP( 1, ('Mutual Fund Transaction'!G:G='Mutual Fund Dividend'!D100) * ('Mutual Fund Transaction'!L:L='Mutual Fund Dividend'!H100) * ('Mutual Fund Transaction'!N:N='Mutual Fund Dividend'!I100), 'Mutual Fund Transaction'!C:C, "" )}
A92: Arun Venkatesan | B92: ICICI | C92: ICICI PRUDENTIAL MUTUAL FUND | D92: ICICI Prudential Multi-Asset Fund - IDCW | E92: 45232 | F92: 0 | G92: 27.4426 | H92: 1318.24 | I92: 0 | J92: DP | K92: {=_xlfn.XLOOKUP( 1, ('Mutual Fund Transaction'!G:G='Mutual Fund Dividend'!D54) * ('Mutual Fund Transaction'!L:L='Mutual Fund Dividend'!H54), 'Mutual Fund Transaction'!C:C, "" )} -> 44707
A93: Arun Venkatesan | B93: ICICI | C93: HDFC ASSET MANAGEMENT COMPANY LIMITED | D93: HDFC Balanced Advantage Fund - Regular Plan - IDCW | E93: 45259 | F93: 0 | G93: 33.945 | H93: 2221.02 | I93: 65.427 | J93: DR | K93: {=_xlfn.XLOOKUP( 1, ('Mutual Fund Transaction'!G:G='Mutual Fund Dividend'!D99) * ('Mutual Fund Transaction'!L:L='Mutual Fund Dividend'!H99) * ('Mutual Fund Transaction'!N:N='Mutual Fund Dividend'!I99), 'Mutual Fund Transaction'!C:C, "" )} -> 45349
A94: Arun Venkatesan | B94: ICICI | C94: ICICI PRUDENTIAL MUTUAL FUND | D94: ICICI Prudential Multi-Asset Fund - IDCW | E94: 45265 | F94: 0 | G94: 29.091 | H94: 1343.67 | I94: 0 | J94: DP | K94: {=_xlfn.XLOOKUP( 1, ('Mutual Fund Transaction'!G:G='Mutual Fund Dividend'!D52) * ('Mutual Fund Transaction'!L:L='Mutual Fund Dividend'!H52), 'Mutual Fund Transaction'!C:C, "" )} -> 44677
A95: Arun Venkatesan | B95: ICICI | C95: HDFC ASSET MANAGEMENT COMPANY LIMITED | D95: HDFC Balanced Advantage Fund - Regular Plan - IDCW | E95: 45287 | F95: 0 | G95: 35.997 | H95: 2428.99 | I95: 67.474 | J95: DR | K95: {=_xlfn.XLOOKUP( 1, ('Mutual Fund Transaction'!G:G='Mutual Fund Dividend'!D98) * ('Mutual Fund Transaction'!L:L='Mutual Fund Dividend'!H98) * ('Mutual Fund Transaction'!N:N='Mutual Fund Dividend'!I98), 'Mutual Fund Transaction'!C:C, "" )}
A96: Arun Venkatesan | B96: ICICI | C96: ICICI PRUDENTIAL MUTUAL FUND | D96: ICICI Prudential Multi-Asset Fund - IDCW | E96: 45293 | F96: 0 | G96: 29.5643 | H96: 1367.94 | I96: 0 | J96: DP | K96: {=_xlfn.XLOOKUP( 1, ('Mutual Fund Transaction'!G:G='Mutual Fund Dividend'!D50) * ('Mutual Fund Transaction'!L:L='Mutual Fund Dividend'!H50), 'Mutual Fund Transaction'!C:C, "" )} -> 44646
A97: Arun Venkatesan | B97: ICICI | C97: HDFC ASSET MANAGEMENT COMPANY LIMITED | D97: HDFC Balanced Advantage Fund - Regular Plan - IDCW | E97: 45317 | F97: 0 | G97: 36.756 | H97: 2475.3 | I97: 67.341 | J97: DR | K97: {=_xlfn.XLOOKUP( 1, ('Mutual Fund Transaction'!G:G='Mutual Fund Dividend'!D97) * ('Mutual Fund Transaction'!L:L='Mutual Fund Dividend'!H97) * ('Mutual Fund Transaction'!N:N='Mutual Fund Dividend'!I97), 'Mutual Fund Transaction'!C:C, "" )} -> 45317
A98: Arun Venkatesan | B98: ICICI | C98: ICICI PRUDENTIAL MUTUAL FUND | D98: ICICI Prudential Multi-Asset Fund - IDCW | E98: 45327 | F98: 0 | G98: 30.1235 | H98: 1391.92 | I98: 0 | J98: DP | K98: {=_xlfn.XLOOKUP( 1, ('Mutual Fund Transaction'!G:G='Mutual Fund Dividend'!D48) * ('Mutual Fund Transaction'!L:L='Mutual Fund Dividend'!H48), 'Mutual Fund Transaction'!C:C, "" )} -> 44618
A99: Arun Venkatesan | B99: ICICI | C99: HDFC ASSET MANAGEMENT COMPANY LIMITED | D99: HDFC Balanced Advantage Fund - Regular Plan - IDCW | E99: 45349 | F99: 0 | G99: 37.873 | H99: 2520.65 | I99: 66.552 | J99: DR | K99: {=_xlfn.XLOOKUP( 1, ('Mutual Fund Transaction'!G:G='Mutual Fund Dividend'!D96) * ('Mutual Fund Transaction'!L:L='Mutual Fund Dividend'!H96) * ('Mutual Fund Transaction'!N:N='Mutual Fund Dividend'!I96), 'Mutual Fund Transaction'!C:C, "" )}
A100: Arun Venkatesan | B100: ICICI | C100: ICICI PRUDENTIAL MUTUAL FUND | D100: ICICI Prudential Multi-Asset Fund - IDCW | E100: 45356 | F100: 0 | G100: 30.9113 | H100: 1416.2 | I100: 0 | J100: DP | K100: {=_xlfn.XLOOKUP( 1, ('Mutual Fund Transaction'!G:G='Mutual Fund Dividend'!D46) * ('Mutual Fund Transaction'!L:L='Mutual Fund Dividend'!H46), 'Mutual Fund Transaction'!C:C, "" )}
...

Sheet LIC
A1: Person | B1: Policy No | C1: Agency Code | D1: Premium Due Date | E1: Paid on | F1: Transaction No | G1: Transaction Type | H1: Premium Amount | I1: Late Fee | J1: Total Amount | K1: Benefit Amount
A2: Arun Venkatesan | B2: 734747593 | C2: 2093733 | D2: 39441 | G2: Contribution | H2: 12209 | J2: 12209
A3: Arun Venkatesan | B3: 734747593 | C3: 2093733 | D3: 39624 | G3: Contribution | H3: 12209 | J3: 12209
A4: Arun Venkatesan | B4: 734747593 | C4: 2093733 | D4: 39807 | G4: Contribution | H4: 12209 | J4: 12209
A5: Arun Venkatesan | B5: 734747593 | C5: 2093733 | D5: 39989 | G5: Contribution | H5: 12209 | J5: 12209
A6: Arun Venkatesan | B6: 734747593 | C6: 2093733 | D6: 40172 | G6: Contribution | H6: 12209 | J6: 12209
A7: Arun Venkatesan | B7: 734747593 | C7: 2093733 | D7: 40354 | E7: 40478 | F7: PR0227127800011011 | G7: Contribution | H7: 12209 | I7: 325.6 | J7: 12534.6
A8: Arun Venkatesan | B8: 734747593 | C8: 2093733 | D8: 40537 | E8: 40540 | F8: PR0315311800011011 | G8: Contribution | H8: 12209 | I8: 0 | J8: 12209
A9: Arun Venkatesan | B9: 734747593 | C9: 2093733 | D9: 40719 | E9: 40724 | F9: PR0627595700011112 | G9: Contribution | H9: 12209 | I9: 0 | J9: 12209
A10: Arun Venkatesan | B10: 734747593 | D10: 40858 | E10: 40858 | G10: Benefit | K10: 70000
A11: Arun Venkatesan | B11: 734747593 | C11: 2093733 | D11: 40902 | E11: 40919 | F11: PR1024166300011112 | G11: Contribution | H11: 12209 | I11: 0 | J11: 12209
A12: Arun Venkatesan | B12: 734747593 | C12: 2093733 | D12: 41085 | E12: 41162 | F12: PR0376500200011213 | G12: Contribution | H12: 12209 | I12: 290 | J12: 12499
A13: Arun Venkatesan | B13: 734747593 | C13: 2093733 | D13: 41268 | E13: 41318 | F13: PR0828455100011213 | G13: Contribution | H13: 12209 | I13: 193.3 | J13: 12402.3
A14: Arun Venkatesan | B14: 734747593 | C14: 2093733 | D14: 41450 | E14: 41486 | F14: PR0320070200011314 | G14: Contribution | H14: 12209 | I14: 96.7 | J14: 12305.7
A15: Arun Venkatesan | B15: 734747593 | C15: 2093733 | D15: 41633 | E15: 41647 | F15: PR0911831300011314 | G15: Contribution | H15: 12209 | I15: 0 | J15: 12209
A16: Arun Venkatesan | B16: 734747593 | C16: 2093733 | D16: 41815 | E16: 41830 | F16: PR0337184600011415 | G16: Contribution | H16: 12209 | I16: 0 | J16: 12209
A17: Arun Venkatesan | B17: 734747593 | C17: 2093733 | D17: 41998 | E17: 41990 | F17: PR1003477000011415 | G17: Contribution | H17: 12209 | I17: 0 | J17: 12209
A18: Arun Venkatesan | B18: 734747593 | C18: 2093733 | D18: 42180 | E18: 42207 | F18: PR0441696100011516 | G18: Contribution | H18: 12209 | I18: 0 | J18: 12209
A19: Arun Venkatesan | B19: 734747593 | D19: 42326 | E19: 42326 | G19: Benefit | K19: 70000
A20: Arun Venkatesan | B20: 734747593 | C20: 2093733 | D20: 42363 | E20: 42457 | F20: PR1663506300011516 | G20: Contribution | H20: 12209 | I20: 290 | J20: 12499
A21: Arun Venkatesan | B21: 734747593 | C21: 2093733 | D21: 42546 | E21: 42648 | F21: PR0837513400011617 | G21: Contribution | H21: 12209 | I21: 290 | J21: 12499
A22: Arun Venkatesan | B22: 734747593 | C22: 2093733 | D22: 42729 | G22: Contribution | H22: 12209 | I22: 0 | J22: 12209
A23: Arun Venkatesan | B23: 734747593 | C23: 2093733 | D23: 42911 | E23: 42948 | F23: PR0609717600011718 | G23: Contribution | H23: 12209 | I23: 96.7 | J23: 12305.7
A24: Arun Venkatesan | B24: 734747593 | C24: 2093733 | D24: 43094 | E24: 43137 | F24: PR1925027500011718 | G24: Contribution | H24: 12209 | I24: 96.7 | J24: 12305.7
A25: Arun Venkatesan | B25: 734747593 | C25: 2093733 | D25: 43276 | E25: 43308 | F25: PR0768348500011819 | G25: Contribution | H25: 12209 | I25: 96.7 | J25: 12305.7
A26: Arun Venkatesan | B26: 734747593 | C26: 2093733 | D26: 43459 | E26: 43468 | F26: PR1972146800011819 | G26: Contribution | H26: 12209 | I26: 0 | J26: 12209
A27: Arun Venkatesan | B27: 734747593 | C27: 2093733 | D27: 43641 | E27: 43654 | F27: PR0741573300011920 | G27: Contribution | H27: 12209 | I27: 0 | J27: 12209
A28: Arun Venkatesan | B28: 734747593 | D28: 43780 | E28: 43780 | G28: Benefit | K28: 70000
A29: Arun Venkatesan | B29: 734747593 | C29: 2093733 | D29: 43824 | E29: 43839 | F29: PR2321735300011920 | G29: Contribution | H29: 12209 | I29: 0 | J29: 12209
A30: Arun Venkatesan | B30: 734747593 | C30: 2093733 | D30: 44007 | E30: 44008 | G30: Contribution | H30: 12209 | I30: 0 | J30: 12209
A31: Arun Venkatesan | B31: 734747593 | C31: 2093733 | D31: 44190 | E31: 44228 | F31: PR3626845100012021 | G31: Contribution | H31: 12209 | I31: 77.36 | J31: 12286.36
A32: Arun Venkatesan | B32: 734747593 | C32: 2093733 | D32: 44372 | E32: 44355 | F32: PR0795036300012122 | G32: Contribution | H32: 12209 | I32: 0 | J32: 12209
A33: Arun Venkatesan | B33: 734747593 | C33: 2093733 | D33: 44555 | E33: 44590 | F33: PR3422682700012122 | G33: Contribution | H33: 12209 | I33: 96.7 | J33: 12305.7
A34: Arun Venkatesan | B34: 734747593 | C34: 2093733 | D34: 44737 | E34: 44764 | F34: PR1240784700012223 | G34: Contribution | H34: 12209 | I34: 0 | J34: 12209
A35: Arun Venkatesan | B35: 734747593 | C35: 2093733 | D35: 44920 | E35: 44936 | F35: PR3191769100012223 | G35: Contribution | H35: 12209 | I35: 0 | J35: 12209
A36: Arun Venkatesan | B36: 734747593 | C36: 2093733 | D36: 45102 | E36: 45141 | F36: PR1317778600012324 | G36: Contribution | H36: 12209 | I36: 96.7 | J36: 12305.7
A37: Arun Venkatesan | B37: 734747593 | D37: 45196 | E37: 45196 | G37: Benefit | K37: 70000
A38: Arun Venkatesan | B38: 734747593 | C38: 2093733 | D38: 45285 | E38: 45299 | F38: PR3161970100012324 | G38: Contribution | H38: 12209 | I38: 0 | J38: 12209
A39: Arun Venkatesan | B39: 734747593 | C39: 2093733 | D39: 45468 | E39: 45651 | F39: PR6323470200012425 | G39: Contribution | H39: 12209 | I39: 580 | J39: 12789
A40: Arun Venkatesan | B40: 734747593 | C40: 2093733 | D40: 45651 | E40: 45651 | F40: PR6323470200012425 | G40: Contribution | H40: 12209 | I40: 0 | J40: 12209
A41: Arun Venkatesan | B41: 734747593 | C41: 2093733 | D41: 45833 | E41: 45580 | F41: PR2528478300012526 | G41: Contribution | H41: 12209 | I41: 270 | J41: 12479

Sheet Providend Fund
A1: Person | B1: UAN | C1: Establishment Name | D1: Member ID | E1: Year | F1: Transaction Type | G1: Date | H1: Particulars | I1: Wages | J1: Contribution | K1: EPF Employee | L1: EPF Employer | M1: Pension
A2: Kurinji Malar Paranthaman | B2: 1.00199E+11 | C2: NTT DATA INFORMATION PROCESSING SERVICES PVT LTD | D2: TNAMB00483530000020685 | E2: 2013 | F2: Contribution | G2: 41479 | H2: Cont. For Due-Month 072013 | I2: 3241 | J2: 3241 | K2: 389 | L2: 119 | M2: 270
A3: Kurinji Malar Paranthaman | B3: 1.00199E+11 | C3: NTT DATA INFORMATION PROCESSING SERVICES PVT LTD | D3: TNAMB00483530000020685 | E3: 2013 | F3: Contribution | G3: 41520 | H3: Cont. For Due-Month 082013 | I3: 4476 | J3: 4476 | K3: 537 | L3: 164 | M3: 373
A4: Kurinji Malar Paranthaman | B4: 1.00199E+11 | C4: NTT DATA INFORMATION PROCESSING SERVICES PVT LTD | D4: TNAMB00483530000020685 | E4: 2013 | F4: Contribution | G4: 41540 | H4: Cont. For Due-Month 092013 | I4: 4630 | J4: 4630 | K4: 556 | L4: 170 | M4: 386
A5: Kurinji Malar Paranthaman | B5: 1.00199E+11 | C5: NTT DATA INFORMATION PROCESSING SERVICES PVT LTD | D5: TNAMB00483530000020685 | E5: 2013 | F5: Contribution | G5: 41571 | H5: Cont. For Due-Month 102013 | I5: 4321 | J5: 4321 | K5: 519 | L5: 159 | M5: 360
A6: Kurinji Malar Paranthaman | B6: 1.00199E+11 | C6: NTT DATA INFORMATION PROCESSING SERVICES PVT LTD | D6: TNAMB00483530000020685 | E6: 2013 | F6: Contribution | G6: 41613 | H6: Cont. For Due-Month 112013 | I6: 4630 | J6: 4630 | K6: 556 | L6: 170 | M6: 386
A7: Kurinji Malar Paranthaman | B7: 1.00199E+11 | C7: NTT DATA INFORMATION PROCESSING SERVICES PVT LTD | D7: TNAMB00483530000020685 | E7: 2013 | F7: Contribution | G7: 41634 | H7: Cont. For Due-Month 122013 | I7: 4630 | J7: 4630 | K7: 556 | L7: 170 | M7: 386
A8: Kurinji Malar Paranthaman | B8: 1.00199E+11 | C8: NTT DATA INFORMATION PROCESSING SERVICES PVT LTD | D8: TNAMB00483530000020685 | E8: 2013 | F8: Contribution | G8: 41662 | H8: Cont. For Due-Month 012014 | I8: 4630 | J8: 4630 | K8: 556 | L8: 170 | M8: 386
A9: Kurinji Malar Paranthaman | B9: 1.00199E+11 | C9: NTT DATA INFORMATION PROCESSING SERVICES PVT LTD | D9: TNAMB00483530000020685 | E9: 2013 | F9: Contribution | G9: 41705 | H9: Cont. For Due-Month 022014 | I9: 5324 | J9: 5324 | K9: 639 | L9: 196 | M9: 443
A10: Kurinji Malar Paranthaman | B10: 1.00199E+11 | C10: NTT DATA INFORMATION PROCESSING SERVICES PVT LTD | D10: TNAMB00483530000020685 | E10: 2013 | F10: Contribution | G10: 41723 | H10: Cont. For Due-Month 032014 | I10: 5324 | J10: 5324 | K10: 639 | L10: 196 | M10: 443
A11: Kurinji Malar Paranthaman | B11: 1.00199E+11 | C11: NTT DATA INFORMATION PROCESSING SERVICES PVT LTD | D11: TNAMB00483530000020685 | E11: 2013 | F11: Interest | G11: 41729 | H11: Interest Updated | K11: 134 | L11: 41 | M11: 0
A12: Kurinji Malar Paranthaman | B12: 1.00199E+11 | C12: NTT DATA INFORMATION PROCESSING SERVICES PVT LTD | D12: TNAMB00483530000020685 | E12: 2013 | F12: Closing Balance | G12: 41729 | H12: Closing Balance | K12: 5081 | L12: 1555 | M12: 3433
A13: Kurinji Malar Paranthaman | B13: 1.00199E+11 | C13: NTT DATA INFORMATION PROCESSING SERVICES PVT LTD | D13: TNAMB00483530000020685 | E13: 2014 | F13: Contribution | G13: 41758 | H13: Cont. For Due-Month 042014 | I13: 5324 | J13: 5324 | K13: 639 | L13: 196 | M13: 443
A14: Kurinji Malar Paranthaman | B14: 1.00199E+11 | C14: NTT DATA INFORMATION PROCESSING SERVICES PVT LTD | D14: TNAMB00483530000020685 | E14: 2014 | F14: Contribution | G14: 41779 | H14: Cont. For Due-Month 052014 | I14: 5324 | J14: 5324 | K14: 639 | L14: 196 | M14: 443
A15: Kurinji Malar Paranthaman | B15: 1.00199E+11 | C15: NTT DATA INFORMATION PROCESSING SERVICES PVT LTD | D15: TNAMB00483530000020685 | E15: 2014 | F15: Contribution | G15: 41809 | H15: Cont. For Due-Month 062014 | I15: 5324 | J15: 5324 | K15: 639 | L15: 196 | M15: 443
A16: Kurinji Malar Paranthaman | B16: 1.00199E+11 | C16: NTT DATA INFORMATION PROCESSING SERVICES PVT LTD | D16: TNAMB00483530000020685 | E16: 2014 | F16: Contribution | G16: 41850 | H16: Cont. For Due-Month 072014 | I16: 5324 | J16: 5324 | K16: 639 | L16: 196 | M16: 443
A17: Kurinji Malar Paranthaman | B17: 1.00199E+11 | C17: NTT DATA INFORMATION PROCESSING SERVICES PVT LTD | D17: TNAMB00483530000020685 | E17: 2014 | F17: Contribution | G17: 41876 | H17: Cont. For Due-Month 082014 | I17: 355 | J17: 355 | K17: 43 | L17: 13 | M17: 30
A18: Kurinji Malar Paranthaman | B18: 1.00564E+11 | C18: AGS HEALTH PVT LTD | D18: TNMAS00838510000003341 | E18: 2014 | F18: Contribution | G18: 41887 | H18: Cont. For Due-Month 082014 | I18: 2600 | J18: 2600 | K18: 312 | L18: 95 | M18: 217
A19: Kurinji Malar Paranthaman | B19: 1.00199E+11 | C19: NTT DATA INFORMATION PROCESSING SERVICES PVT LTD | D19: TNAMB00483530000020685 | E19: 2014 | F19: Contribution | G19: 41900 | H19: Cont. For Due-Month 092014 | I19: 0 | J19: 0 | K19: 0 | L19: 0 | M19: 0
A20: Kurinji Malar Paranthaman | B20: 1.00564E+11 | C20: AGS HEALTH PVT LTD | D20: TNMAS00838510000003341 | E20: 2014 | F20: Contribution | G20: 41920 | H20: Cont. For Due-Month 092014 | I20: 6283 | J20: 6283 | K20: 754 | L20: 231 | M20: 523
A21: Kurinji Malar Paranthaman | B21: 1.00564E+11 | C21: AGS HEALTH PVT LTD | D21: TNMAS00838510000003341 | E21: 2014 | F21: Contribution | G21: 42080 | H21: Cont. For Due-Month 032015 | I21: 6500 | J21: 6500 | K21: 780 | L21: 239 | M21: 541
A22: Kurinji Malar Paranthaman | B22: 1.00564E+11 | C22: AGS HEALTH PVT LTD | D22: TNMAS00838510000003341 | E22: 2014 | F22: Contribution | G22: 42088 | H22: Cont. For Due-Month 102014 | I22: 6500 | J22: 6500 | K22: 780 | L22: 239 | M22: 541
A23: Kurinji Malar Paranthaman | B23: 1.00564E+11 | C23: AGS HEALTH PVT LTD | D23: TNMAS00838510000003341 | E23: 2014 | F23: Contribution | G23: 42089 | H23: Cont. For Due-Month 122014 | I23: 6500 | J23: 6500 | K23: 780 | L23: 239 | M23: 541
A24: Kurinji Malar Paranthaman | B24: 1.00564E+11 | C24: AGS HEALTH PVT LTD | D24: TNMAS00838510000003341 | E24: 2014 | F24: Contribution | G24: 42089 | H24: Cont. For Due-Month 012015 | I24: 6500 | J24: 6500 | K24: 780 | L24: 239 | M24: 541
A25: Kurinji Malar Paranthaman | B25: 1.00564E+11 | C25: AGS HEALTH PVT LTD | D25: TNMAS00838510000003341 | E25: 2014 | F25: Contribution | G25: 42089 | H25: Cont. For Due-Month 022015 | I25: 6500 | J25: 6500 | K25: 780 | L25: 239 | M25: 541
A26: Kurinji Malar Paranthaman | B26: 1.00199E+11 | C26: NTT DATA INFORMATION PROCESSING SERVICES PVT LTD | D26: TNAMB00483530000020685 | E26: 2014 | F26: Interest | G26: 42094 | H26: Interest Updated | K26: 624 | L26: 191 | M26: 0
A27: Kurinji Malar Paranthaman | B27: 1.00199E+11 | C27: NTT DATA INFORMATION PROCESSING SERVICES PVT LTD | D27: TNAMB00483530000020685 | E27: 2014 | F27: Closing Balance | G27: 42094 | H27: Closing Balance | K27: 8304 | L27: 2543 | M27: 5235
A28: Kurinji Malar Paranthaman | B28: 1.00564E+11 | C28: AGS HEALTH PVT LTD | D28: TNMAS00838510000003341 | E28: 2014 | F28: Contribution | G28: 42094 | H28: Cont. For Due-Month 112014 | I28: 6067 | J28: 6067 | K28: 728 | L28: 223 | M28: 505
A29: Kurinji Malar Paranthaman | B29: 1.00564E+11 | C29: AGS HEALTH PVT LTD | D29: TNMAS00838510000003341 | E29: 2014 | F29: Interest | G29: 42094 | H29: Interest Updated | K29: 133 | L29: 41 | M29: 0
A30: Kurinji Malar Paranthaman | B30: 1.00564E+11 | C30: AGS HEALTH PVT LTD | D30: TNMAS00838510000003341 | E30: 2014 | F30: Closing Balance | G30: 42094 | H30: Closing Balance | K30: 5827 | L30: 1785 | M30: 3950
A31: Kurinji Malar Paranthaman | B31: 1.00564E+11 | C31: AGS HEALTH PVT LTD | D31: TNMAS00838510000003341 | E31: 2015 | F31: Contribution | G31: 42145 | H31: Cont. For Due-Month 042015 | I31: 6500 | J31: 6500 | K31: 780 | L31: 239 | M31: 541
A32: Kurinji Malar Paranthaman | B32: 1.00564E+11 | C32: AGS HEALTH PVT LTD | D32: TNMAS00838510000003341 | E32: 2015 | F32: Contribution | G32: 42157 | H32: Cont. For Due-Month 052015 | I32: 6500 | J32: 6500 | K32: 780 | L32: 239 | M32: 541
A33: Kurinji Malar Paranthaman | B33: 1.00564E+11 | C33: AGS HEALTH PVT LTD | D33: TNMAS00838510000003341 | E33: 2015 | F33: Contribution | G33: 42185 | H33: Cont. For Due-Month 062015 | I33: 0 | J33: 0 | K33: 1 | L33: 1 | M33: 1
A34: Kurinji Malar Paranthaman | B34: 1.00649E+11 | C34: MEDUSIND SOLUTIONS | D34: TNMAS00497090000002652 | E34: 2015 | F34: Contribution | G34: 42221 | H34: Cont. For Due-Month 062015 | I34: 4925 | J34: 4925 | K34: 591 | L34: 181 | M34: 410
A35: Kurinji Malar Paranthaman | B35: 1.00649E+11 | C35: MEDUSIND SOLUTIONS | D35: TNMAS00497090000002652 | E35: 2015 | F35: Contribution | G35: 42221 | H35: Cont. For Due-Month 072015 | I35: 12723 | J35: 12723 | K35: 1527 | L35: 467 | M35: 1060
A36: Kurinji Malar Paranthaman | B36: 1.00564E+11 | C36: AGS HEALTH PVT LTD | D36: TNMAS00838510000003341 | E36: 2015 | F36: Contribution | G36: 42234 | H36: Cont. For Due-Month 072015 | I36: 0 | J36: 0 | K36: 1 | L36: 1 | M36: 1
A37: Kurinji Malar Paranthaman | B37: 1.00649E+11 | C37: MEDUSIND SOLUTIONS | D37: TNMAS00497090000002652 | E37: 2015 | F37: Contribution | G37: 42243 | H37: Cont. For Due-Month 082015 | I37: 12313 | J37: 12313 | K37: 1478 | L37: 452 | M37: 1026
A38: Kurinji Malar Paranthaman | B38: 1.00649E+11 | C38: MEDUSIND SOLUTIONS | D38: TNMAS00497090000002652 | E38: 2015 | F38: Contribution | G38: 42293 | H38: Cont. For Due-Month 092015 | I38: 12723 | J38: 12723 | K38: 1527 | L38: 467 | M38: 1060
A39: Kurinji Malar Paranthaman | B39: 1.00649E+11 | C39: MEDUSIND SOLUTIONS | D39: TNMAS00497090000002652 | E39: 2015 | F39: Contribution | G39: 42305 | H39: Cont. For Due-Month 102015 | I39: 12298 | J39: 12298 | K39: 1476 | L39: 452 | M39: 1024
A40: Kurinji Malar Paranthaman | B40: 1.00649E+11 | C40: MEDUSIND SOLUTIONS | D40: TNMAS00497090000002652 | E40: 2015 | F40: Contribution | G40: 42338 | H40: Cont. For Due-Month 112015 | I40: 12313 | J40: 12313 | K40: 1478 | L40: 452 | M40: 1026
A41: Kurinji Malar Paranthaman | B41: 1.00649E+11 | C41: MEDUSIND SOLUTIONS | D41: TNMAS00497090000002652 | E41: 2015 | F41: Contribution | G41: 42359 | H41: Cont. For Due-Month 122015 | I41: 12298 | J41: 12298 | K41: 1476 | L41: 452 | M41: 1024
A42: Kurinji Malar Paranthaman | B42: 1.00649E+11 | C42: MEDUSIND SOLUTIONS | D42: TNMAS00497090000002652 | E42: 2015 | F42: Contribution | G42: 42396 | H42: Cont. For Due-Month 012016 | I42: 12723 | J42: 12723 | K42: 1527 | L42: 467 | M42: 1060
... A44: Kurinji Malar Paranthaman | B44: 1.00649E+11 | C44: MEDUSIND SOLUTIONS | D44: TNMAS00497090000002652 | E44: 2015 | F44: Contribution | G44: 42444 | H44: Cont. For Due-Month 032016 | I44: 12723 | J44: 12723 | K44: 1527 | L44: 467 | M44: 1060
A45: Kurinji Malar Paranthaman | B45: 1.00199E+11 | C45: NTT DATA INFORMATION PROCESSING SERVICES PVT LTD | D45: TNAMB00483530000020685 | E45: 2015 | F45: Interest | G45: 42460 | H45: Interest Updated | K45: 731 | L45: 224 | M45: 0
A46: Kurinji Malar Paranthaman | B46: 1.00199E+11 | C46: NTT DATA INFORMATION PROCESSING SERVICES PVT LTD | D46: TNAMB00483530000020685 | E46: 2015 | F46: Closing Balance | G46: 42460 | H46: Closing Balance | K46: 9035 | L46: 2767 | M46: 5235
A47: Kurinji Malar Paranthaman | B47: 1.00649E+11 | C47: MEDUSIND SOLUTIONS | D47: TNMAS00497090000002652 | E47: 2015 | F47: Interest | G47: 42460 | H47: Interest Updated | K47: 435 | L47: 133 | M47: 0
A48: Kurinji Malar Paranthaman | B48: 1.00649E+11 | C48: MEDUSIND SOLUTIONS | D48: TNMAS00497090000002652 | E48: 2015 | F48: Closing Balance | G48: 42460 | H48: Closing Balance | K48: 14569 | L48: 4457 | M48: 9810
A49: Kurinji Malar Paranthaman | B49: 1.00564E+11 | C49: AGS HEALTH PVT LTD | D49: TNMAS00838510000003341 | E49: 2015 | F49: Interest | G49: 42460 | H49: Interest Updated | K49: 633 | L49: 194 | M49: 0
A50: Kurinji Malar Paranthaman | B50: 1.00564E+11 | C50: AGS HEALTH PVT LTD | D50: TNMAS00838510000003341 | E50: 2015 | F50: Closing Balance | G50: 42460 | H50: Closing Balance | K50: 8022 | L50: 2459 | M50: 5034
A51: Kurinji Malar Paranthaman | B51: 1.00649E+11 | C51: MEDUSIND SOLUTIONS | D51: TNMAS00497090000002652 | E51: 2016 | F51: Contribution | G51: 42473 | H51: Cont. For Due-Month 042016 | I51: 12723 | J51: 12723 | K51: 1527 | L51: 467 | M51: 1060
A52: Kurinji Malar Paranthaman | B52: 1.00649E+11 | C52: MEDUSIND SOLUTIONS | D52: TNMAS00497090000002652 | E52: 2016 | F52: Contribution | G52: 42502 | H52: Cont. For Due-Month 052016 | I52: 14039 | J52: 14039 | K52: 1685 | L52: 516 | M52: 1169
A53: Kurinji Malar Paranthaman | B53: 1.00649E+11 | C53: MEDUSIND SOLUTIONS | D53: TNMAS00497090000002652 | E53: 2016 | F53: Contribution | G53: 42534 | H53: Cont. For Due-Month 062016 | I53: 14039 | J53: 14039 | K53: 1685 | L53: 516 | M53: 1169
A54: Kurinji Malar Paranthaman | B54: 1.00649E+11 | C54: MEDUSIND SOLUTIONS | D54: TNMAS00497090000002652 | E54: 2016 | F54: Contribution | G54: 42565 | H54: Cont. For Due-Month 072016 | I54: 14039 | J54: 14039 | K54: 1685 | L54: 516 | M54: 1169
A55: Kurinji Malar Paranthaman | B55: 1.00649E+11 | C55: MEDUSIND SOLUTIONS | D55: TNMAS00497090000002652 | E55: 2016 | F55: Contribution | G55: 42593 | H55: Cont. For Due-Month 082016 | I55: 14039 | J55: 14039 | K55: 1685 | L55: 516 | M55: 1169
A56: Kurinji Malar Paranthaman | B56: 1.00649E+11 | C56: MEDUSIND SOLUTIONS | D56: TNMAS00497090000002652 | E56: 2016 | F56: Contribution | G56: 42628 | H56: Cont. For Due-Month 092016 | I56: 14039 | J56: 14039 | K56: 1685 | L56: 516 | M56: 1169
A57: Kurinji Malar Paranthaman | B57: 1.00649E+11 | C57: MEDUSIND SOLUTIONS | D57: TNMAS00497090000002652 | E57: 2016 | F57: Contribution | G57: 42656 | H57: Cont. For Due-Month 102016 | I57: 13805 | J57: 13805 | K57: 1657 | L57: 507 | M57: 1150
A58: Kurinji Malar Paranthaman | B58: 1.00649E+11 | C58: MEDUSIND SOLUTIONS | D58: TNMAS00497090000002652 | E58: 2016 | F58: Contribution | G58: 42689 | H58: Cont. For Due-Month 112016 | I58: 14039 | J58: 14039 | K58: 1685 | L58: 516 | M58: 1169
A59: Kurinji Malar Paranthaman | B59: 1.00649E+11 | C59: MEDUSIND SOLUTIONS | D59: TNMAS00497090000002652 | E59: 2016 | F59: Contribution | G59: 42718 | H59: Cont. For Due-Month 122016 | I59: 15000 | J59: 15000 | K59: 1800 | L59: 550 | M59: 1250
A60: Kurinji Malar Paranthaman | B60: 1.00649E+11 | C60: MEDUSIND SOLUTIONS | D60: TNMAS00497090000002652 | E60: 2016 | F60: Contribution | G60: 42753 | H60: Cont. For Due-Month 012017 | I60: 15000 | J60: 15000 | K60: 1800 | L60: 550 | M60: 1250
A61: Kurinji Malar Paranthaman | B61: 1.00649E+11 | C61: MEDUSIND SOLUTIONS | D61: TNMAS00497090000002652 | E61: 2016 | F61: Contribution | G61: 42780 | H61: Cont. For Due-Month 022017 | I61: 15000 | J61: 15000 | K61: 1800 | L61: 550 | M61: 1250
A62: Kurinji Malar Paranthaman | B62: 1.00649E+11 | C62: MEDUSIND SOLUTIONS | D62: TNMAS00497090000002652 | E62: 2016 | F62: Contribution | G62: 42811 | H62: Cont. For Due-Month 032017 | I62: 15000 | J62: 15000 | K62: 1800 | L62: 550 | M62: 1250
A63: Kurinji Malar Paranthaman | B63: 1.00199E+11 | C63: NTT DATA INFORMATION PROCESSING SERVICES PVT LTD | D63: TNAMB00483530000020685 | E63: 2016 | F63: Interest | G63: 42825 | H63: Interest Updated | K63: 782 | L63: 239 | M63: 0
A64: Kurinji Malar Paranthaman | B64: 1.00199E+11 | C64: NTT DATA INFORMATION PROCESSING SERVICES PVT LTD | D64: TNAMB00483530000020685 | E64: 2016 | F64: Closing Balance | G64: 42825 | H64: Closing Balance | K64: 9817 | L64: 3006 | M64: 5235
A65: Kurinji Malar Paranthaman | B65: 1.00649E+11 | C65: MEDUSIND SOLUTIONS | D65: TNMAS00497090000002652 | E65: 2016 | F65: Interest | G65: 42825 | H65: Interest Updated | K65: 2053 | L65: 628 | M65: 0
A66: Kurinji Malar Paranthaman | B66: 1.00649E+11 | C66: MEDUSIND SOLUTIONS | D66: TNMAS00497090000002652 | E66: 2016 | F66: Closing Balance | G66: 42825 | H66: Closing Balance | K66: 37116 | L66: 11355 | M66: 24034
A67: Kurinji Malar Paranthaman | B67: 1.00564E+11 | C67: AGS HEALTH PVT LTD | D67: TNMAS00838510000003341 | E67: 2016 | F67: Interest | G67: 42825 | H67: Interest Updated | K67: 694 | L67: 213 | M67: 0
A68: Kurinji Malar Paranthaman | B68: 1.00564E+11 | C68: AGS HEALTH PVT LTD | D68: TNMAS00838510000003341 | E68: 2016 | F68: Closing Balance | G68: 42825 | H68: Closing Balance | K68: 8716 | L68: 2672 | M68: 5034
A69: Kurinji Malar Paranthaman | B69: 1.00649E+11 | C69: MEDUSIND SOLUTIONS | D69: TNMAS00497090000002652 | E69: 2017 | F69: Contribution | G69: 42835 | H69: Cont. For Due-Month 042017 | I69: 15000 | J69: 15000 | K69: 1800 | L69: 550 | M69: 1250
A70: Kurinji Malar Paranthaman | B70: 1.00649E+11 | C70: MEDUSIND SOLUTIONS | D70: TNMAS00497090000002652 | E70: 2017 | F70: Contribution | G70: 42866 | H70: Cont. For Due-Month 052017 | I70: 15000 | J70: 15000 | K70: 1800 | L70: 550 | M70: 1250
A71: Kurinji Malar Paranthaman | B71: 1.00649E+11 | C71: MEDUSIND SOLUTIONS | D71: TNMAS00497090000002652 | E71: 2017 | F71: Contribution | G71: 42900 | H71: Cont. For Due-Month 062017 | I71: 15000 | J71: 15000 | K71: 1800 | L71: 550 | M71: 1250
A72: Kurinji Malar Paranthaman | B72: 1.00649E+11 | C72: MEDUSIND SOLUTIONS | D72: TNMAS00497090000002652 | E72: 2017 | F72: Contribution | G72: 42928 | H72: Cont. For Due-Month 072017 | I72: 15000 | J72: 15000 | K72: 1800 | L72: 550 | M72: 1250
A73: Kurinji Malar Paranthaman | B73: 1.00649E+11 | C73: MEDUSIND SOLUTIONS | D73: TNMAS00497090000002652 | E73: 2017 | F73: Contribution | G73: 42958 | H73: Cont. For Due-Month 082017 | I73: 15000 | J73: 15000 | K73: 1800 | L73: 550 | M73: 1250
A74: Kurinji Malar Paranthaman | B74: 1.00649E+11 | C74: MEDUSIND SOLUTIONS | D74: TNMAS00497090000002652 | E74: 2017 | F74: Contribution | G74: 42993 | H74: Cont. For Due-Month 092017 | I74: 15000 | J74: 15000 | K74: 1800 | L74: 550 | M74: 1250
A75: Kurinji Malar Paranthaman | B75: 1.00649E+11 | C75: MEDUSIND SOLUTIONS | D75: TNMAS00497090000002652 | E75: 2017 | F75: Contribution | G75: 43025 | H75: Cont. For Due-Month 102017 | I75: 15000 | J75: 15000 | K75: 1800 | L75: 550 | M75: 1250
A76: Kurinji Malar Paranthaman | B76: 1.00649E+11 | C76: MEDUSIND SOLUTIONS | D76: TNMAS00497090000002652 | E76: 2017 | F76: Contribution | G76: 43054 | H76: Cont. For Due-Month 112017 | I76: 15000 | J76: 15000 | K76: 1800 | L76: 550 | M76: 1250
A77: Kurinji Malar Paranthaman | B77: 1.00649E+11 | C77: MEDUSIND SOLUTIONS | D77: TNMAS00497090000002652 | E77: 2017 | F77: Contribution | G77: 43084 | H77: Cont. For Due-Month 122017 | I77: 15000 | J77: 15000 | K77: 1800 | L77: 550 | M77: 1250
A78: Kurinji Malar Paranthaman | B78: 1.00649E+11 | C78: MEDUSIND SOLUTIONS | D78: TNMAS00497090000002652 | E78: 2017 | F78: Contribution | G78: 43105 | H78: Cont. For Due-Month 012018 | I78: 15000 | J78: 15000 | K78: 1800 | L78: 550 | M78: 1250
A79: Kurinji Malar Paranthaman | B79: 1.00649E+11 | C79: MEDUSIND SOLUTIONS | D79: TNMAS00497090000002652 | E79: 2017 | F79: Contribution | G79: 43145 | H79: Cont. For Due-Month 022018 | I79: 15000 | J79: 15000 | K79: 1800 | L79: 550 | M79: 1250
A80: Kurinji Malar Paranthaman | B80: 1.00649E+11 | C80: MEDUSIND SOLUTIONS | D80: TNMAS00497090000002652 | E80: 2017 | F80: Contribution | G80: 43173 | H80: Cont. For Due-Month 032018 | I80: 15000 | J80: 15000 | K80: 1800 | L80: 550 | M80: 1250
A81: Kurinji Malar Paranthaman | B81: 1.00199E+11 | C81: NTT DATA INFORMATION PROCESSING SERVICES PVT LTD | D81: TNAMB00483530000020685 | E81: 2017 | F81: Interest | G81: 43190 | H81: Interest Updated | K81: 839 | L81: 257 | M81: 0
A82: Kurinji Malar Paranthaman | B82: 1.00199E+11 | C82: NTT DATA INFORMATION PROCESSING SERVICES PVT LTD | D82: TNAMB00483530000020685 | E82: 2017 | F82: Closing Balance | G82: 43190 | H82: Closing Balance | K82: 10656 | L82: 3263 | M82: 5235
A83: Kurinji Malar Paranthaman | B83: 1.00649E+11 | C83: MEDUSIND SOLUTIONS | D83: TNMAS00497090000002652 | E83: 2017 | F83: Interest | G83: 43190 | H83: Interest Updated | K83: 4020 | L83: 1229 | M83: 0
A84: Kurinji Malar Paranthaman | B84: 1.00649E+11 | C84: MEDUSIND SOLUTIONS | D84: TNMAS00497090000002652 | E84: 2017 | F84: Closing Balance | G84: 43190 | H84: Closing Balance | K84: 62736 | L84: 19184 | M84: 39034
A85: Kurinji Malar Paranthaman | B85: 1.00564E+11 | C85: AGS HEALTH PVT LTD | D85: TNMAS00838510000003341 | E85: 2017 | F85: Interest | G85: 43190 | H85: Interest Updated | K85: 745 | L85: 228 | M85: 0
A86: Kurinji Malar Paranthaman | B86: 1.00564E+11 | C86: AGS HEALTH PVT LTD | D86: TNMAS00838510000003341 | E86: 2017 | F86: Closing Balance | G86: 43190 | H86: Closing Balance | K86: 9461 | L86: 2900 | M86: 5034
A87: Kurinji Malar Paranthaman | B87: 1.00649E+11 | C87: MEDUSIND SOLUTIONS | D87: TNMAS00497090000002652 | E87: 2018 | F87: Contribution | G87: 43203 | H87: Cont. For Due-Month 042018 | I87: 15000 | J87: 15000 | K87: 1800 | L87: 550 | M87: 1250
A88: Kurinji Malar Paranthaman | B88: 1.00649E+11 | C88: MEDUSIND SOLUTIONS | D88: TNMAS00497090000002652 | E88: 2018 | F88: Contribution | G88: 43231 | H88: Cont. For Due-Month 052018 | I88: 15000 | J88: 15000 | K88: 1800 | L88: 550 | M88: 1250
A89: Kurinji Malar Paranthaman | B89: 1.00649E+11 | C89: MEDUSIND SOLUTIONS | D89: TNMAS00497090000002652 | E89: 2018 | F89: Contribution | G89: 43262 | H89: Cont. For Due-Month 062018 | I89: 15000 | J89: 15000 | K89: 1800 | L89: 550 | M89: 1250
A90: Kurinji Malar Paranthaman | B90: 1.00649E+11 | C90: MEDUSIND SOLUTIONS | D90: TNMAS00497090000002652 | E90: 2018 | F90: Contribution | G90: 43292 | H90: Cont. For Due-Month 072018 | I90: 15000 | J90: 15000 | K90: 1800 | L90: 550 | M90: 1250
A91: Kurinji Malar Paranthaman | B91: 1.00649E+11 | C91: MEDUSIND SOLUTIONS | D91: TNMAS00497090000002652 | E91: 2018 | F91: Contribution | G91: 43322 | H91: Cont. For Due-Month 082018 | I91: 15000 | J91: 15000 | K91: 1800 | L91: 550 | M91: 1250
A92: Kurinji Malar Paranthaman | B92: 1.00649E+11 | C92: MEDUSIND SOLUTIONS | D92: TNMAS00497090000002652 | E92: 2018 | F92: Contribution | G92: 43353 | H92: Cont. For Due-Month 092018 | I92: 15000 | J92: 15000 | K92: 1800 | L92: 550 | M92: 1250
A93: Kurinji Malar Paranthaman | B93: 1.00649E+11 | C93: MEDUSIND SOLUTIONS | D93: TNMAS00497090000002652 | E93: 2018 | F93: Contribution | G93: 43383 | H93: Cont. For Due-Month 102018 | I93: 15000 | J93: 15000 | K93: 1800 | L93: 550 | M93: 1250
A94: Kurinji Malar Paranthaman | B94: 1.00649E+11 | C94: MEDUSIND SOLUTIONS | D94: TNMAS00497090000002652 | E94: 2018 | F94: Contribution | G94: 43418 | H94: Cont. For Due-Month 112018 | I94: 15000 | J94: 15000 | K94: 1800 | L94: 550 | M94: 1250
A95: Kurinji Malar Paranthaman | B95: 1.00649E+11 | C95: MEDUSIND SOLUTIONS | D95: TNMAS00497090000002652 | E95: 2018 | F95: Contribution | G95: 43444 | H95: Cont. For Due-Month 122018 | I95: 15000 | J95: 15000 | K95: 1800 | L95: 550 | M95: 1250
A96: Kurinji Malar Paranthaman | B96: 1.00649E+11 | C96: MEDUSIND SOLUTIONS | D96: TNMAS00497090000002652 | E96: 2018 | F96: Contribution | G96: 43474 | H96: Cont. For Due-Month 012019 | I96: 15000 | J96: 15000 | K96: 1800 | L96: 550 | M96: 1250
A97: Kurinji Malar Paranthaman | B97: 1.00649E+11 | C97: MEDUSIND SOLUTIONS | D97: TNMAS00497090000002652 | E97: 2018 | F97: Contribution | G97: 43503 | H97: Cont. For Due-Month 022019 | I97: 15000 | J97: 15000 | K97: 1800 | L97: 550 | M97: 1250
A98: Kurinji Malar Paranthaman | B98: 1.00649E+11 | C98: MEDUSIND SOLUTIONS | D98: TNMAS00497090000002652 | E98: 2018 | F98: Contribution | G98: 43532 | H98: Cont. For Due-Month 032019 | I98: 3534 | J98: 3534 | K98: 424 | L98: 130 | M98: 294
A99: Kurinji Malar Paranthaman | B99: 1.00199E+11 | C99: NTT DATA INFORMATION PROCESSING SERVICES PVT LTD | D99: TNAMB00483530000020685 | E99: 2018 | F99: Interest | G99: 43555 | H99: Interest Updated | K99: 922 | L99: 282 | M99: 0
A100: Kurinji Malar Paranthaman | B100: 1.00199E+11 | C100: NTT DATA INFORMATION PROCESSING SERVICES PVT LTD | D100: TNAMB00483530000020685 | E100: 2018 | F100: Closing Balance | G100: 43555 | H100: Closing Balance | K100: 11578 | L100: 3545 | M100: 5235
A101: Kurinji Malar Paranthaman | B101: 1.00649E+11 | C101: MEDUSIND SOLUTIONS | D101: TNMAS00497090000002652 | E101: 2018 | F101: Closing Balance | G101: 43555 | H101: Closing Balance | K101: 89170 | L101: 27263 | M101: 53078
...

Sheet SSY
A1: Person | B1: Financial Year | C1: Date | D1: Particulars | E1: Amount | F1: Type
A2: Aarna Arun | B2: FY 2018 - 2019 | C2: 43555 | E2: 41000 | F2: Contribution
A3: Aarna Arun | B3: FY 2019 - 2020 | C3: 43921 | E3: 150000 | F3: Contribution
A4: Aarna Arun | B4: FY 2019 - 2020 | C4: 43921 | E4: 7645 | F4: Interest
A5: Aarna Arun | B5: FY 2020 - 2021 | C5: 44196 | E5: 80000 | F5: Contribution
A6: Aarna Arun | B6: FY 2020 - 2021 | C6: 44287 | E6: 19530 | F6: Interest
A7: Aarna Arun | B7: FY 2021 - 2022 | C7: 44409 | E7: 15000 | F7: Contribution
A8: Aarna Arun | B8: FY 2021 - 2022 | C8: 44288 | E8: 10000 | F8: Contribution
A9: Aarna Arun | B9: FY 2020 - 2021 | C9: 44198 | E9: 10000 | F9: Contribution
A10: Aarna Arun | B10: FY 2020 - 2021 | C10: 44229 | E10: 10000 | F10: Contribution
A11: Aarna Arun | B11: FY 2020 - 2021 | C11: 44253 | E11: 40000 | F11: Contribution
A12: Aarna Arun | B12: FY 2020 - 2021 | C12: 44257 | E12: 10000 | F12: Contribution
A13: Aarna Arun | B13: FY 2021 - 2022 | C13: 44440 | E13: 15000 | F13: Contribution
... A27: Aarna Arun | B27: FY2022-2023 | C27: 44805 | E27: 15000 | F27: Contribution
A28: Aarna Arun | B28: FY2025-2026 | C28: 45659 | D28: SI - From Account- 13041530002729 NET BANKING SI -ForAarnaSSY | E28: 15000 | F28: Contribution
A29: Aarna Arun | B29: FY2025-2026 | C29: 45690 | D29: SI - From Account- 13041530002729 NET BANKING SI -ForAarnaSSY | E29: 15000 | F29: Contribution
A30: Aarna Arun | B30: FY2025-2026 | C30: 45718 | D30: SI - From Account- 13041530002729 NET BANKING SI -ForAarnaSSY | E30: 15000 | F30: Contribution
A31: Aarna Arun | B31: FY2025-2026 | C31: 45747 | D31: Interest paid till 31-MAR-2025 | E31: 84720 | F31: Interest

Sheet NPS
A1: PRAN No | B1: Account Type | C1: Scheme Name | D1: Contribution Amount (Rs.) | E1: Units | F1: NAV | G1: Current Value | H1: Notional Gain/Loss | I1: XIRR
A2: '110113329811 | B2: Tier-I | C2: HDFC PENSION MANAGEMENT COMPANY LIMITED Equity - TIER I | D2: 119000 | E2: 2830.85 | F2: 56.1568 | G2: 158971.49
A3: '110113329811 | B3: Tier-I | C3: HDFC PENSION MANAGEMENT COMPANY LIMITED Corporate Bonds - TIER I | D3: 72000 | E3: 3119.39 | F3: 29.9296 | G3: 93362.11
A4: '110113329811 | B4: Tier-I | C4: HDFC PENSION MANAGEMENT COMPANY LIMITED Government Bond - TIER I | D4: 59000 | E4: 4462.99 | F4: 28.1029 | G4: 125422.92
A5: '110113329811 | B5: Tier-I | C5: Total | D5: 250000 | G5: 377756.53 | H5: 127756.53 | I5: 10.58
A6: '110113329811 | B6: Tier-II | C6: HDFC PENSION MANAGEMENT COMPANY LIMITED Corporate Bonds - TIER II | D6: 800 | E6: 90.62 | F6: 27.889 | G6: 2527.42
A7: '110113329811 | B7: Tier-II | C7: HDFC PENSION MANAGEMENT COMPANY LIMITED Government Bond - TIER II | D7: 1200 | E7: 170.64 | F7: 28.6706 | G7: 4892.23
A8: '110113329811 | B8: Tier-II | C8: HDFC PENSION MANAGEMENT COMPANY LIMITED Equity - TIER II | D8: 6000 | E8: 203.68 | F8: 48.5415 | G8: 9886.73
A9: '110113329811 | B9: Tier-II | C9: Total | D9: 8000 | G9: 17306.38 | H9: 9306.38 | I9: 13.12

Sheet NPS Transaction
A1: Person | B1: Account | C1: Pran | D1: Contribution Date | E1: Self Contribution | F1: Gross Contribution Amount | G1: Service Charges | H1: GST | I1: Net Contribution Amount | J1: Account Type
A2: Arun Venkatesan | B2: ICICI | C2: 110113329811 | D2: 43860 | E2: 15000 | F2: 15000 | G2: 37.5 | H2: 6.76 | I2: 15044.26 | J2: Tier-I
A3: Arun Venkatesan | B3: ICICI | C3: 110113329811 | D3: 43769 | E3: 15000 | F3: 15000 | G3: 37.5 | H3: 6.76 | I3: 15044.26 | J3: Tier-I
A4: Arun Venkatesan | B4: ICICI | C4: 110113329811 | D4: 43769 | E4: 4000 | F4: 4000 | G4: 20 | H4: 3.6 | I4: 4023.6 | J4: Tier-II
A5: Arun Venkatesan | B5: ICICI | C5: 110113329811 | D5: 43691 | E5: 20000 | F5: 20000 | G5: 250 | H5: 45 | I5: 20295 | J5: Tier-I
A6: Arun Venkatesan | B6: ICICI | C6: 110113329811 | D6: 43691 | E6: 4000 | F6: 4000 | G6: 20 | H6: 3.6 | I6: 4023.6 | J6: Tier-II
A7: Arun Venkatesan | B7: ICICI | C7: 110113329811 | D7: 44224 | E7: 50000 | F7: 50000 | G7: 125 | H7: 22.5 | I7: 50147.5 | J7: Tier-I
A8: Arun Venkatesan | B8: ICICI | C8: 110113329811 | D8: 44561 | E8: 50000 | F8: 50000 | G8: 125 | H8: 22.5 | I8: 50147.5 | J8: Tier-I
A9: Arun Venkatesan | B9: ICICI | C9: 110113329811 | D9: 44928 | E9: 50000 | F9: 50000 | G9: 250 | H9: 45 | I9: 50295 | J9: Tier-I
A10: Arun Venkatesan | B10: ICICI | C10: 110113329811 | D10: 45317 | E10: 50000 | F10: 50000 | G10: 250 | H10: 45 | I10: 50295 | J10: Tier-I

Sheet Bond
A1: Person | B1: Account | C1: Date | D1: Type | E1: Scheme | F1: Particulars | G1: Rate of Interest | H1: Amount | I1: Marutiry Date
A2: Arun Venkatesan | B2: ICICI | C2: 44120 | D2: Contribution | E2: Sovereign Gold Bond 2020-21 | G2: 0.025 | H2: 100020 | I2: 47046
A3: Arun Venkatesan | B3: ICICI | C3: 44126 | D3: Contribution | E3: Floating Rate Savings Bonds, 2020 | G3: 0.075 | H3: 100000 | I3: 46682
A4: Arun Venkatesan | B4: ICICI | C4: 44134 | D4: Contribution | E4: Muthoot Fincorp Limited | G4: 0.0915 | H4: 200000
A5: Arun Venkatesan | B5: ICICI | C5: 44166 | D5: Interest | E5: Muthoot Fincorp Limited | F5: NEFT-000302541722-MUTHOOT FINCORP LTD NCD II 7246- | H5: 1655
A6: Arun Venkatesan | B6: ICICI | C6: 44197 | D6: Interest | E6: Muthoot Fincorp Limited | F6: NEFT-000310270945-MUTHOOT FINCORP LTD NCD II 7246- | H6: 1554
A7: Arun Venkatesan | B7: ICICI | C7: 44228 | D7: Interest | E7: Muthoot Fincorp Limited | F7: NEFT-000317437097-MUTHOOT FINCORP LTD NCD II 7246- | H7: 1554
A8: Arun Venkatesan | B8: ICICI | C8: 44256 | D8: Interest | E8: Muthoot Fincorp Limited | F8: NEFT-000324498387-MUTHOOT FINCORP LTD NCD II 7246- | H8: 1404
A9: Arun Venkatesan | B9: ICICI | C9: 44286 | D9: Interest | E9: Muthoot Fincorp Limited | F9: NEFT-000333190306-MUTHOOT FINCORP LTD NCD II 7246- | H9: 1554
A10: Arun Venkatesan | B10: ICICI | C10: 44316 | D10: Interest | E10: Muthoot Fincorp Limited | F10: NEFT-000340206597-MUTHOOT FINCORP LTD NCD II 7246- | H10: 1504
A11: Arun Venkatesan | B11: ICICI | C11: 44348 | D11: Interest | E11: Muthoot Fincorp Limited | F11: NEFT-000346845644-MUTHOOT FINCORP LTD NCD II 7246- | H11: 1554
A12: Arun Venkatesan | B12: ICICI | C12: 44378 | D12: Interest | E12: Muthoot Fincorp Limited | F12: NEFT-000352292183-MUTHOOT FINCORP LTD NCD II 7246- | H12: 1504
A13: Arun Venkatesan | B13: ICICI | C13: 44408 | D13: Interest | E13: Muthoot Fincorp Limited | F13: NEFT-000356639960-MUTHOOT FINCORP LTD NCD II 7246- | H13: 1554
A14: Arun Venkatesan | B14: ICICI | C14: 44440 | D14: Interest | E14: Muthoot Fincorp Limited | F14: NEFT-000360786403-MUTHOOT FINCORP LTD NCD II 7246- | H14: 1554
A15: Arun Venkatesan | B15: ICICI | C15: 44470 | D15: Interest | E15: Muthoot Fincorp Limited | F15: NEFT-000364722478-MUTHOOT FINCORP LTD NCD II 7246- | H15: 1504
A16: Arun Venkatesan | B16: ICICI | C16: 44501 | D16: Interest | E16: Muthoot Fincorp Limited | F16: NEFT-INDBN01114754253-MUTHOOT FINCORP LTD NCD II 7246-N MF7M102104155 ARUN | H16: 1554
... A68: Arun Venkatesan | B68: ICICI | C68: 45839 | D68: Interest | E68: Floating Rate Savings Bonds, 2020 | F68: Int on GOI BOND XXX109242 Tds:0. Int:4025 and TAX:0. | H68: 4025

Sheet Fixed Deposit

Sheet ESPP

Sheet Gold

Sheet Silver

Sheet Fixed Assets

Sheet Loan
